Workbook

Sheet LEIA-ME
A1: Simples GRC — Planilha do portal (mesma sequência do roadmap)
A2: Todos os dados vêm do portal HTML. Premissas próprias estão sinalizadas em RISCO_PARAMETROS (azul sobre amarelo). Gerada em 03/10/2026.
A4: Aba | B4: Etapa do portal | C4: Conteúdo | D4: Nº de itens
A5: TOTAIS | B5: Resumo | C5: Totais e checagens de todo o roadmap
A6: 0_PERFIL_108 | B6: Etapa 0 | C6: Perfil: quem é a empresa | D6: =COUNTA(0_PERFIL_108!A5:A112) -> 108
A7: I_ESSENCIAIS_10 | B7: Etapa I | C7: Pacto Essencial: 10 medidas mínimas | D7: =COUNTA(I_ESSENCIAIS_10!A5:A14) -> 10
A8: II_PACTO_80_ITENS | B8: Etapa II | C8: Pacto Completo: catálogo de 80 itens (11 + 69) | D8: =COUNTA(II_PACTO_80_ITENS!A5:A84) -> 80
A9: II_PACTO_COMPL_69 | B9: Etapa II | C9: Complemento do Pacto: 69 itens | D9: =COUNTA(II_PACTO_COMPL_69!A5:A73) -> 69
A10: II_PACTO_QPE_76 | B10: Etapa II | C10: QPE correlatas ao Pacto | D10: =COUNTA(II_PACTO_QPE_76!A5:A80) -> 76
A11: III_PROETICA_137 | B11: Etapa III | C11: Complemento do Pró-Ética | D11: =COUNTA(III_PROETICA_137!A5:A141) -> 137
A12: III_AREAS_CGU | B12: Etapa III | C12: 10 áreas, tetos e mínimo de 45% | D12: =COUNTA(III_AREAS_CGU!B5:B14) -> 10
A13: IV_ISO_COMPL_27 | B13: Etapa IV | C13: Complemento ISO 37301/37001 | D13: =COUNTA(IV_ISO_COMPL_27!A5:A31) -> 27
A14: IV_ISO_REAPROV_24 | B14: Etapa IV | C14: ISO reaproveitável | D14: =COUNTA(IV_ISO_REAPROV_24!A5:A28) -> 24
A15: AG_PERFIL_108 | B15: Agentes | C15: Agentes de verificação do Perfil | D15: =COUNTA(AG_PERFIL_108!A5:A112) -> 108
A16: AG_CONFORMIDADE_223 | B16: Agentes | C16: Agentes de verificação da Conformidade | D16: =COUNTA(AG_CONFORMIDADE_223!A5:A227) -> 223
A17: AG_ISO_51 | B17: Agentes | C17: Agentes de verificação ISO | D17: =COUNTA(AG_ISO_51!A5:A55) -> 51
A18: LIC_CHECKLIST_14133 | B18: Licitações | C18: Checagem com a Lei 14.133/2021 | D18: =COUNTA(LIC_CHECKLIST_14133!A5:A16) -> 12
A19: LIC_PERGUNTAS | B19: Licitações | C19: Perguntas relevantes para licitações | D19: =COUNTA(LIC_PERGUNTAS!A5:A23) -> 19
A20: CONF_MATRIZ_108 | B20: Conflitos | C20: Matriz de conflitos Perfil × Conformidade | D20: =COUNTA(CONF_MATRIZ_108!A5:A112) -> 108
A21: CONF_REGRAS_42 | B21: Conflitos | C21: Regras de conflito | D21: =COUNTA(CONF_REGRAS_42!A5:A46) -> 42
A22: CONF_DEPENDENCIAS_23 | B22: Conflitos | C22: Regras de dependência | D22: =COUNTA(CONF_DEPENDENCIAS_23!A5:A27) -> 23
A23: RISCO_PARAMETROS | B23: Riscos | C23: Premissas editáveis (meta, apetite, capacidade, datas)
A24: RISCO_MATRIZ_17 | B24: Riscos | C24: Matriz de risco P×I (editável) | D24: =COUNTA(RISCO_MATRIZ_17!A5:A21) -> 17
A25: RISCO_ESTRESSE | B25: Riscos | C25: 5 cenários de estresse | D25: =COUNTA(RISCO_ESTRESSE!A5:A9) -> 5
A26: RISCO_SIMULADOR | B26: Riscos | C26: Simulador de probabilidade × impacto | D26: =COUNTA(RISCO_SIMULADOR!A6:A22) -> 17
A27: RISCO_MAPA_CALOR | B27: Riscos | C27: Mapa de calor base × simulado
A28: SIM_PROETICA | B28: Riscos | C28: Simulador da pontuação Pró-Ética (70 pts e 45%)
A29: PMO_BIBLIOTECA_25 | B29: PMO | C29: Biblioteca de ações | D29: =COUNTA(PMO_BIBLIOTECA_25!A5:A29) -> 25
A30: PMO_PLANO | B30: PMO | C30: Quadro do PMO | D30: =COUNTIF(PMO_PLANO!D10:D44,"?*") -> 25
A31: PMO_COMITE | B31: PMO | C31: Prioridades de remediação para o Comitê de Sócios | D31: =COUNTA(PMO_COMITE!B5:B29) -> 25
A32: LEG_ART57 | B32: Legislação | C32: Decreto 11.129/2022, art. 57 × perguntas | D32: =COUNTA(LEG_ART57!A22:A244) -> 223
A33: LEG_LEGISLACAO | B33: Legislação | C33: Legislação, guias e regras que sustentam o portal | D33: =COUNTA(LEG_LEGISLACAO!A5:A34) -> 30
A35: Como usar: ajuste RISCO_PARAMETROS; edite P e I em RISCO_MATRIZ_17; ligue cenários em RISCO_ESTRESSE; acompanhe o PMO_PLANO; informe o % atendido por área e marque ações (PMO_BIBLIOTECA_25, coluna S) em SIM_PROETICA.
A36: Células azuis sobre amarelo são editáveis; as demais são fórmulas ou dados do portal.
A37: Agentes: o portal configura os agentes por tipo de revisor, testes e critério; as abas AG_* materializam um agente por pergunta com essa configuração. Parecer é preliminar e a decisão é humana.
A38: Premissas que não vêm do portal: apetite de risco = 9, redução máxima de 1 ponto em P e em I por risco totalmente tratado, início do PMO em 05/10/2026 (RISCO_PARAMETROS).
A39: A pontuação simulada é estimativa de planejamento; não é nota nem homologação da CGU. As correspondências Pacto/Pró-Ética/ISO do portal não são homologadas.

Sheet TOTAIS
A1: Totais na sequência do portal: Perfil → Essenciais → Pacto → Pró-Ética → ISO → agentes → licitações → conflitos → riscos → PMO
A2: Todas as contagens são fórmulas sobre as abas de dados. A coluna Check deve mostrar OK.
A4: Etapa | B4: Item | C4: Perguntas / itens | D4: Pontos Pró-Ética | E4: Agentes | F4: Aba | G4: Check
A5: 0 · Perfil | B5: Perguntas de Perfil | C5: =COUNTA(0_PERFIL_108!A5:A112) -> 108 | E5: =COUNTA(AG_PERFIL_108!A5:A112) -> 108 | F5: 0_PERFIL_108 · AG_PERFIL_108 | G5: =IF(AND(C5=108,E5=108),"OK","REVISAR") -> OK
A6: I · Essenciais | B6: Conformidade: 10 Essenciais | C6: =COUNTA(I_ESSENCIAIS_10!A5:A14) -> 10 | D6: =SUM(I_ESSENCIAIS_10!G5:G14) -> 4.7 | E6: =COUNTIF(AG_CONFORMIDADE_223!$C$5:$C$227,"Essenciais") -> 10 | F6: I_ESSENCIAIS_10 | G6: =IF(AND(C6=10,E6=10),"OK","REVISAR") -> OK
A7: II · Pacto | B7: Conformidade: 76 QPE correlatas ao Pacto | C7: =COUNTA(II_PACTO_QPE_76!A5:A80) -> 76 | D7: =SUM(II_PACTO_QPE_76!G5:G80) -> 35.5 | E7: =COUNTIF(AG_CONFORMIDADE_223!$C$5:$C$227,"Pacto Brasil") -> 76 | F7: II_PACTO_QPE_76 | G7: =IF(AND(C7=76,E7=76),"OK","REVISAR") -> OK
A8: III · Pró-Ética | B8: Conformidade: 137 complementares | C8: =COUNTA(III_PROETICA_137!A5:A141) -> 137 | D8: =SUM(III_PROETICA_137!G5:G141) -> 59.8 | E8: =COUNTIF(AG_CONFORMIDADE_223!$C$5:$C$227,"Pró-Ética") -> 137 | F8: III_PROETICA_137 | G8: =IF(AND(C8=137,E8=137),"OK","REVISAR") -> OK
A9: Conformidade | B9: TOTAL da Conformidade (10 + 76 + 137) | C9: =SUM(C6:C8) -> 223 | D9: =SUM(D6:D8) -> 100 | E9: =SUM(E6:E8) -> 223 | F9: AG_CONFORMIDADE_223 | G9: =IF(AND(C9=223,E9=223,ROUND(D9,2)=100),"OK","REVISAR") -> OK
A10: II · Pacto | B10: Pacto Completo: itens do catálogo | C10: =COUNTA(II_PACTO_80_ITENS!A5:A84) -> 80 | F10: II_PACTO_80_ITENS | G10: =IF(C10=80,"OK","REVISAR") -> OK
A11: II · Pacto | B11: reaproveitáveis das Essenciais | C11: =COUNTIF(II_PACTO_80_ITENS!H5:H84,"Reaproveitável*") -> 11 | F11: II_PACTO_80_ITENS | G11: =IF(C11=11,"OK","REVISAR") -> OK
A12: II · Pacto | B12: complementos | C12: =COUNTA(II_PACTO_COMPL_69!A5:A73) -> 69 | F12: II_PACTO_COMPL_69 | G12: =IF(AND(C12=69,C11+C12=C10),"OK","REVISAR") -> OK
A13: IV · ISO | B13: Complemento ISO (parcial ou não previsto) | C13: =COUNTA(IV_ISO_COMPL_27!A5:A31) -> 27 | F13: IV_ISO_COMPL_27 | G13: =IF(C13=27,"OK","REVISAR") -> OK
A14: IV · ISO | B14: ISO reaproveitável (coberto pela CGU) | C14: =COUNTA(IV_ISO_REAPROV_24!A5:A28) -> 24 | F14: IV_ISO_REAPROV_24 | G14: =IF(C14=24,"OK","REVISAR") -> OK
A15: IV · ISO | B15: TOTAL ISO 37301/37001 | C15: =C13+C14 -> 51 | E15: =COUNTA(AG_ISO_51!A5:A55) -> 51 | F15: AG_ISO_51 | G15: =IF(AND(C15=51,E15=51),"OK","REVISAR") -> OK
A16: Licitações | B16: Checklist Lei 14.133/2021 | C16: =COUNTA(LIC_CHECKLIST_14133!A5:A16) -> 12 | F16: LIC_CHECKLIST_14133 | G16: =IF(C16>0,"OK","REVISAR") -> OK
A17: Licitações | B17: Perguntas marcadas "Licitações" | C17: =COUNTA(LIC_PERGUNTAS!A5:A23) -> 19 | F17: LIC_PERGUNTAS | G17: =IF(C17>0,"OK","REVISAR") -> OK
A18: Conflitos | B18: Agentes de conflito Perfil × Conformidade | C18: =COUNTA(CONF_MATRIZ_108!A5:A112) -> 108 | E18: =COUNTA(CONF_MATRIZ_108!A5:A112) -> 108 | F18: CONF_MATRIZ_108 | G18: =IF(C18=108,"OK","REVISAR") -> OK
A19: Conflitos | B19: Regras de conflito / dependência | C19: =COUNTA(CONF_REGRAS_42!A5:A46)&" / "&COUNTA(CONF_DEPENDENCIAS_23!A5:A27) -> 42 / 23 | F19: CONF_REGRAS_42 · CONF_DEPENDENCIAS_23
A20: Riscos | B20: Riscos na matriz (10 CGU + 7 ISO) | C20: =COUNTA(RISCO_MATRIZ_17!A5:A21) -> 17 | F20: RISCO_MATRIZ_17 | G20: =IF(C20=17,"OK","REVISAR") -> OK
A21: PMO | B21: Ações da biblioteca (18 CGU + 7 ISO) | C21: =COUNTA(PMO_BIBLIOTECA_25!A5:A29) -> 25 | F21: PMO_BIBLIOTECA_25 | G21: =IF(C21=25,"OK","REVISAR") -> OK
A22: Agentes | B22: TOTAL de agentes (Perfil + Conformidade + ISO + Conflitos) | E22: =E5+E9+E15+E18 -> 490 | F22: AG_* · CONF_MATRIZ_108
A24: Leitura: a Conformidade tem 223 perguntas = 10 Essenciais + 76 correlatas ao Pacto + 137 do Pró-Ética. O Pacto Completo tem 80 itens = 11 reaproveitáveis das Essenciais + 69 complementos (o item é reaproveitável quando seu QPE vinculado é uma Essencial). A ISO tem 51 requisitos = 27 complementos + 24 reaproveitáveis.

Sheet 0_PERFIL_108
A1: Etapa 0 · Perfil — 108 perguntas (quem é a empresa)
A2: Fonte: portal (DB.P). Agente = revisor de cada pergunta (detalhe na aba AG_PERFIL_108). Isos relacionadas: itens ISO que reaproveitam a resposta do Perfil.
A4: ID | B4: Grupo | C4: Pergunta | D4: Tipo de resposta | E4: Pergunta-pai (condição) | F4: Aplicável? | G4: Obrigatória? | H4: Evidência sugerida | I4: Agente | J4: Tipo de verificação | K4: Itens ISO relacionados
A5: DB1 | B5: Dados básicos | C5: Razão social registrada no CNPJ. | D5: text | F5: Sim | G5: Não | H5: Comprovante de inscrição e situação cadastral no CNPJ; ato societário ou histórico de alterações apenas para a informação societária solicitada. | I5: AG-PERF-DB1 | J5: CADASTRAL_REGULARIDADE
A6: DB2 | B6: Dados básicos | C6: Nome fantasia; informe não se aplica caso inexistente. | D6: text | F6: Sim | G6: Não | H6: Comprovante de inscrição e situação cadastral no CNPJ; ato societário ou histórico de alterações apenas para a informação societária solicitada. | I6: AG-PERF-DB2 | J6: CADASTRAL_REGULARIDADE
A7: DB3 | B7: Dados básicos | C7: Houve mudança de razão social nos últimos três anos? | D7: yn | F7: Sim | G7: Não | H7: Comprovante de inscrição e situação cadastral no CNPJ; ato societário ou histórico de alterações apenas para a informação societária solicitada. | I7: AG-PERF-DB3 | J7: CADASTRAL_REGULARIDADE
A8: DB3.1 | B8: Dados básicos | C8: Descreva as mudanças de razão social e suas datas. | D8: long | E8: DB3 | F8: Sim | G8: Não | H8: Comprovante de inscrição e situação cadastral no CNPJ; ato societário ou histórico de alterações apenas para a informação societária solicitada. | I8: AG-PERF-DB3.1 | J8: CADASTRAL_REGULARIDADE
A9: DB4 | B9: Dados básicos | C9: E-mail institucional da área de integridade. | D9: email | F9: Sim | G9: Não | H9: Somente resposta declaratória, salvo documento previsto no enunciado ou solicitado no formulário oficial. | I9: AG-PERF-DB4 | J9: DADO_DECLARATORIO
A10: DB5 | B10: Dados básicos | C10: CNPJ da pessoa jurídica participante. | D10: cnpj | F10: Sim | G10: Não | H10: Comprovante de inscrição e situação cadastral no CNPJ; ato societário ou histórico de alterações apenas para a informação societária solicitada. | I10: AG-PERF-DB5 | J10: CADASTRAL_REGULARIDADE
A11: DB6 | B11: Dados básicos | C11: Nome do representante da empresa. | D11: text | F11: Sim | G11: Não | H11: Ato de representação ou indicação do representante, apenas para conferência interna do responsável indicado. | I11: AG-PERF-DB6 | J11: DADO_DECLARATORIO
A12: DB7 | B12: Dados básicos | C12: Cargo do representante. | D12: text | F12: Sim | G12: Não | H12: Ato de representação ou indicação do representante, apenas para conferência interna do responsável indicado. | I12: AG-PERF-DB7 | J12: DADO_DECLARATORIO
A13: DB8 | B13: Dados básicos | C13: E-mail institucional do representante. | D13: email | F13: Sim | G13: Não | H13: Somente resposta declaratória, salvo documento previsto no enunciado ou solicitado no formulário oficial. | I13: AG-PERF-DB8 | J13: DADO_DECLARATORIO
A14: DB9 | B14: Dados básicos | C14: Telefone do representante. | D14: tel | F14: Sim | G14: Não | H14: Somente resposta declaratória, salvo documento previsto no enunciado ou solicitado no formulário oficial. | I14: AG-PERF-DB9 | J14: DADO_DECLARATORIO
A15: DB10 | B15: Dados básicos | C15: E-mail restrito para esclarecimentos sigilosos à CGU. | D15: email | F15: Sim | G15: Não | H15: Somente resposta declaratória, salvo documento previsto no enunciado ou solicitado no formulário oficial. | I15: AG-PERF-DB10 | J15: DADO_DECLARATORIO
A16: EA1 | B16: Estrutura e atividade econômica | C16: Principal setor de atividade econômica da empresa (faixa CNAE). | D16: text | F16: Sim | G16: Não | H16: Cadastro CNPJ e/ou ato constitutivo que identifique o setor, a atividade, a natureza societária ou a sede perguntada. | I16: AG-PERF-EA1 | J16: CADASTRAL_REGULARIDADE | K16: ISO-01
A17: EA2 | B17: Estrutura e atividade econômica | C17: CNAE principal, com sete dígitos. | D17: cnae | F17: Sim | G17: Não | H17: Cadastro CNPJ e/ou ato constitutivo que identifique o setor, a atividade, a natureza societária ou a sede perguntada. | I17: AG-PERF-EA2 | J17: CADASTRAL_REGULARIDADE
A18: EA3 | B18: Estrutura e atividade econômica | C18: Demais atividades econômicas desempenhadas. | D18: long | F18: Sim | G18: Não | H18: Cadastro CNPJ e/ou ato constitutivo que identifique o setor, a atividade, a natureza societária ou a sede perguntada. | I18: AG-PERF-EA3 | J18: CADASTRAL_REGULARIDADE | K18: ISO-01
A19: EA4 | B19: Estrutura e atividade econômica | C19: Tipo organizacional ou societário. | D19: text | F19: Sim | G19: Não | H19: Cadastro CNPJ e/ou ato constitutivo que identifique o setor, a atividade, a natureza societária ou a sede perguntada. | I19: AG-PERF-EA4 | J19: CADASTRAL_REGULARIDADE
A20: EA5 | B20: Estrutura e atividade econômica | C20: Porte da empresa segundo o faturamento anual. | D20: porte | F20: Sim | G20: Não | H20: Demonstração contábil ou apuração do faturamento no período-base que sustente a faixa informada. | I20: AG-PERF-EA5 | J20: DADO_QUANTITATIVO | K20: ISO-01
A21: EA6 | B21: Estrutura e atividade econômica | C21: Faixa do faturamento anual da empresa. | D21: text | F21: Sim | G21: Não | H21: Demonstração contábil ou apuração do faturamento no período-base que sustente a faixa informada. | I21: AG-PERF-EA6 | J21: DADO_QUANTITATIVO
A22: EA7 | B22: Estrutura e atividade econômica | C22: A empresa tem capital aberto? | D22: yn | F22: Sim | G22: Não | H22: Cadastro CNPJ e/ou ato constitutivo que identifique o setor, a atividade, a natureza societária ou a sede perguntada. | I22: AG-PERF-EA7 | J22: CADASTRAL_REGULARIDADE
A23: EA8 | B23: Estrutura e atividade econômica | C23: Unidades da Federação em que a empresa atua. | D23: long | F23: Sim | G23: Não | H23: Somente resposta declaratória, salvo documento previsto no enunciado ou solicitado no formulário oficial. | I23: AG-PERF-EA8 | J23: DADO_DECLARATORIO | K23: ISO-01; ISO-04
A24: EA9 | B24: Estrutura e atividade econômica | C24: Unidade da Federação da sede. | D24: uf | F24: Sim | G24: Não | H24: Cadastro CNPJ e/ou ato constitutivo que identifique o setor, a atividade, a natureza societária ou a sede perguntada. | I24: AG-PERF-EA9 | J24: CADASTRAL_REGULARIDADE
A25: EA10 | B25: Estrutura e atividade econômica | C25: A empresa atua fora do Brasil? | D25: yn | F25: Sim | G25: Não | H25: Ato societário, organograma do grupo ou instrumento da operação apenas se a situação descrita ocorreu. | I25: AG-PERF-EA10 | J25: DADO_DECLARATORIO | K25: ISO-01; ISO-06
A26: EA10.1 | B26: Estrutura e atividade econômica | C26: Países em que possui operações. | D26: long | E26: EA10 | F26: Sim | G26: Não | H26: Ato societário, organograma do grupo ou instrumento da operação apenas se a situação descrita ocorreu. | I26: AG-PERF-EA10.1 | J26: DADO_DECLARATORIO
A27: EA10.2 | B27: Estrutura e atividade econômica | C27: Legislação anticorrupção estrangeira aplicável às operações. | D27: long | E27: EA10 | F27: Sim | G27: Não | H27: Ato societário, organograma do grupo ou instrumento da operação apenas se a situação descrita ocorreu. | I27: AG-PERF-EA10.2 | J27: DADO_DECLARATORIO
A28: EA11 | B28: Estrutura e atividade econômica | C28: Possui subsidiárias em outros países? | D28: yn | F28: Sim | G28: Não | H28: Ato societário, organograma do grupo ou instrumento da operação apenas se a situação descrita ocorreu. | I28: AG-PERF-EA11 | J28: DADO_DECLARATORIO
A29: EA12 | B29: Estrutura e atividade econômica | C29: Integra grupo econômico? | D29: yn | F29: Sim | G29: Não | H29: Ato societário, organograma do grupo ou instrumento da operação apenas se a situação descrita ocorreu. | I29: AG-PERF-EA12 | J29: DADO_DECLARATORIO | K29: ISO-01; ISO-03; ISO-04
A30: EA12.1 | B30: Estrutura e atividade econômica | C30: Nome do grupo econômico. | D30: text | E30: EA12 | F30: Sim | G30: Não | H30: Ato societário, organograma do grupo ou instrumento da operação apenas se a situação descrita ocorreu. | I30: AG-PERF-EA12.1 | J30: DADO_DECLARATORIO
A31: EA12.2 | B31: Estrutura e atividade econômica | C31: Empresas do grupo cobertas pelo programa de integridade. | D31: long | E31: EA12 | F31: Sim | G31: Não | H31: Ato societário, organograma do grupo ou instrumento da operação apenas se a situação descrita ocorreu. | I31: AG-PERF-EA12.2 | J31: DADO_DECLARATORIO | K31: ISO-04
A32: EA12.3 | B32: Estrutura e atividade econômica | C32: Posição societária da empresa no grupo e principais integrantes e países. | D32: long | E32: EA12 | F32: Sim | G32: Não | H32: Ato societário, organograma do grupo ou instrumento da operação apenas se a situação descrita ocorreu. | I32: AG-PERF-EA12.3 | J32: DADO_DECLARATORIO
A33: EA13 | B33: Estrutura e atividade econômica | C33: Estrutura organizacional, órgãos e linhas de reporte. | D33: long | F33: Sim | G33: Não | H33: Organograma ou documento organizacional vigente, se disponível. | I33: AG-PERF-EA13 | J33: DADO_DECLARATORIO | K33: ISO-01
A34: EA14 | B34: Estrutura e atividade econômica | C34: Houve fusões, aquisições ou outras operações societárias entre 2022 e 2025? | D34: yn | F34: Sim | G34: Não | H34: Ato societário, organograma do grupo ou instrumento da operação apenas se a situação descrita ocorreu. | I34: AG-PERF-EA14 | J34: DADO_DECLARATORIO
A35: EA14.1 | B35: Estrutura e atividade econômica | C35: Detalhes e datas das operações societárias realizadas entre 2022 e 2025. | D35: long | E35: EA14 | F35: Sim | G35: Não | H35: Ato societário, organograma do grupo ou instrumento da operação apenas se a situação descrita ocorreu. | I35: AG-PERF-EA14.1 | J35: GOVERNANCA
A36: EA15 | B36: Estrutura e atividade econômica | C36: Houve consórcios, joint ventures ou outras parcerias entre 2022 e 2025? | D36: yn | F36: Sim | G36: Não | H36: Ato societário, organograma do grupo ou instrumento da operação apenas se a situação descrita ocorreu. | I36: AG-PERF-EA15 | J36: DADO_DECLARATORIO
A37: EA15.1 | B37: Estrutura e atividade econômica | C37: Descreva as parcerias firmadas entre 2022 e 2025. | D37: long | E37: EA15 | F37: Sim | G37: Não | H37: Ato societário, organograma do grupo ou instrumento da operação apenas se a situação descrita ocorreu. | I37: AG-PERF-EA15.1 | J37: DADO_DECLARATORIO
A38: EA16 | B38: Estrutura e atividade econômica | C38: Total de colaboradores, incluindo terceirizados, aprendizes e estagiários. | D38: int | F38: Sim | G38: Não | H38: Relatório de pessoal ou quantitativo consolidado referente ao período declarado; sem nomes pessoais desnecessários. | I38: AG-PERF-EA16 | J38: DADO_DECLARATORIO
A39: EA17 | B39: Estrutura e atividade econômica | C39: Quantidade de colaboradores em funções gerenciais. | D39: int | F39: Sim | G39: Não | H39: Relatório de pessoal ou quantitativo consolidado referente ao período declarado; sem nomes pessoais desnecessários. | I39: AG-PERF-EA17 | J39: DADO_QUANTITATIVO
A40: EA18 | B40: Estrutura e atividade econômica | C40: Quantidade de colaboradores em funções administrativas. | D40: int | F40: Sim | G40: Não | H40: Relatório de pessoal ou quantitativo consolidado referente ao período declarado; sem nomes pessoais desnecessários. | I40: AG-PERF-EA18 | J40: DADO_QUANTITATIVO
A41: EA19 | B41: Estrutura e atividade econômica | C41: Quantidade de colaboradores em funções operacionais. | D41: int | F41: Sim | G41: Não | H41: Relatório de pessoal ou quantitativo consolidado referente ao período declarado; sem nomes pessoais desnecessários. | I41: AG-PERF-EA19 | J41: DADO_QUANTITATIVO
A42: EA20 | B42: Estrutura e atividade econômica | C42: Faixa percentual de trabalhadores operacionais com acesso à internet no trabalho. | D42: percent | F42: Sim | G42: Não | H42: Relatório de pessoal ou quantitativo consolidado referente ao período declarado; sem nomes pessoais desnecessários. | I42: AG-PERF-EA20 | J42: DADO_QUANTITATIVO
A43: IP1 | B43: Interação com o poder público | C43: Atividades sujeitas a regulação estatal? | D43: yn | F43: Sim | G43: Não | H43: Somente resposta declaratória, salvo documento previsto no enunciado ou solicitado no formulário oficial. | I43: AG-PERF-IP1 | J43: GOVERNANCA | K43: ISO-01; ISO-03; ISO-06
A44: IP1.1 | B44: Interação com o poder público | C44: Órgãos reguladores e respectivas atividades reguladas. | D44: long | E44: IP1 | F44: Sim | G44: Não | H44: Licença, permissão, autorização ou registro no órgão regulador correspondente somente para a atividade regulada informada. | I44: AG-PERF-IP1.1 | J44: DADO_DECLARATORIO
A45: IP2 | B45: Interação com o poder público | C45: Grau de dependência de licenças, permissões e autorizações governamentais. | D45: long | F45: Sim | G45: Não | H45: Licença, permissão, autorização ou registro no órgão regulador correspondente somente para a atividade regulada informada. | I45: AG-PERF-IP2 | J45: DADO_DECLARATORIO | K45: ISO-01
A46: IP3 | B46: Interação com o poder público | C46: Quais licenças, permissões ou autorizações governamentais são necessárias? | D46: long | F46: Sim | G46: Não | H46: Licença, permissão, autorização ou registro no órgão regulador correspondente somente para a atividade regulada informada. | I46: AG-PERF-IP3 | J46: DADO_DECLARATORIO | K46: ISO-06
A47: IP4 | B47: Interação com o poder público | C47: Perfil de participação da empresa em licitações públicas. | D47: long | F47: Sim | G47: Não | H47: Relação de licitações, contratos administrativos, concessões ou subcontratos aplicáveis ao período e à informação solicitada. | I47: AG-PERF-IP4 | J47: DADO_DECLARATORIO | K47: ISO-01; ISO-03
A48: IP5 | B48: Interação com o poder público | C48: Perfil de contratos celebrados com a Administração Pública. | D48: long | F48: Sim | G48: Não | H48: Relação de licitações, contratos administrativos, concessões ou subcontratos aplicáveis ao período e à informação solicitada. | I48: AG-PERF-IP5 | J48: DADO_DECLARATORIO | K48: ISO-01; ISO-03
A49: IP6 | B49: Interação com o poder público | C49: Faixa percentual do faturamento proveniente de contratos públicos vigentes. | D49: percent | F49: Sim | G49: Não | H49: Relação de licitações, contratos administrativos, concessões ou subcontratos aplicáveis ao período e à informação solicitada. | I49: AG-PERF-IP6 | J49: DADO_QUANTITATIVO | K49: ISO-01
A50: IP7 | B50: Interação com o poder público | C50: Entre 2022 e 2025, utilizou intermediários em interações com o poder público? | D50: yn | F50: Sim | G50: Não | H50: Relação dos intermediários e instrumentos contratuais das interações declaradas, se existentes. | I50: AG-PERF-IP7 | J50: DADO_DECLARATORIO
A51: IP7.1 | B51: Interação com o poder público | C51: Detalhes dos intermediários, atividades, órgãos e período. | D51: long | E51: IP7 | F51: Sim | G51: Não | H51: Relação dos intermediários e instrumentos contratuais das interações declaradas, se existentes. | I51: AG-PERF-IP7.1 | J51: DADO_DECLARATORIO
A52: IP8 | B52: Interação com o poder público | C52: Entre 2022 e 2025, subcontratou atividades de contratos administrativos? | D52: yn | F52: Sim | G52: Não | H52: Relação de licitações, contratos administrativos, concessões ou subcontratos aplicáveis ao período e à informação solicitada. | I52: AG-PERF-IP8 | J52: DADO_DECLARATORIO
A53: IP8.1 | B53: Interação com o poder público | C53: Detalhes das subcontratações, contratos e terceiros envolvidos. | D53: long | E53: IP8 | F53: Sim | G53: Não | H53: Relação de licitações, contratos administrativos, concessões ou subcontratos aplicáveis ao período e à informação solicitada. | I53: AG-PERF-IP8.1 | J53: GOVERNANCA
A54: IP9 | B54: Interação com o poder público | C54: É concessionária ou permissionária de serviço público? | D54: yn | F54: Sim | G54: Não | H54: Relação de licitações, contratos administrativos, concessões ou subcontratos aplicáveis ao período e à informação solicitada. | I54: AG-PERF-IP9 | J54: DADO_DECLARATORIO
A55: IP9.1 | B55: Interação com o poder público | C55: Faixa percentual de receita relacionada a concessões ou permissões vigentes. | D55: percent | E55: IP9 | F55: Sim | G55: Não | H55: Relação de licitações, contratos administrativos, concessões ou subcontratos aplicáveis ao período e à informação solicitada. | I55: AG-PERF-IP9.1 | J55: DADO_QUANTITATIVO
A56: IP10 | B56: Interação com o poder público | C56: Usufruiu de incentivos ou benefícios fiscais entre 2022 e 2025? | D56: yn | F56: Sim | G56: Não | H56: Ato concessivo do benefício e demonstrativo do valor/período, apenas quando houver benefício declarado. | I56: AG-PERF-IP10 | J56: DADO_DECLARATORIO
A57: IP10.1 | B57: Interação com o poder público | C57: Detalhes dos benefícios fiscais, fundamento, valores e período. | D57: long | E57: IP10 | F57: Sim | G57: Não | H57: Ato concessivo do benefício e demonstrativo do valor/período, apenas quando houver benefício declarado. | I57: AG-PERF-IP10.1 | J57: DADO_DECLARATORIO
A58: DP1 | B58: Doações e patrocínios | C58: Efetuou patrocínios esportivos ou culturais entre 2022 e 2025? | D58: yn | F58: Sim | G58: Não | H58: Relação, contrato e comprovante do patrocínio ocorrido; ato concessivo somente se declarado uso de incentivo fiscal. | I58: AG-PERF-DP1 | J58: DADO_DECLARATORIO | K58: ISO-37
A59: DP1.1 | B59: Doações e patrocínios | C59: Algum patrocínio se beneficiou de incentivo fiscal? | D59: yn | E59: DP1 | F59: Sim | G59: Não | H59: Relação, contrato e comprovante do patrocínio ocorrido; ato concessivo somente se declarado uso de incentivo fiscal. | I59: AG-PERF-DP1.1 | J59: DADO_DECLARATORIO
A60: DP1.2 | B60: Doações e patrocínios | C60: Descreva os patrocínios realizados, beneficiários, datas e incentivos fiscais. | D60: long | E60: DP1 | F60: Sim | G60: Não | H60: Relação, contrato e comprovante do patrocínio ocorrido; ato concessivo somente se declarado uso de incentivo fiscal. | I60: AG-PERF-DP1.2 | J60: GOVERNANCA
A61: DP2 | B61: Doações e patrocínios | C61: Realizou doações filantrópicas entre 2022 e 2025? | D61: yn | F61: Sim | G61: Não | H61: Relação de doações realizadas e respectivos comprovantes ou instrumentos, se ocorreram no período. | I61: AG-PERF-DP2 | J61: DADO_DECLARATORIO | K61: ISO-37
A62: DP2.1 | B62: Doações e patrocínios | C62: Informe os destinatários, a finalidade e os procedimentos das doações. | D62: long | E62: DP2 | F62: Sim | G62: Não | H62: Relação de doações realizadas e respectivos comprovantes ou instrumentos, se ocorreram no período. | I62: AG-PERF-DP2.1 | J62: NORMATIVO
A63: PI1 | B63: Programa de integridade | C63: Ano de formalização do programa de integridade. | D63: int | F63: Sim | G63: Não | H63: Ato de instituição do programa, organograma ou registros da equipe pertinentes à informação perguntada. | I63: AG-PERF-PI1 | J63: DADO_DECLARATORIO | K63: ISO-05
A64: PI2 | B64: Programa de integridade | C64: Organização, composição e reporte hierárquico da área de integridade. | D64: long | F64: Sim | G64: Não | H64: Ato de instituição do programa, organograma ou registros da equipe pertinentes à informação perguntada. | I64: AG-PERF-PI2 | J64: DADO_DECLARATORIO | K64: ISO-05
A65: PI3 | B65: Programa de integridade | C65: Quantidade de colaboradores dedicados exclusivamente à integridade. | D65: int | F65: Sim | G65: Não | H65: Ato de instituição do programa, organograma ou registros da equipe pertinentes à informação perguntada. | I65: AG-PERF-PI3 | J65: DADO_QUANTITATIVO
A66: PI4 | B66: Programa de integridade | C66: Representantes de integridade nas UFs em que a empresa atua e sua atuação. | D66: long | F66: Sim | G66: Não | H66: Ato de instituição do programa, organograma ou registros da equipe pertinentes à informação perguntada. | I66: AG-PERF-PI4 | J66: DADO_DECLARATORIO
A67: PI5 | B67: Programa de integridade | C67: Principais riscos de integridade identificados para a empresa. | D67: long | F67: Sim | G67: Não | H67: Matriz ou relatório de riscos de integridade referente ao período declarado. | I67: AG-PERF-PI5 | J67: RISCOS_TERCEIROS | K67: ISO-07
A68: PI6 | B68: Programa de integridade | C68: Houve denúncias de fraude ou corrupção entre 2023 e 2025? | D68: yn | F68: Sim | G68: Não | H68: Relatório agregado do canal correspondente e registros de providências, se houve casos; preservar sigilo de denunciantes e dados pessoais. | I68: AG-PERF-PI6 | J68: DADO_DECLARATORIO
A69: PI7 | B69: Programa de integridade | C69: Houve denúncias de discriminação ou assédio entre 2023 e 2025? | D69: yn | F69: Sim | G69: Não | H69: Relatório agregado do canal correspondente e registros de providências, se houve casos; preservar sigilo de denunciantes e dados pessoais. | I69: AG-PERF-PI7 | J69: DADO_DECLARATORIO
A70: PI8 | B70: Programa de integridade | C70: Houve denúncias de infração ambiental entre 2023 e 2025? | D70: yn | F70: Sim | G70: Não | H70: Relatório agregado do canal correspondente e registros de providências, se houve casos; preservar sigilo de denunciantes e dados pessoais. | I70: AG-PERF-PI8 | J70: DADO_DECLARATORIO
A71: PI9 | B71: Programa de integridade | C71: A empresa participou de edições anteriores do Pró-Ética? | D71: yn | F71: Sim | G71: Não | H71: Comprovante da participação, relatório de edição anterior ou certificado da distinção informada, quando existente. | I71: AG-PERF-PI9 | J71: DADO_DECLARATORIO
A72: PI9.1 | B72: Programa de integridade | C72: Edições anteriores efetivamente avaliadas e respectivos relatórios. | D72: long | E72: PI9 | F72: Sim | G72: Não | H72: Comprovante da participação, relatório de edição anterior ou certificado da distinção informada, quando existente. | I72: AG-PERF-PI9.1 | J72: DADO_DECLARATORIO
A73: PI10 | B73: Programa de integridade | C73: Recebeu reconhecimento em ética, integridade ou sustentabilidade nos últimos dois anos? | D73: yn | F73: Sim | G73: Não | H73: Comprovante da participação, relatório de edição anterior ou certificado da distinção informada, quando existente. | I73: AG-PERF-PI10 | J73: DADO_DECLARATORIO
A74: PI10.1 | B74: Programa de integridade | C74: Identifique os reconhecimentos e os anos correspondentes. | D74: long | E74: PI10 | F74: Sim | G74: Não | H74: Comprovante da participação, relatório de edição anterior ou certificado da distinção informada, quando existente. | I74: AG-PERF-PI10.1 | J74: DADO_DECLARATORIO
A75: PI11 | B75: Programa de integridade | C75: Há investigações, processos ou condenações da empresa relativos a corrupção, improbidade ou fraude licitatória nos últimos três anos? | D75: yn | F75: Sim | G75: Não | H75: Registro ou decisão pública pertinente e relato institucional das medidas, se houve caso; não exigir exposição de dados pessoais sigilosos. | I75: AG-PERF-PI11 | J75: DADO_DECLARATORIO
A76: PI11.1 | B76: Programa de integridade | C76: Contexto e respostas institucionais aos casos referentes à empresa. | D76: long | E76: PI11 | F76: Sim | G76: Não | H76: Registro ou decisão pública pertinente e relato institucional das medidas, se houve caso; não exigir exposição de dados pessoais sigilosos. | I76: AG-PERF-PI11.1 | J76: DADO_DECLARATORIO
A77: PI12 | B77: Programa de integridade | C77: Há casos dessa natureza envolvendo membro da alta direção nos últimos três anos? | D77: yn | F77: Sim | G77: Não | H77: Registro ou decisão pública pertinente e relato institucional das medidas, se houve caso; não exigir exposição de dados pessoais sigilosos. | I77: AG-PERF-PI12 | J77: GOVERNANCA
A78: PI12.1 | B78: Programa de integridade | C78: Medidas institucionais adotadas em relação aos casos envolvendo a alta direção. | D78: long | E78: PI12 | F78: Sim | G78: Não | H78: Registro ou decisão pública pertinente e relato institucional das medidas, se houve caso; não exigir exposição de dados pessoais sigilosos. | I78: AG-PERF-PI12.1 | J78: GOVERNANCA
A79: PI13 | B79: Programa de integridade | C79: A alta direção possui política de remuneração variável? | D79: yn | F79: Sim | G79: Não | H79: Norma de remuneração variável, somente se declarada existente. | I79: AG-PERF-PI13 | J79: GOVERNANCA
A80: PI14 | B80: Programa de integridade | C80: As atividades da empresa podem causar impactos ambientais? | D80: yn | F80: Sim | G80: Não | H80: Somente resposta declaratória, salvo documento previsto no enunciado ou solicitado no formulário oficial. | I80: AG-PERF-PI14 | J80: DADO_DECLARATORIO | K80: ISO-02
A81: PI14.1 | B81: Programa de integridade | C81: Fundamentação da conclusão de ausência de impactos ambientais. | D81: long | E81: PI14 | F81: Não | G81: Não | H81: Estudo ou justificativa técnica utilizada na conclusão declarada; não exigir licença que a pergunta não solicita. | I81: AG-PERF-PI14.1 | J81: DADO_DECLARATORIO
A82: PI15 | B82: Programa de integridade | C82: Há exposição significativa a riscos decorrentes das mudanças climáticas? | D82: yn | F82: Sim | G82: Não | H82: Somente resposta declaratória, salvo documento previsto no enunciado ou solicitado no formulário oficial. | I82: AG-PERF-PI15 | J82: RISCOS_TERCEIROS | K82: ISO-02
A83: PI15.1 | B83: Programa de integridade | C83: Fundamentação da conclusão de ausência de risco climático significativo. | D83: long | E83: PI15 | F83: Não | G83: Não | H83: Estudo ou justificativa técnica utilizada na conclusão declarada; não exigir licença que a pergunta não solicita. | I83: AG-PERF-PI15.1 | J83: RISCOS_TERCEIROS
A84: PI16 | B84: Programa de integridade | C84: Houve prejuízos causados por eventos climáticos nos últimos cinco anos? | D84: yn | F84: Sim | G84: Não | H84: Registro de perdas por evento climático, somente se ocorreu. | I84: AG-PERF-PI16 | J84: DADO_DECLARATORIO | K84: ISO-02
A85: PI16.1 | B85: Programa de integridade | C85: Descreva os prejuízos decorrentes de eventos climáticos. | D85: long | E85: PI16 | F85: Sim | G85: Não | H85: Registro de perdas por evento climático, somente se ocorreu. | I85: AG-PERF-PI16.1 | J85: DADO_DECLARATORIO
A86: PI17 | B86: Programa de integridade | C86: Há plano de transição para fontes renováveis e monitoramento do consumo de energia? | D86: yn | F86: Sim | G86: Não | H86: Plano de transição energética e relatórios de consumo, se a empresa declarar sua existência. | I86: AG-PERF-PI17 | J86: DADO_DECLARATORIO | K86: ISO-02
A87: PI17.1 | B87: Programa de integridade | C87: Descreva o plano de transição energética e o acompanhamento de energia. | D87: long | E87: PI17 | F87: Sim | G87: Não | H87: Plano de transição energética e relatórios de consumo, se a empresa declarar sua existência. | I87: AG-PERF-PI17.1 | J87: DADO_DECLARATORIO
A88: PI18 | B88: Programa de integridade | C88: Existe ouvidoria ou setor equivalente para consumidores e colaboradores? | D88: yn | F88: Sim | G88: Não | H88: Ato constitutivo ou regimento da ouvidoria, somente se existente ou expressamente solicitado. | I88: AG-PERF-PI18 | J88: NORMATIVO
A89: PI18.1 | B89: Programa de integridade | C89: Apresente documento formal que institua a ouvidoria ou setor equivalente. | D89: file | E89: PI18 | F89: Sim | G89: Sim | H89: Ato constitutivo ou regimento da ouvidoria, somente se existente ou expressamente solicitado. | I89: AG-PERF-PI18.1 | J89: NORMATIVO
A90: PI19 | B90: Programa de integridade | C90: Houve reclamação ou denúncia relacionada a direitos do consumidor entre 2023 e 2025? | D90: yn | F90: Sim | G90: Não | H90: Relatório agregado do canal correspondente e registros de providências, se houve casos; preservar sigilo de denunciantes e dados pessoais. | I90: AG-PERF-PI19 | J90: DADO_DECLARATORIO
A91: PI19.1 | B91: Programa de integridade | C91: Descreva as reclamações e as providências adotadas. | D91: long | E91: PI19 | F91: Sim | G91: Não | H91: Relatório agregado do canal correspondente e registros de providências, se houve casos; preservar sigilo de denunciantes e dados pessoais. | I91: AG-PERF-PI19.1 | J91: DADO_DECLARATORIO
A92: PI20 | B92: Programa de integridade | C92: Há política ou norma de diversidade e inclusão implementada? | D92: yn | F92: Sim | G92: Não | H92: Política ou norma de diversidade e inclusão aprovada, somente se existente ou expressamente solicitada.; Política de diversidade e inclusão (não integra automaticamente as 11 políticas essenciais). | I92: AG-PERF-PI20 | J92: NORMATIVO
A93: PI20.1 | B93: Programa de integridade | C93: Anexe a política ou norma de diversidade e inclusão aprovada. | D93: file | E93: PI20 | F93: Sim | G93: Sim | H93: Política ou norma de diversidade e inclusão aprovada, somente se existente ou expressamente solicitada.; Política de diversidade e inclusão (não integra automaticamente as 11 políticas essenciais). | I93: AG-PERF-PI20.1 | J93: NORMATIVO
A94: AD1 | B94: Admissibilidade | C94: Certidão fiscal federal RFB/PGFN, negativa ou positiva com efeitos de negativa, válida na submissão. | D94: file | F94: Sim | G94: Sim | H94: Certidão conjunta RFB/PGFN vigente no CNPJ da empresa. | I94: AG-PERF-AD1 | J94: CADASTRAL_REGULARIDADE
A95: AD2 | B95: Admissibilidade | C95: Certificado de Regularidade do FGTS vigente no envio do Perfil. | D95: file | F95: Sim | G95: Sim | H95: Certificado de Regularidade do FGTS vigente no CNPJ da empresa. | I95: AG-PERF-AD2 | J95: CADASTRAL_REGULARIDADE
A96: AD3 | B96: Admissibilidade | C96: Certidão Negativa de Débitos Trabalhistas ou positiva com efeito de negativa válida na submissão. | D96: file | F96: Sim | G96: Sim | H96: Certidão de débitos trabalhistas vigente emitida pelo órgão competente. | I96: AG-PERF-AD3 | J96: CADASTRAL_REGULARIDADE
A97: AD4 | B97: Admissibilidade | C97: Certidão Negativa de Débitos do Ibama válida na submissão. | D97: file | F97: Sim | G97: Sim | H97: Certidão de débitos do Ibama pertinente à empresa, conforme condição de admissibilidade da edição. | I97: AG-PERF-AD4 | J97: CADASTRAL_REGULARIDADE
A98: AD5 | B98: Admissibilidade | C98: A empresa não consta do CEIS? | D98: yn | F98: Sim | G98: Não | H98: Consulta atualizada à relação CEIS no CNPJ. | I98: AG-PERF-AD5 | J98: CADASTRAL_REGULARIDADE
A99: AD6 | B99: Admissibilidade | C99: A entidade está regular perante o CEPIM (quando aplicável)? | D99: ynna | F99: Sim | G99: Sim | H99: Consulta CEPIM somente quando o cadastro for aplicável à natureza da entidade. | I99: AG-PERF-AD6 | J99: DADO_DECLARATORIO
A100: AD7 | B100: Admissibilidade | C100: A empresa não consta do CNEP? | D100: yn | F100: Sim | G100: Não | H100: Consulta atualizada à relação CNEP no CNPJ. | I100: AG-PERF-AD7 | J100: CADASTRAL_REGULARIDADE
A101: AD8 | B101: Admissibilidade | C101: A empresa não consta da Lista Suja do Trabalho Escravo? | D101: yn | F101: Sim | G101: Não | H101: Consulta atualizada ao cadastro de empregadores referido na pergunta. | I101: AG-PERF-AD8 | J101: DADO_DECLARATORIO
...

Sheet I_ESSENCIAIS_10
A1: Etapa I · Pacto Essencial — 10 medidas mínimas (perguntas QPE próprias)
A2: Fonte: portal (DB.Q trilha Essenciais + DB.ESS). A coluna "Medida essencial" liga a pergunta ao item ITP e ao item do Pacto (PB).
A4: ID | B4: Nº formulário | C4: Trilha | D4: Área | E4: Pergunta | F4: Evidência sugerida | G4: Peso (pts) | H4: Agente | I4: Tipo de verificação | J4: Natureza | K4: Janela | L4: Itens do Pacto | M4: Itens ISO | N4: Incisos art. 57 | O4: Licitações? | P4: Medida essencial (ITP)
A5: QPE-006 | B5: 2.2 | C5: Essenciais | D5: Comprometimento da Alta Direção | E5: A alta direção da empresa supervisiona a implantação e a aplicação do programa de integridade, por meio do recebimento e avaliação de relatórios periódicos de acompanhamento das atividades relacionadas ao programa de integridade, inclusive de suas controladas/subsidiárias, quando for o caso? Se sim, indicar a forma e a periodicidade com que a alta direção participa da supervisão do programa de integridade, bem como descrever o tipo e o conteúdo dos documentos que lhe foram apresentados para subsidiar suas decisões. | F5: Documentos que indiquem a forma como a alta direção participou da supervisão da implantação e da aplicação do programa de integridade, tais como: − documentos que comprovem a frequência das ações de supervisão do programa pela alta direção; − atas de reuniões entre membros da alta direção e responsáveis pelas atividades do programa de integridade; − e-mails, apresentações feitas em reuniões, registros de frequência das ações de supervisão; − assinaturas de membros da alta direção em relatórios de atividades do programa de integridade. Inclua também, quando existente, a política ou norma interna de governança que formaliza o dever de supervisão da alta direção sobre o programa de integridade. | G5: 0.9 | H5: AG-FCG-QPE-006 | I5: GOVERNANCA | J5: Execução | K5: PERIODO | L5: 1.1; 2.2 | M5: ISO-08; ISO-44; ISO-47; ISO-48 | N5: I | P5: ITP-001 / PB-001
A6: QPE-024 | B6: 4.1 | C6: Essenciais | D6: Instância Responsável pelo Programa | E6: A empresa possui área específica ou pessoa responsável pela aplicação do programa de integridade? Se sim, informar a data em que a área foi instituída ou em que a pessoa responsável foi contratada/designada para a função, o currículo do atual responsável pela instância interna, o processo de seleção do atual responsável pela instância interna, e o órgão competente por sua contratação e eventual demissão. | F6: Documentos que comprovem a existência de uma instância interna (seja uma área ou pessoa designada) responsável pela implementação, fiscalização e monitoramento contínuo do programa de integridade no Brasil, tais como: políticas, regimento interno, estatuto, job description etc. Não serão considerados como área específica órgãos colegiados (comitês, conselhos etc.). Inclua também, quando existente, a política ou diretriz interna que formaliza as atribuições e a autonomia da instância responsável pelo programa (além do regimento/estatuto já solicitado). | G6: 1 | H6: AG-FCG-QPE-024 | I6: GOVERNANCA | J6: Desenho | K6: VIGENTE | L6: 4.1 | M6: ISO-14 | N6: IX | P6: ITP-002 / PB-009
A7: QPE-041 | B7: 6.2 | C7: Essenciais | D7: Gestão de Riscos para a Integridade | E7: No período avaliado, a empresa realizou análise de riscos para integridade, incluindo uma análise que contemple expressamente riscos relacionados a corrupção e fraude? (*Medida mínima prevista no art. 14 do Regulamento, de caráter obrigatório) | F7: Evidências da análise de riscos para integridade, relacionadas à corrupção e fraude, realizada pela própria empresa ou por terceiros,; POL-06 — Due Diligence de Terceiros Inclua também a política ou diretriz de gestão de riscos de integridade aplicável, quando existente, além da própria análise de riscos. | G7: 1 | H7: AG-FCG-QPE-041 | I7: RISCOS_TERCEIROS | J7: Execução | K7: PERIODO | L7: 5.1 | M7: ISO-07 | N7: V | P7: ITP-003 / PB-011
A8: QPE-051 | B8: 7.1 | C8: Essenciais | D8: Código de Ética, Políticas e Procedimentos | E8: A empresa possui Código de Ética e Conduta, ou documento equivalente, disponível em português? (Medida mínima prevista no art. 14 do Regulamento, de caráter obrigatório) | F8: Código de Ética, ou documento equivalente, em língua portuguesa.; POL-01 — Código de Ética Inclua também eventuais diretrizes ou guias complementares ao Código de Ética (ex.: guia de aplicação, FAQ interno), quando existentes. | G8: 0.1 | H8: AG-FCG-QPE-051 | I8: NORMATIVO | J8: Desenho | K8: VIGENTE | L8: 6.1 | M8: ISO-12 | N8: II | P8: ITP-004 / PB-016
A9: QPE-107 | B9: 11.3.1 | C9: Essenciais | D9: Treinamento e Comunicação | E9: No período avaliado, a empresa realizou treinamentos: direcionados a todos os empregados, abordando conteúdo geral do programa de integridade, como Código de Ética, canais de denúncia e política anticorrupção? | F9: Listas de presenças acompanhadas de materiais de estudo, links de acesso a treinamentos online ou registros de frequência e participação que demonstrem: o treinamento geral dos colaboradores nos temas fundamentais do programa de integridade (código de ética, canais de denúncia e política anticorrupção);; POL-01 — Código de Ética Inclua também, quando existente, a política ou diretriz de treinamento e capacitação em integridade que rege o conteúdo e a periodicidade das ações formativas. | G9: 0.5 | H9: AG-FCG-QPE-107 | I9: TREINAMENTO | J9: Execução | K9: PERIODO | L9: 8.1 | M9: ISO-26; ISO-27 | N9: IV | P9: ITP-006 / PB-036
A10: QPE-128 | B10: 12.3.7 | C10: Essenciais | D10: Treinamento e Comunicação | E10: As ações de comunicação realizadas pela empresa no período avaliado: foram realizadas por diferentes meios, para alcançar o público interno da empresa em toda sua diversidade? | F10: Correlacionar os diversos públicos de empregados da empresa com os meios de comunicação utilizados (e-mails, vídeos, cartazes, folders, registros da intranet, site etc.), com o objetivo de avaliar se todo o público interno foi alcançado. Inclua também, quando existente, a política ou diretriz de comunicação interna sobre integridade que orienta essas ações. | G10: 0.7 | H10: AG-FCG-QPE-128 | I10: PUBLICACAO_COMUNICACAO | J10: Execução | K10: PERIODO | L10: 9.1 | M10: ISO-28 | N10: IV | P10: ITP-007 / PB-039
A11: QPE-169 | B11: 19.1 | C11: Essenciais | D11: Canal de Denúncia e Medidas Disciplinares | E11: *A empresa possui canais para realização de denúncias, disponíveis em português? | F11: Link do site e caminho de navegação desde a página inicial até o canal de denúncias. Inclua também a política ou regulamento interno do canal de denúncias (sigilo, apuração e vedação a retaliação), quando existente, além do link de acesso. | G11: 0.1 | H11: AG-FCG-QPE-169 | I11: PUBLICACAO_COMUNICACAO | J11: Desenho | K11: VIGENTE | L11: 14.1 | M11: ISO-39 | N11: X | P11: ITP-008 / PB-053
A12: QPE-218 | B12: 23.2 | C12: Essenciais | D12: Transparência e Responsabilidade Socioambiental | E12: Existe uma seção específica no site da empresa que reúna as informações sobre o programa de integridade? | F12: Informar tanto o link de acesso quanto o caminho da página inicial do site da empresa até a seção específica no site da empresa que reúna as informações sobre o programa de integridade. Inclua também, quando existente, a diretriz ou guia de comunicação institucional que rege o conteúdo publicado sobre o programa de integridade. | G12: 0.2 | H12: AG-FCG-QPE-218 | I12: EXECUCAO_CONTROLE | J12: Publicação | K12: VIGENTE | L12: 19.1 | M12: ISO-28 | P12: ITP-009 / PB-072
A13: QPE-221 | B13: 24.3 | C13: Essenciais | D13: Transparência e Responsabilidade Socioambiental | E13: A empresa possui políticas e procedimentos para o tratamento e a destinação sustentável de resíduos sólidos, efluentes e gases gerados em suas áreas administrativas e/ou produtivas, considerando os impactos ambientais de suas atividades? | F13: Política, norma ou procedimento formal, aprovado pela direção da empresa e amplamente divulgado, que disponha sobre regras de tratamento e destino de resíduos sólidos e efluentes, considerando seus impactos no meio ambiente, sua mitigação e potencialidades de uso sustentável. Inclua também eventuais guias operacionais complementares à política ambiental, quando existentes, além da própria política já solicitada. | G13: 0.1 | H13: AG-FCG-QPE-221 | I13: GOVERNANCA | J13: Desenho | K13: VIGENTE | L13: 18.1 | P13: ITP-010 / PB-069
A14: QPE-073 | B14: 9.1.1 | C14: Essenciais | D14: Código de Ética, Políticas e Procedimentos | E14: A empresa possui políticas e procedimentos de integridade que: vedam expressamente a concessão de vantagens indevidas, econômicas ou não, a agentes públicos? | F14: Políticas, regras, orientações e/ou procedimentos (indicar a seção e a página) que: vedam expressamente a concessão de vantagens indevidas, econômicas ou não, a agentes públicos;; POL-05 — Relacionamento com o Setor Público Inclua também eventuais guias práticos ou diretrizes complementares sobre relacionamento com agentes públicos, quando existentes, além da própria política. | G14: 0.1 | H14: AG-FCG-QPE-073 | I14: NORMATIVO | J14: Desenho | K14: VIGENTE | L14: 7.1.1 | M14: ISO-12; ISO-31 | N14: II; VIII | O14: Sim | P14: ITP-005 / PB-026
E16: Total de perguntas / pontos | F16: =COUNTA(A5:A14) -> 10 | G16: =SUM(G5:G14) -> 4.7

Sheet II_PACTO_80_ITENS
A1: Etapa II · Pacto Completo — catálogo de 80 itens (11 reaproveitáveis das Essenciais + 69 complementos)
A2: Fonte: portal (DB.PACTO). Regra do portal: item cujo QPE vinculado é uma Essencial = reaproveitável; os demais = complemento. Redação sintética a validar no SAMPI.
A4: ID | B4: Nº | C4: Área | D4: Item do Pacto | E4: Medida essencial? | F4: Perguntas QPE vinculadas | G4: Medida (ITP) | H4: Classe | I4: Fonte
A5: PB-001 | B5: 1.1 | C5: Área I | D5: Os membros da alta direção apoiam de forma inequívoca a implementação de medidas de integridade? | E5: Sim | F5: QPE-006 | G5: ITP-001 | H5: Reaproveitável (Essencial) | I5: DIM_PACTO do modelo Simples GRC; redação sintética a validar no SAMPI
A6: PB-002 | B6: 1.2 | C6: Área I | D6: Os membros manifestam publicamente o apoio à integridade empresarial de forma personalizada? | E6: Não | F6: QPE-014 | H6: Complemento | I6: DIM_PACTO do modelo Simples GRC; redação sintética a validar no SAMPI
A7: PB-003 | B7: 1.3 | C7: Área I | D7: As mensagens incentivam conduta ética e tolerância zero com corrupção? | E7: Não | F7: QPE-019 | H7: Complemento | I7: DIM_PACTO do modelo Simples GRC; redação sintética a validar no SAMPI
A8: PB-004 | B8: 1.4 | C8: Área I | D8: As mensagens promovem preservação ambiental e respeito aos direitos humanos e trabalhistas? | E8: Não | F8: QPE-013; QPE-020 | H8: Complemento | I8: DIM_PACTO do modelo Simples GRC; redação sintética a validar no SAMPI
A9: PB-005 | B9: 2.1 | C9: Área I | D9: A aprovação das principais políticas de integridade é feita pelas elevadas instâncias decisórias? | E9: Não | F9: QPE-005 | H9: Complemento | I9: DIM_PACTO do modelo Simples GRC; redação sintética a validar no SAMPI
A10: PB-006 | B10: 2.2 | C10: Área I | D10: A alta direção supervisiona implantação mediante recebimento de relatórios periódicos? | E10: Não | F10: QPE-006 | H10: Reaproveitável (Essencial) | I10: DIM_PACTO do modelo Simples GRC; redação sintética a validar no SAMPI
A11: PB-007 | B11: 3.1 | C11: Área I | D11: Adota formalmente critérios de integridade para seleção de candidatos à alta direção? | E11: Não | F11: QPE-001; QPE-002 | H11: Complemento | I11: DIM_PACTO do modelo Simples GRC; redação sintética a validar no SAMPI
A12: PB-008 | B12: 3.2 | C12: Área I | D12: Remuneração variável está condicionada a indicadores relacionados à aplicação de medidas? | E12: Não | F12: QPE-004 | H12: Complemento | I12: DIM_PACTO do modelo Simples GRC; redação sintética a validar no SAMPI
A13: PB-009 | B13: 4.1 | C13: Área II | D13: A empresa possui instância interna responsável pela aplicação do programa de integridade? | E13: Sim | F13: QPE-024 | G13: ITP-002 | H13: Reaproveitável (Essencial) | I13: DIM_PACTO do modelo Simples GRC; redação sintética a validar no SAMPI
A14: PB-010 | B14: 4.2 | C14: Área II | D14: A instância está formalmente constituída com atribuições em documento aprovado? | E14: Não | F14: QPE-025 | H14: Complemento | I14: DIM_PACTO do modelo Simples GRC; redação sintética a validar no SAMPI
A15: PB-011 | B15: 5.1 | C15: Área III | D15: Realizou análise de riscos nos últimos 24 meses contemplando expressamente corrupção e fraude? | E15: Sim | F15: QPE-041 | G15: ITP-003 | H15: Reaproveitável (Essencial) | I15: DIM_PACTO do modelo Simples GRC; redação sintética a validar no SAMPI
A16: PB-012 | B16: 5.2 | C16: Área III | D16: A análise contempla classificação dos riscos por probabilidade e impacto? | E16: Não | F16: QPE-042 | H16: Complemento | I16: DIM_PACTO do modelo Simples GRC; redação sintética a validar no SAMPI
A17: PB-013 | B17: 5.3 | C17: Área III | D17: Estabeleceu medidas de mitigação com prazos e responsáveis definidos? | E17: Não | F17: QPE-043; QPE-044 | H17: Complemento | I17: DIM_PACTO do modelo Simples GRC; redação sintética a validar no SAMPI
A18: PB-014 | B18: 5.4 | C18: Área III | D18: Possui normativo sobre gestão de riscos prevendo reavaliação periódica? | E18: Não | F18: QPE-037; QPE-038 | H18: Complemento | I18: DIM_PACTO do modelo Simples GRC; redação sintética a validar no SAMPI
A19: PB-015 | B19: 5.5 | C19: Área III | D19: Identifica e trata riscos relacionados a impactos ambientais de suas atividades? | E19: Não | F19: QPE-050 | H19: Complemento | I19: DIM_PACTO do modelo Simples GRC; redação sintética a validar no SAMPI
A20: PB-016 | B20: 6.1 | C20: Área IV | D20: Possui Código de Ética e Conduta ou equivalente em português? | E20: Sim | F20: QPE-051 | G20: ITP-004 | H20: Reaproveitável (Essencial) | I20: DIM_PACTO do modelo Simples GRC; redação sintética a validar no SAMPI
A21: PB-017 | B21: 6.2.1 | C21: Área IV | D21: O código foi formalmente aprovado pela alta direção? | E21: Não | F21: QPE-052 | H21: Complemento | I21: DIM_PACTO do modelo Simples GRC; redação sintética a validar no SAMPI
A22: PB-018 | B22: 6.2.2 | C22: Área IV | D22: Inclui expressamente ética e integridade entre princípios ou valores? | E22: Não | F22: QPE-053 | H22: Complemento | I22: DIM_PACTO do modelo Simples GRC; redação sintética a validar no SAMPI
A23: PB-019 | B23: 6.2.3 | C23: Área IV | D23: Está alinhado com legislação anticorrupção brasileira, vedando corrupção? | E23: Não | F23: QPE-055 | H23: Complemento | I23: DIM_PACTO do modelo Simples GRC; redação sintética a validar no SAMPI
A24: PB-020 | B24: 6.2.4 | C24: Área IV | D24: Expressa compromisso com respeito aos direitos humanos? | E24: Não | H24: Complemento | I24: DIM_PACTO do modelo Simples GRC; redação sintética a validar no SAMPI
A25: PB-021 | B25: 6.2.5 | C25: Área IV | D25: Expressa compromisso com direitos trabalhistas e salário justo? | E25: Não | H25: Complemento | I25: DIM_PACTO do modelo Simples GRC; redação sintética a validar no SAMPI
A26: PB-022 | B26: 6.2.6 | C26: Área IV | D26: Expressa compromisso com preservação ambiental e desenvolvimento sustentável? | E26: Não | F26: QPE-061 | H26: Complemento | I26: DIM_PACTO do modelo Simples GRC; redação sintética a validar no SAMPI
A27: PB-023 | B27: 6.2.7 | C27: Área IV | D27: Estabelece condutas permitidas e proibidas pela empresa? | E27: Não | F27: QPE-056 | H27: Complemento | I27: DIM_PACTO do modelo Simples GRC; redação sintética a validar no SAMPI
A28: PB-024 | B28: 6.2.8 | C28: Área IV | D28: Menciona possibilidade de sanções para violações, inclusive para alta direção? | E28: Não | F28: QPE-062 | H28: Complemento | I28: DIM_PACTO do modelo Simples GRC; redação sintética a validar no SAMPI
A29: PB-025 | B29: 6.3 | C29: Área IV | D29: O código encontra-se disponível na página institucional ou redes sociais? | E29: Não | F29: QPE-066 | H29: Complemento | I29: DIM_PACTO do modelo Simples GRC; redação sintética a validar no SAMPI
A30: PB-026 | B30: 7.1.1 | C30: Área IV | D30: Políticas vedam expressamente concessão de vantagens econômicas a agentes públicos? | E30: Sim | F30: QPE-073 | G30: ITP-005 | H30: Reaproveitável (Essencial) | I30: DIM_PACTO do modelo Simples GRC; redação sintética a validar no SAMPI
A31: PB-027 | B31: 7.1.2 | C31: Área IV | D31: Tratam do oferecimento de presentes, brindes e hospitalidades a agentes públicos? | E31: Não | F31: QPE-074 | H31: Complemento | I31: DIM_PACTO do modelo Simples GRC; redação sintética a validar no SAMPI
A32: PB-028 | B32: 7.1.3 | C32: Área IV | D32: Tratam prevenção de conflito de interesses com Administração Pública? | E32: Não | F32: QPE-075 | H32: Complemento | I32: DIM_PACTO do modelo Simples GRC; redação sintética a validar no SAMPI
A33: PB-029 | B33: 7.1.4 | C33: Área IV | D33: Estabelecem orientações sobre reuniões e interações com agentes públicos? | E33: Não | F33: QPE-076 | H33: Complemento | I33: DIM_PACTO do modelo Simples GRC; redação sintética a validar no SAMPI
A34: PB-030 | B34: 7.1.5 | C34: Área IV | D34: Tratam realização de doação e patrocínio ou informam que não realiza? | E34: Não | F34: QPE-078 | H34: Complemento | I34: DIM_PACTO do modelo Simples GRC; redação sintética a validar no SAMPI
A35: PB-031 | B35: 7.1.6 | C35: Área IV | D35: Estabelecem orientações específicas para prevenção de fraudes em licitações? | E35: Não | H35: Complemento | I35: DIM_PACTO do modelo Simples GRC; redação sintética a validar no SAMPI
A36: PB-032 | B36: 7.1.7 | C36: Área IV | D36: Estabelecem orientações para prevenção de fraudes em execução de contratos? | E36: Não | F36: QPE-093 | H36: Complemento | I36: DIM_PACTO do modelo Simples GRC; redação sintética a validar no SAMPI
A37: PB-033 | B37: 7.1.8 | C37: Área IV | D37: Vedam expressamente exploração de trabalho infantil? | E37: Não | H37: Complemento | I37: DIM_PACTO do modelo Simples GRC; redação sintética a validar no SAMPI
A38: PB-034 | B38: 7.1.9 | C38: Área IV | D38: Vedam expressamente trabalho escravo ou em condições análogas? | E38: Não | H38: Complemento | I38: DIM_PACTO do modelo Simples GRC; redação sintética a validar no SAMPI
A39: PB-035 | B39: 7.2 | C39: Área IV | D39: As políticas e procedimentos foram aplicados periodicamente nos últimos 12 meses? | E39: Não | F39: QPE-083 | H39: Complemento | I39: DIM_PACTO do modelo Simples GRC; redação sintética a validar no SAMPI
A40: PB-036 | B40: 8.1 | C40: Área V | D40: Realizou treinamentos nos últimos 12 meses abordando conteúdo de integridade? | E40: Sim | F40: QPE-107 | G40: ITP-006 | H40: Reaproveitável (Essencial) | I40: DIM_PACTO do modelo Simples GRC; redação sintética a validar no SAMPI
A41: PB-037 | B41: 8.2 | C41: Área V | D41: Os treinamentos são planejados considerando características de cada público-alvo? | E41: Não | F41: QPE-103 | H41: Complemento | I41: DIM_PACTO do modelo Simples GRC; redação sintética a validar no SAMPI
A42: PB-038 | B42: 8.3 | C42: Área V | D42: Os treinamentos atingiram percentual relevante do público-alvo? | E42: Não | F42: QPE-114 | H42: Complemento | I42: DIM_PACTO do modelo Simples GRC; redação sintética a validar no SAMPI
A43: PB-039 | B43: 9.1 | C43: Área V | D43: Promoveu ações de comunicação nos últimos 12 meses para fomentar cultura de integridade? | E43: Sim | F43: QPE-128 | G43: ITP-007 | H43: Reaproveitável (Essencial) | I43: DIM_PACTO do modelo Simples GRC; redação sintética a validar no SAMPI
A44: PB-040 | B44: 9.2.1 | C44: Área V | D44: As ações difundiram aspectos gerais do programa como Código e Canal de Denúncia? | E44: Não | F44: QPE-122; QPE-123 | H44: Complemento | I44: DIM_PACTO do modelo Simples GRC; redação sintética a validar no SAMPI
A45: PB-041 | B45: 9.2.2 | C45: Área V | D45: Buscaram difundir necessidade de prevenir assédio e discriminação? | E45: Não | F45: QPE-124 | H45: Complemento | I45: DIM_PACTO do modelo Simples GRC; redação sintética a validar no SAMPI
A46: PB-042 | B46: 9.2.3 | C46: Área V | D46: Buscaram difundir importância da preservação ambiental e desenvolvimento sustentável? | E46: Não | F46: QPE-125 | H46: Complemento | I46: DIM_PACTO do modelo Simples GRC; redação sintética a validar no SAMPI
A47: PB-043 | B47: 10.1 | C47: Área VI | D47: Possui procedimentos definidos para lançamentos contábeis com fluxogramas e segregação? | E47: Não | F47: QPE-132; QPE-133; QPE-134 | H47: Complemento | I47: DIM_PACTO do modelo Simples GRC; redação sintética a validar no SAMPI
A48: PB-044 | B48: 10.2 | C48: Área VI | D48: Os registros contábeis são feitos de forma detalhada para evitar irregularidades? | E48: Não | F48: QPE-135 | H48: Complemento | I48: DIM_PACTO do modelo Simples GRC; redação sintética a validar no SAMPI
A49: PB-045 | B49: 10.3 | C49: Área VI | D49: Possui área de auditoria interna, formalizada ou terceirizada? | E49: Não | F49: QPE-137 | H49: Complemento | I49: DIM_PACTO do modelo Simples GRC; redação sintética a validar no SAMPI
A50: PB-046 | B50: 11.1.1 | C50: Área VII | D50: Realiza diligências verificando possível envolvimento em corrupção e fraude? | E50: Não | F50: QPE-144 | H50: Complemento | I50: DIM_PACTO do modelo Simples GRC; redação sintética a validar no SAMPI
A51: PB-047 | B51: 11.1.2 | C51: Área VII | D51: Verifica registro em listas sujas de trabalho escravo? | E51: Não | H51: Complemento | I51: DIM_PACTO do modelo Simples GRC; redação sintética a validar no SAMPI
A52: PB-048 | B52: 11.2 | C52: Área VII | D52: Realizou efetivamente diligências de integridade nos últimos 12 meses? | E52: Não | F52: QPE-159 | H52: Complemento | I52: DIM_PACTO do modelo Simples GRC; redação sintética a validar no SAMPI
A53: PB-049 | B53: 12.1.1 | C53: Área VII | D53: Inclui cláusulas nos contratos estabelecendo obrigatoriedade de normas éticas? | E53: Não | F53: QPE-160; QPE-161 | H53: Complemento | I53: DIM_PACTO do modelo Simples GRC; redação sintética a validar no SAMPI
A54: PB-050 | B54: 12.1.2 | C54: Área VII | D54: Exigem observância de direitos trabalhistas, proibindo trabalho infantil? | E54: Não | H54: Complemento | I54: DIM_PACTO do modelo Simples GRC; redação sintética a validar no SAMPI
A55: PB-051 | B55: 12.2 | C55: Área VII | D55: As cláusulas preveem aplicação de penalidades ou rescisão em caso de descumprimento? | E55: Não | F55: QPE-163 | H55: Complemento | I55: DIM_PACTO do modelo Simples GRC; redação sintética a validar no SAMPI
A56: PB-052 | B56: 13.1 | C56: Área VII | D56: Possui políticas específicas para fusões/aquisições verificando histórico de corrupção? | E56: Não | F56: QPE-164; QPE-168 | H56: Complemento | I56: DIM_PACTO do modelo Simples GRC; redação sintética a validar no SAMPI
A57: PB-053 | B57: 14.1 | C57: Área VIII | D57: Possui canal para realização de denúncias disponível em português? | E57: Sim | F57: QPE-169 | G57: ITP-008 | H57: Reaproveitável (Essencial) | I57: DIM_PACTO do modelo Simples GRC; redação sintética a validar no SAMPI
A58: PB-054 | B58: 14.2.1 | C58: Área VIII | D58: O canal pode ser utilizado por empregados? | E58: Não | F58: QPE-170 | H58: Complemento | I58: DIM_PACTO do modelo Simples GRC; redação sintética a validar no SAMPI
A59: PB-055 | B59: 14.2.2 | C59: Área VIII | D59: O canal pode ser utilizado pelo público externo? | E59: Não | F59: QPE-171 | H59: Complemento | I59: DIM_PACTO do modelo Simples GRC; redação sintética a validar no SAMPI
A60: PB-056 | B60: 14.2.3 | C60: Área VIII | D60: É acessível a partir da página institucional ou redes sociais? | E60: Não | F60: QPE-178 | H60: Complemento | I60: DIM_PACTO do modelo Simples GRC; redação sintética a validar no SAMPI
A61: PB-057 | B61: 14.2.4 | C61: Área VIII | D61: Indica expressamente garantias de proteção aos denunciantes de boa-fé? | E61: Não | F61: QPE-175 | H61: Complemento | I61: DIM_PACTO do modelo Simples GRC; redação sintética a validar no SAMPI
A62: PB-058 | B62: 14.2.5 | C62: Área VIII | D62: Permite acompanhamento da apuração pelo denunciante? | E62: Não | F62: QPE-176 | H62: Complemento | I62: DIM_PACTO do modelo Simples GRC; redação sintética a validar no SAMPI
A63: PB-059 | B63: 14.3 | C63: Área VIII | D63: Monitora canais mediante análise estatística de dados sobre denúncias? | E63: Não | F63: QPE-203 | H63: Complemento | I63: DIM_PACTO do modelo Simples GRC; redação sintética a validar no SAMPI
A64: PB-060 | B64: 15.1 | C64: Área VIII | D64: Possui políticas e procedimentos estabelecendo fluxo de tratamento de denúncias? | E64: Não | F64: QPE-179 | H64: Complemento | I64: DIM_PACTO do modelo Simples GRC; redação sintética a validar no SAMPI
A65: PB-061 | B65: 15.2 | C65: Área VIII | D65: Realizou apuração de denúncias nos últimos 12 meses? | E65: Não | F65: QPE-187 | H65: Complemento | I65: DIM_PACTO do modelo Simples GRC; redação sintética a validar no SAMPI
A66: PB-062 | B66: 16.1 | C66: Área VIII | D66: Possui políticas definindo medidas disciplinares aplicáveis? | E66: Não | F66: QPE-192 | H66: Complemento | I66: DIM_PACTO do modelo Simples GRC; redação sintética a validar no SAMPI
A67: PB-063 | B67: 16.2 | C67: Área VIII | D67: As medidas disciplinares estão correlacionadas ao tipo de infração? | E67: Não | F67: QPE-193 | H67: Complemento | I67: DIM_PACTO do modelo Simples GRC; redação sintética a validar no SAMPI
A68: PB-064 | B68: 17.1 | C68: Área IX | D68: Realiza monitoramento contínuo da aplicação de suas medidas de integridade? | E68: Não | F68: QPE-201 | H68: Complemento | I68: DIM_PACTO do modelo Simples GRC; redação sintética a validar no SAMPI
A69: PB-065 | B69: 17.2.1 | C69: Área IX | D69: O monitoramento é realizado de forma planejada? | E69: Não | F69: QPE-199 | H69: Complemento | I69: DIM_PACTO do modelo Simples GRC; redação sintética a validar no SAMPI
... A72: PB-068 | B72: 17.2.4 | C72: Área IX | D72: Com utilização de indicadores e estabelecimento de metas de desempenho? | E72: Não | F72: QPE-201; QPE-202 | H72: Complemento | I72: DIM_PACTO do modelo Simples GRC; redação sintética a validar no SAMPI
A73: PB-069 | B73: 18.1 | C73: Área X | D73: Observa legislação ambiental e mantém licenças ambientais em dia? | E73: Sim | F73: QPE-221 | G73: ITP-010 | H73: Reaproveitável (Essencial) | I73: DIM_PACTO do modelo Simples GRC; redação sintética a validar no SAMPI
A74: PB-070 | B74: 18.2 | C74: Área X | D74: Participa de ações coletivas relacionadas a integridade empresarial? | E74: Não | F74: QPE-222 | H74: Complemento | I74: DIM_PACTO do modelo Simples GRC; redação sintética a validar no SAMPI
A75: PB-071 | B75: 18.3 | C75: Área X | D75: Incentiva parceiros de negócios a adotarem medidas de integridade? | E75: Não | F75: QPE-072; QPE-112; QPE-147; QPE-152 | H75: Complemento | I75: DIM_PACTO do modelo Simples GRC; redação sintética a validar no SAMPI
A76: PB-072 | B76: 19.1 | C76: Área X | D76: Há manifestação clara do compromisso com ética na página institucional? | E76: Sim | F76: QPE-218 | G76: ITP-009 | H76: Reaproveitável (Essencial) | I76: DIM_PACTO do modelo Simples GRC; redação sintética a validar no SAMPI
A77: PB-073 | B77: 19.2.1 | C77: Área X | D77: Disponibiliza informações sobre principais atividades exercidas? | E77: Não | F77: QPE-207 | H77: Complemento | I77: DIM_PACTO do modelo Simples GRC; redação sintética a validar no SAMPI
A78: PB-074 | B78: 19.2.2 | C78: Área X | D78: Divulga identificação e função de principais executivos? | E78: Não | F78: QPE-208; QPE-209 | H78: Complemento | I78: DIM_PACTO do modelo Simples GRC; redação sintética a validar no SAMPI
A79: PB-075 | B79: 19.2.3 | C79: Área X | D79: Divulga participação em licitações públicas? | E79: Não | F79: QPE-211 | H79: Complemento | I79: DIM_PACTO do modelo Simples GRC; redação sintética a validar no SAMPI
A80: PB-076 | B80: 19.2.4 | C80: Área X | D80: Divulga celebração de contratos administrativos? | E80: Não | F80: QPE-212 | H80: Complemento | I80: DIM_PACTO do modelo Simples GRC; redação sintética a validar no SAMPI
A81: PB-077 | B81: 19.2.5 | C81: Área X | D81: Divulga realização de doações? | E81: Não | F81: QPE-214 | H81: Complemento | I81: DIM_PACTO do modelo Simples GRC; redação sintética a validar no SAMPI
A82: PB-078 | B82: 19.2.6 | C82: Área X | D82: Divulga realização de patrocínios? | E82: Não | F82: QPE-214 | H82: Complemento | I82: DIM_PACTO do modelo Simples GRC; redação sintética a validar no SAMPI
A83: PB-079 | B83: 19.2.7 | C83: Área X | D83: Divulga principais políticas e informações sobre programa de integridade? | E83: Não | F83: QPE-216 | H83: Complemento | I83: DIM_PACTO do modelo Simples GRC; redação sintética a validar no SAMPI
A84: PB-080 | B84: 19.2.8 | C84: Área X | D84: Divulga relatórios com desempenho ambiental, social e de governança? | E84: Não | F84: QPE-215; QPE-223 | H84: Complemento | I84: DIM_PACTO do modelo Simples GRC; redação sintética a validar no SAMPI
D86: Total / complementos / reaproveitáveis | E86: =COUNTA(A5:A84) -> 80 | H86: =COUNTIF(H5:H84,"Complemento") -> 69
H87: =COUNTIF(H5:H84,"Reaproveitável*") -> 11

Sheet II_PACTO_COMPL_69
A1: Etapa II · Complemento do Pacto — os 69 itens que não vêm das Essenciais
A2: Fonte: portal (DB.PACTO filtrado pela regra acima). Nº das perguntas QPE vem do formulário.
A4: ID | B4: Nº | C4: Área | D4: Item do Pacto | E4: Perguntas QPE vinculadas | F4: Nº no formulário | G4: Fonte
A5: PB-002 | B5: 1.2 | C5: Área I | D5: Os membros manifestam publicamente o apoio à integridade empresarial de forma personalizada? | E5: QPE-014 | F5: 3.1 | G5: DIM_PACTO do modelo Simples GRC; redação sintética a validar no SAMPI
A6: PB-003 | B6: 1.3 | C6: Área I | D6: As mensagens incentivam conduta ética e tolerância zero com corrupção? | E6: QPE-019 | F6: 3.2.5 | G6: DIM_PACTO do modelo Simples GRC; redação sintética a validar no SAMPI
A7: PB-004 | B7: 1.4 | C7: Área I | D7: As mensagens promovem preservação ambiental e respeito aos direitos humanos e trabalhistas? | E7: QPE-013; QPE-020 | F7: 2.5; 3.2.6 | G7: DIM_PACTO do modelo Simples GRC; redação sintética a validar no SAMPI
A8: PB-005 | B8: 2.1 | C8: Área I | D8: A aprovação das principais políticas de integridade é feita pelas elevadas instâncias decisórias? | E8: QPE-005 | F8: 2.1 | G8: DIM_PACTO do modelo Simples GRC; redação sintética a validar no SAMPI
A9: PB-007 | B9: 3.1 | C9: Área I | D9: Adota formalmente critérios de integridade para seleção de candidatos à alta direção? | E9: QPE-001; QPE-002 | F9: 1.1; 1.2 | G9: DIM_PACTO do modelo Simples GRC; redação sintética a validar no SAMPI
A10: PB-008 | B10: 3.2 | C10: Área I | D10: Remuneração variável está condicionada a indicadores relacionados à aplicação de medidas? | E10: QPE-004 | F10: 1.4 | G10: DIM_PACTO do modelo Simples GRC; redação sintética a validar no SAMPI
A11: PB-010 | B11: 4.2 | C11: Área II | D11: A instância está formalmente constituída com atribuições em documento aprovado? | E11: QPE-025 | F11: 4.2.1 | G11: DIM_PACTO do modelo Simples GRC; redação sintética a validar no SAMPI
A12: PB-012 | B12: 5.2 | C12: Área III | D12: A análise contempla classificação dos riscos por probabilidade e impacto? | E12: QPE-042 | F12: 6.3.1 | G12: DIM_PACTO do modelo Simples GRC; redação sintética a validar no SAMPI
A13: PB-013 | B13: 5.3 | C13: Área III | D13: Estabeleceu medidas de mitigação com prazos e responsáveis definidos? | E13: QPE-043; QPE-044 | F13: 6.3.2; 6.3.3 | G13: DIM_PACTO do modelo Simples GRC; redação sintética a validar no SAMPI
A14: PB-014 | B14: 5.4 | C14: Área III | D14: Possui normativo sobre gestão de riscos prevendo reavaliação periódica? | E14: QPE-037; QPE-038 | F14: 6.1; 6.1.1 | G14: DIM_PACTO do modelo Simples GRC; redação sintética a validar no SAMPI
A15: PB-015 | B15: 5.5 | C15: Área III | D15: Identifica e trata riscos relacionados a impactos ambientais de suas atividades? | E15: QPE-050 | F15: 6.5 | G15: DIM_PACTO do modelo Simples GRC; redação sintética a validar no SAMPI
... A18: PB-019 | B18: 6.2.3 | C18: Área IV | D18: Está alinhado com legislação anticorrupção brasileira, vedando corrupção? | E18: QPE-055 | F18: 7.2.4 | G18: DIM_PACTO do modelo Simples GRC; redação sintética a validar no SAMPI
A19: PB-020 | B19: 6.2.4 | C19: Área IV | D19: Expressa compromisso com respeito aos direitos humanos? | G19: DIM_PACTO do modelo Simples GRC; redação sintética a validar no SAMPI
A20: PB-021 | B20: 6.2.5 | C20: Área IV | D20: Expressa compromisso com direitos trabalhistas e salário justo? | G20: DIM_PACTO do modelo Simples GRC; redação sintética a validar no SAMPI
A21: PB-022 | B21: 6.2.6 | C21: Área IV | D21: Expressa compromisso com preservação ambiental e desenvolvimento sustentável? | E21: QPE-061 | F21: 7.2.10 | G21: DIM_PACTO do modelo Simples GRC; redação sintética a validar no SAMPI
A22: PB-023 | B22: 6.2.7 | C22: Área IV | D22: Estabelece condutas permitidas e proibidas pela empresa? | E22: QPE-056 | F22: 7.2.5 | G22: DIM_PACTO do modelo Simples GRC; redação sintética a validar no SAMPI
A23: PB-024 | B23: 6.2.8 | C23: Área IV | D23: Menciona possibilidade de sanções para violações, inclusive para alta direção? | E23: QPE-062 | F23: 7.2.11 | G23: DIM_PACTO do modelo Simples GRC; redação sintética a validar no SAMPI
A24: PB-025 | B24: 6.3 | C24: Área IV | D24: O código encontra-se disponível na página institucional ou redes sociais? | E24: QPE-066 | F24: 7.3 | G24: DIM_PACTO do modelo Simples GRC; redação sintética a validar no SAMPI
A25: PB-027 | B25: 7.1.2 | C25: Área IV | D25: Tratam do oferecimento de presentes, brindes e hospitalidades a agentes públicos? | E25: QPE-074 | F25: 9.1.2 | G25: DIM_PACTO do modelo Simples GRC; redação sintética a validar no SAMPI
A26: PB-028 | B26: 7.1.3 | C26: Área IV | D26: Tratam prevenção de conflito de interesses com Administração Pública? | E26: QPE-075 | F26: 9.1.3 | G26: DIM_PACTO do modelo Simples GRC; redação sintética a validar no SAMPI
A27: PB-029 | B27: 7.1.4 | C27: Área IV | D27: Estabelecem orientações sobre reuniões e interações com agentes públicos? | E27: QPE-076 | F27: 9.1.4 | G27: DIM_PACTO do modelo Simples GRC; redação sintética a validar no SAMPI
A28: PB-030 | B28: 7.1.5 | C28: Área IV | D28: Tratam realização de doação e patrocínio ou informam que não realiza? | E28: QPE-078 | F28: 9.1.6 | G28: DIM_PACTO do modelo Simples GRC; redação sintética a validar no SAMPI
A29: PB-031 | B29: 7.1.6 | C29: Área IV | D29: Estabelecem orientações específicas para prevenção de fraudes em licitações? | G29: DIM_PACTO do modelo Simples GRC; redação sintética a validar no SAMPI
A30: PB-032 | B30: 7.1.7 | C30: Área IV | D30: Estabelecem orientações para prevenção de fraudes em execução de contratos? | E30: QPE-093 | F30: 10.3.1 | G30: DIM_PACTO do modelo Simples GRC; redação sintética a validar no SAMPI
A31: PB-033 | B31: 7.1.8 | C31: Área IV | D31: Vedam expressamente exploração de trabalho infantil? | G31: DIM_PACTO do modelo Simples GRC; redação sintética a validar no SAMPI
A32: PB-034 | B32: 7.1.9 | C32: Área IV | D32: Vedam expressamente trabalho escravo ou em condições análogas? | G32: DIM_PACTO do modelo Simples GRC; redação sintética a validar no SAMPI
A33: PB-035 | B33: 7.2 | C33: Área IV | D33: As políticas e procedimentos foram aplicados periodicamente nos últimos 12 meses? | E33: QPE-083 | F33: 9.3 | G33: DIM_PACTO do modelo Simples GRC; redação sintética a validar no SAMPI
A34: PB-037 | B34: 8.2 | C34: Área V | D34: Os treinamentos são planejados considerando características de cada público-alvo? | E34: QPE-103 | F34: 11.1.4 | G34: DIM_PACTO do modelo Simples GRC; redação sintética a validar no SAMPI
A35: PB-038 | B35: 8.3 | C35: Área V | D35: Os treinamentos atingiram percentual relevante do público-alvo? | E35: QPE-114 | F35: 11.4.2 | G35: DIM_PACTO do modelo Simples GRC; redação sintética a validar no SAMPI
A36: PB-040 | B36: 9.2.1 | C36: Área V | D36: As ações difundiram aspectos gerais do programa como Código e Canal de Denúncia? | E36: QPE-122; QPE-123 | F36: 12.3.1; 12.3.2 | G36: DIM_PACTO do modelo Simples GRC; redação sintética a validar no SAMPI
A37: PB-041 | B37: 9.2.2 | C37: Área V | D37: Buscaram difundir necessidade de prevenir assédio e discriminação? | E37: QPE-124 | F37: 12.3.3 | G37: DIM_PACTO do modelo Simples GRC; redação sintética a validar no SAMPI
A38: PB-042 | B38: 9.2.3 | C38: Área V | D38: Buscaram difundir importância da preservação ambiental e desenvolvimento sustentável? | E38: QPE-125 | F38: 12.3.4 | G38: DIM_PACTO do modelo Simples GRC; redação sintética a validar no SAMPI
A39: PB-043 | B39: 10.1 | C39: Área VI | D39: Possui procedimentos definidos para lançamentos contábeis com fluxogramas e segregação? | E39: QPE-132; QPE-133; QPE-134 | F39: 14.1; 14.2; 14.3 | G39: DIM_PACTO do modelo Simples GRC; redação sintética a validar no SAMPI
A40: PB-044 | B40: 10.2 | C40: Área VI | D40: Os registros contábeis são feitos de forma detalhada para evitar irregularidades? | E40: QPE-135 | F40: 14.4 | G40: DIM_PACTO do modelo Simples GRC; redação sintética a validar no SAMPI
A41: PB-045 | B41: 10.3 | C41: Área VI | D41: Possui área de auditoria interna, formalizada ou terceirizada? | E41: QPE-137 | F41: 15.1 | G41: DIM_PACTO do modelo Simples GRC; redação sintética a validar no SAMPI
A42: PB-046 | B42: 11.1.1 | C42: Área VII | D42: Realiza diligências verificando possível envolvimento em corrupção e fraude? | E42: QPE-144 | F42: 16.1.2 | G42: DIM_PACTO do modelo Simples GRC; redação sintética a validar no SAMPI
A43: PB-047 | B43: 11.1.2 | C43: Área VII | D43: Verifica registro em listas sujas de trabalho escravo? | G43: DIM_PACTO do modelo Simples GRC; redação sintética a validar no SAMPI
A44: PB-048 | B44: 11.2 | C44: Área VII | D44: Realizou efetivamente diligências de integridade nos últimos 12 meses? | E44: QPE-159 | F44: 16.6 | G44: DIM_PACTO do modelo Simples GRC; redação sintética a validar no SAMPI
A45: PB-049 | B45: 12.1.1 | C45: Área VII | D45: Inclui cláusulas nos contratos estabelecendo obrigatoriedade de normas éticas? | E45: QPE-160; QPE-161 | F45: 17.1; 17.2 | G45: DIM_PACTO do modelo Simples GRC; redação sintética a validar no SAMPI
A46: PB-050 | B46: 12.1.2 | C46: Área VII | D46: Exigem observância de direitos trabalhistas, proibindo trabalho infantil? | G46: DIM_PACTO do modelo Simples GRC; redação sintética a validar no SAMPI
A47: PB-051 | B47: 12.2 | C47: Área VII | D47: As cláusulas preveem aplicação de penalidades ou rescisão em caso de descumprimento? | E47: QPE-163 | F47: 17.2.2 | G47: DIM_PACTO do modelo Simples GRC; redação sintética a validar no SAMPI
A48: PB-052 | B48: 13.1 | C48: Área VII | D48: Possui políticas específicas para fusões/aquisições verificando histórico de corrupção? | E48: QPE-164; QPE-168 | F48: 18.1.1; 18.2 | G48: DIM_PACTO do modelo Simples GRC; redação sintética a validar no SAMPI
A49: PB-054 | B49: 14.2.1 | C49: Área VIII | D49: O canal pode ser utilizado por empregados? | E49: QPE-170 | F49: 19.2.1 | G49: DIM_PACTO do modelo Simples GRC; redação sintética a validar no SAMPI
A50: PB-055 | B50: 14.2.2 | C50: Área VIII | D50: O canal pode ser utilizado pelo público externo? | E50: QPE-171 | F50: 19.2.2 | G50: DIM_PACTO do modelo Simples GRC; redação sintética a validar no SAMPI
A51: PB-056 | B51: 14.2.3 | C51: Área VIII | D51: É acessível a partir da página institucional ou redes sociais? | E51: QPE-178 | F51: 19.4 | G51: DIM_PACTO do modelo Simples GRC; redação sintética a validar no SAMPI
A52: PB-057 | B52: 14.2.4 | C52: Área VIII | D52: Indica expressamente garantias de proteção aos denunciantes de boa-fé? | E52: QPE-175 | F52: 19.2.6 | G52: DIM_PACTO do modelo Simples GRC; redação sintética a validar no SAMPI
A53: PB-058 | B53: 14.2.5 | C53: Área VIII | D53: Permite acompanhamento da apuração pelo denunciante? | E53: QPE-176 | F53: 19.2.7 | G53: DIM_PACTO do modelo Simples GRC; redação sintética a validar no SAMPI
A54: PB-059 | B54: 14.3 | C54: Área VIII | D54: Monitora canais mediante análise estatística de dados sobre denúncias? | E54: QPE-203 | F54: 22.2.3 | G54: DIM_PACTO do modelo Simples GRC; redação sintética a validar no SAMPI
A55: PB-060 | B55: 15.1 | C55: Área VIII | D55: Possui políticas e procedimentos estabelecendo fluxo de tratamento de denúncias? | E55: QPE-179 | F55: 20.1.1 | G55: DIM_PACTO do modelo Simples GRC; redação sintética a validar no SAMPI
A56: PB-061 | B56: 15.2 | C56: Área VIII | D56: Realizou apuração de denúncias nos últimos 12 meses? | E56: QPE-187 | F56: 20.5 | G56: DIM_PACTO do modelo Simples GRC; redação sintética a validar no SAMPI
A57: PB-062 | B57: 16.1 | C57: Área VIII | D57: Possui políticas definindo medidas disciplinares aplicáveis? | E57: QPE-192 | F57: 21.1.3 | G57: DIM_PACTO do modelo Simples GRC; redação sintética a validar no SAMPI
A58: PB-063 | B58: 16.2 | C58: Área VIII | D58: As medidas disciplinares estão correlacionadas ao tipo de infração? | E58: QPE-193 | F58: 21.1.4 | G58: DIM_PACTO do modelo Simples GRC; redação sintética a validar no SAMPI
... A73: PB-080 | B73: 19.2.8 | C73: Área X | D73: Divulga relatórios com desempenho ambiental, social e de governança? | E73: QPE-215; QPE-223 | F73: 23.1.9; 24.5 | G73: DIM_PACTO do modelo Simples GRC; redação sintética a validar no SAMPI
D75: Total de complementos | E75: =COUNTA(A5:A73) -> 69

Sheet II_PACTO_QPE_76
A1: Etapa II · Perguntas QPE correlatas ao Pacto Brasil (76)
A2: Fonte: portal (DB.Q trilha Pacto Brasil). Com as 10 Essenciais e as 137 do Pró-Ética completam as 223 QPE.
A4: ID | B4: Nº formulário | C4: Trilha | D4: Área | E4: Pergunta | F4: Evidência sugerida | G4: Peso (pts) | H4: Agente | I4: Tipo de verificação | J4: Natureza | K4: Janela | L4: Itens do Pacto | M4: Itens ISO | N4: Incisos art. 57 | O4: Licitações? | P4: Medida essencial (ITP)
A5: QPE-075 | B5: 9.1.3 | C5: Pacto Brasil | D5: Código de Ética, Políticas e Procedimentos | E5: A empresa possui políticas e procedimentos de integridade que: tratam da prevenção de conflito de interesses nas relações com a Administração Pública, incluindo contratações de agentes públicos, pessoas expostas politicamente, seus familiares, estreitos colaboradores e pessoas jurídicas de que participem? | F5: tratam da prevenção de conflitos de interesse nas relações com a Administração Pública, incluindo contratações de agentes públicos, suas famílias, colaboradores e pessoas jurídicas relacionadas;; POL-02 — Conflito de Interesses | POL-05 — Relacionamento com o Setor Público | G5: 0.3 | H5: AG-FCG-QPE-075 | I5: GOVERNANCA | J5: Desenho | K5: VIGENTE | L5: 7.1.3 | M5: ISO-16; ISO-23; ISO-31 | N5: VIII | O5: Sim
A6: QPE-001 | B6: 1.1 | C6: Pacto Brasil | D6: Comprometimento da Alta Direção | E6: A empresa possui critérios de integridade formalizados para seleção dos candidatos aos cargos da alta direção, inclusive para escolha de membros da alta direção de suas controladas/subsidiárias, quando for o caso? Se sim, informar os cargos a que são aplicados, a forma como são considerados no processo de seleção e os responsáveis por sua avaliação. | F6: Documentos que comprovem que a empresa possui critérios formalizados relacionados à integridade para escolha de membros da alta direção, tais como política de seleção, procedimentos de contratação. | G6: 1 | H6: AG-FCG-QPE-001 | I6: GOVERNANCA | J6: Desenho | K6: VIGENTE | L6: 3.1 | M6: ISO-22; ISO-23 | N6: I
A7: QPE-002 | B7: 1.2 | C7: Pacto Brasil | D7: Comprometimento da Alta Direção | E7: A empresa aplica critérios de integridade para seleção dos candidatos aos cargos da alta direção, inclusive para escolha de membros da alta direção de suas controladas/subsidiárias, quando for o caso? Se sim, informar se foram aplicados no processo de seleção dos atuais membros da alta direção e dos membros da alta direção de controladas/subsidiárias da empresa, quando for o caso. | F7: Documentos que comprovem que a empresa aplica critérios de integridade para escolha de membros da alta direção, tais como: testes de integridade, background check, know your employee – KYE, realização de pesquisas em fontes abertas, e outros critérios análogos que demonstrem avaliação do histórico profissional, casos de envolvimento em práticas de corrupção, fraude e outros ilícitos, bem como outras análises de antecedentes que impactem numa conduta íntegra. | G7: 1.2 | H7: AG-FCG-QPE-002 | I7: GOVERNANCA | J7: Execução | K7: PERIODO | L7: 3.1 | M7: ISO-22; ISO-23 | N7: I
A8: QPE-004 | B8: 1.4 | C8: Pacto Brasil | D8: Comprometimento da Alta Direção | E8: A política de remuneração variável para os membros da alta direção está condicionada ao atingimento de metas de desempenho relacionadas aos indicadores de aplicação do programa de integridade? | F8: Política, norma ou procedimento formal, aprovado pela direção da empresa, que disponha sobre regras que condicionem a remuneração variável dos membros da alta direção ao atingimento de metas relacionadas aos indicadores de aplicação do programa de integridade.; Documento normativo do tema explicitamente citado na pergunta; não atribuir automaticamente uma das 11 políticas essenciais. | G8: 0.1 | H8: AG-FCG-QPE-004 | I8: GOVERNANCA | J8: Desenho | K8: VIGENTE | L8: 3.2 | M8: ISO-10; ISO-25 | N8: I
A9: QPE-005 | B9: 2.1 | C9: Pacto Brasil | D9: Comprometimento da Alta Direção | E9: A aprovação das principais políticas relacionadas ao programa de integridade é feita pelas mais elevadas instâncias decisórias da empresa? | F9: Documentos que indiquem a forma como a alta direção participou da aprovação das principais políticas relacionadas ao programa de integridade, tais como: − atas de reuniões, e-mails ou outros documentos que comprovem que houve aprovação de criação ou atualização de estruturas, políticas ou procedimentos do programa de integridade pelos membros da alta direção; e registros incluídos na própria política. | G9: 0.9 | H9: AG-FCG-QPE-005 | I9: GOVERNANCA | J9: Execução | K9: PERIODO | L9: 2.1 | M9: ISO-08; ISO-12; ISO-48 | N9: I
A10: QPE-013 | B10: 2.5 | C10: Pacto Brasil | D10: Comprometimento da Alta Direção | E10: A alta direção da empresa incentiva o debate, a aprovação e a aplicação efetiva de normas, políticas e procedimentos relacionados com a preservação do meio ambiente, a redução ou eliminação da sua parcela de contribuição aos efeitos das mudanças climáticas e o combate à corrupção ambiental? | F10: Atas de reunião, comunicações internas, manifestações pessoais ou outros documentos que comprovem o incentivo da alta direção ao debate, aprovação e a aplicação efetiva de normas, políticas e procedimentos relacionados aos temas mencionados. | G10: 0.1 | H10: AG-FCG-QPE-013 | I10: PUBLICACAO_COMUNICACAO | J10: Execução | K10: PERIODO | L10: 1.4 | M10: ISO-09 | N10: I
A11: QPE-014 | B11: 3.1 | C11: Pacto Brasil | D11: Comprometimento da Alta Direção | E11: Os membros da alta direção, de forma pessoalizada, manifestam publicamente apoio ao programa de integridade? | F11: Mensagens ostensivas e identificáveis dos membros da alta direção aos funcionários da empresa, à sociedade, ao mercado, aos fornecedores e demais stakeholders, promovendo o comportamento ético e demonstrando o compromisso da empresa com a prevenção e o combate à corrupção (p.ex.: e-mails, redes sociais, intranet, vídeos institucionais e comunicados internos e externos), nos quais constem de forma visível e inequívoca, apoio ao programa de integridade e à importância da defesa da ética e integridade nas relações negociais, principalmente nas relações com o setor público. | G11: 0.4 | H11: AG-FCG-QPE-014 | I11: GOVERNANCA | J11: Execução | K11: PERIODO | L11: 1.2 | M11: ISO-09; ISO-10 | N11: I
A12: QPE-019 | B12: 3.2.5 | C12: Pacto Brasil | D12: Comprometimento da Alta Direção | E12: As manifestações de apoio ao programa de integridade: expressam uma mensagem de incentivo à adoção de uma conduta ética, seguindo os ditames do programa de integridade? (questão direcionada ao avaliador) | F12: Evidências de mensagens claras da alta direção aos colaboradores, sociedade, mercado e stakeholders, reforçando o compromisso da empresa no combate ao preconceito, à discriminação e ao assédio em qualquer forma. | G12: 0.3 | H12: AG-FCG-QPE-019 | I12: GOVERNANCA | J12: Avaliador | L12: 1.3 | M12: ISO-09; ISO-10 | N12: I
A13: QPE-020 | B13: 3.2.6 | C13: Pacto Brasil | D13: Comprometimento da Alta Direção | E13: As manifestações de apoio ao programa de integridade: expressam o compromisso da alta direção com o combate ao preconceito, à discriminação e ao assédio de qualquer natureza? | F13: Evidências de mensagens claras da alta direção aos colaboradores, sociedade, mercado e stakeholders, reforçando o compromisso da empresa no combate ao preconceito, à discriminação e ao assédio em qualquer forma. | G13: 0.1 | H13: AG-FCG-QPE-020 | I13: GOVERNANCA | J13: Execução | K13: PERIODO | L13: 1.4 | M13: ISO-09; ISO-10 | N13: I
A14: QPE-025 | B14: 4.2.1 | C14: Pacto Brasil | D14: Instância Responsável pelo Programa | E14: A instância interna responsável pelo programa de integridade: *está formalmente constituída, tendo suas atribuições expressamente previstas em documento aprovado pela alta direção da empresa? (*Medida mínima prevista no art. 14 do Regulamento, de caráter obrigatório) | F14: Regimento, estatuto, manuais, políticas, procedimentos ou outros documentos que estabeleçam a forma de organização do setor, incluindo a indicação da quantidade de funcionários dedicados exclusivamente ao programa de integridade e a respectiva qualificação; Descritivo dos principais cargos da área de integridade, incluindo-se o do chefe da área; Ata de reunião de assembleia geral de acionistas ou deliberação constante de ata de reunião de conselho de administração ou diretoria em que haja deliberação sobre a criação, as atribuições e o funcionamento do setor; “4.2”. Atentar que a data de criação da área ou designação do responsável deve ser até 30/04/2024. Obs.: A data de aprovação deve estar indicada no próprio documento ou, quando inexistente, deve ser enviado cópia do ato de sua aprovação em que conste a referida data. | G14: 1.4 | H14: AG-FCG-QPE-025 | I14: GOVERNANCA | J14: Desenho | K14: VIGENTE | L14: 4.2 | M14: ISO-13; ISO-14 | N14: IX
A15: QPE-037 | B15: 6.1 | C15: Pacto Brasil | D15: Gestão de Riscos para a Integridade | E15: Existe na empresa política ou planejamento que trate da gestão de riscos e que defina a metodologia para a realização da análise de riscos? | F15: Documento normativo do tema explicitamente citado na pergunta; não atribuir automaticamente uma das 11 políticas essenciais. | G15: 0.2 | H15: AG-FCG-QPE-037 | I15: RISCOS_TERCEIROS | J15: Desenho | K15: VIGENTE | L15: 5.4 | M15: ISO-07 | N15: V
A16: QPE-038 | B16: 6.1.1 | C16: Pacto Brasil | D16: Gestão de Riscos para a Integridade | E16: A política ou planejamento que trata da gestão de riscos institui a periodicidade mínima para atualização/revisão do processo de análise de riscos? | F16: periodicidade mínima para atualização/revisão do processo de gestão de riscos;; Documento normativo do tema explicitamente citado na pergunta; não atribuir automaticamente uma das 11 políticas essenciais. | G16: 0.5 | H16: AG-FCG-QPE-038 | I16: RISCOS_TERCEIROS | J16: Desenho | K16: VIGENTE | L16: 5.4 | M16: ISO-07 | N16: V
A17: QPE-042 | B17: 6.3.1 | C17: Pacto Brasil | D17: Gestão de Riscos para a Integridade | E17: A análise de riscos para a integridade realizada contempla: a classificação dos riscos com base em sua probabilidade e impacto? | F17: Política ou planejamento da empresa, aprovado(s) pela alta direção, que trate da gestão de riscos e que defina a metodologia de análise de riscos, contendo: a descrição dos riscos de integridade, avaliando sua probabilidade e impacto; | G17: 0.7 | H17: AG-FCG-QPE-042 | I17: RISCOS_TERCEIROS | J17: Execução | K17: PERIODO | L17: 5.2 | M17: ISO-07 | N17: V
A18: QPE-043 | B18: 6.3.2 | C18: Pacto Brasil | D18: Gestão de Riscos para a Integridade | E18: A análise de riscos para a integridade realizada contempla: O tratamento indicado para cada um dos riscos identificados? | F18: Política ou planejamento da empresa, aprovado(s) pela alta direção, que trate da gestão de riscos e que defina a metodologia de análise de riscos, contendo: a identificação, classificação e indicando o tratamento para cada risco de integridade; | G18: 1.5 | H18: AG-FCG-QPE-043 | I18: RISCOS_TERCEIROS | J18: Execução | K18: PERIODO | L18: 5.3 | M18: ISO-07; ISO-17 | N18: V
A19: QPE-044 | B19: 6.3.3 | C19: Pacto Brasil | D19: Gestão de Riscos para a Integridade | E19: A análise de riscos para a integridade realizada contempla: Os responsáveis pelo tratamento dos riscos identificados? | F19: Política ou planejamento da empresa, aprovado(s) pela alta direção, que trate da gestão de riscos e que defina a metodologia de análise de riscos, contendo: a identificação dos responsáveis pelo tratamento dos riscos apontados; | G19: 1 | H19: AG-FCG-QPE-044 | I19: RISCOS_TERCEIROS | J19: Execução | K19: PERIODO | L19: 5.3 | M19: ISO-07; ISO-13; ISO-17 | N19: V
A20: QPE-050 | B20: 6.5 | C20: Pacto Brasil | D20: Gestão de Riscos para a Integridade | E20: No período avaliado, a empresa identificou e tratou riscos ambientais e climáticos, sejam relacionados a eventos externos que afetam as atividades da empresa, sejam relacionados às atividades da empresa que afetam terceiros? | F20: Exemplos de processos reais como matriz de risco, relatórios e plano de gestão, que identificam e tratam riscos ambientais e climáticos, tanto relacionados a eventos externos que impactam as atividades da empresa quanto aos riscos decorrentes das atividades da empresa que afetam terceiros. | G20: 0.1 | H20: AG-FCG-QPE-050 | I20: RISCOS_TERCEIROS | J20: Execução | K20: PERIODO | L20: 5.5 | M20: ISO-02 | N20: V
A21: QPE-052 | B21: 7.2.1 | C21: Pacto Brasil | D21: Código de Ética, Políticas e Procedimentos | E21: O Código de Ética e Conduta, ou documento equivalente, apresentado: foi formalmente aprovado pela alta direção da empresa? Se sim, descrever o processo de aprovação da versão atual do Código de Ética e Conduta da empresa. | F21: Documento que comprove a sua aprovação pela alta direção (ata de reunião ou mensagem constante no próprio Código).; POL-01 — Código de Ética | G21: 0.3 | H21: AG-FCG-QPE-052 | I21: GOVERNANCA | J21: Desenho | K21: VIGENTE | L21: 6.2.1 | M21: ISO-12 | N21: II
A22: QPE-053 | B22: 7.2.2 | C22: Pacto Brasil | D22: Código de Ética, Políticas e Procedimentos | E22: O Código de Ética e Conduta, ou documento equivalente, apresentado: inclui expressamente a ética e/ou a integridade entre os princípios ou valores da empresa? | F22: Indicar a seção e a página do Código de Ética e Conduta ou documento equivalente onde a ética e/ou integridade são mencionadas expressamente como princípios ou valores da empresa.; POL-01 — Código de Ética | G22: 0.2 | H22: AG-FCG-QPE-053 | I22: NORMATIVO | J22: Desenho | K22: VIGENTE | L22: 6.2.2 | M22: ISO-12 | N22: II
A23: QPE-055 | B23: 7.2.4 | C23: Pacto Brasil | D23: Código de Ética, Políticas e Procedimentos | E23: O Código de Ética e Conduta, ou documento equivalente, apresentado: Indicar a seção e a página do Código de Ética e Conduta ou documento equivalente onde consta vedações expressas à prática de atos de corrupção | F23: está alinhado com a legislação anticorrupção brasileira, contendo vedações expressas à prática de atos de corrupção e fraude e a prevenção de conflitos de interesses?; POL-01 — Código de Ética | G23: 0.3 | H23: AG-FCG-QPE-055 | I23: NORMATIVO | J23: Desenho | K23: VIGENTE | L23: 6.2.3 | N23: II
A24: QPE-056 | B24: 7.2.5 | C24: Pacto Brasil | D24: Código de Ética, Políticas e Procedimentos | E24: O Código de Ética e Conduta, ou documento equivalente, apresentado: Estabelece as condutas permitidas e proibidas dentro da empresa? | F24: Indicar a seção e a página do Código de Ética e Conduta ou documento equivalente onde se estabelece as condutas permitidas e proibidas dentro da empresa.; POL-01 — Código de Ética | G24: 0.1 | H24: AG-FCG-QPE-056 | I24: NORMATIVO | J24: Desenho | K24: VIGENTE | L24: 6.2.7 | M24: ISO-15 | N24: II
A25: QPE-061 | B25: 7.2.10 | C25: Pacto Brasil | D25: Código de Ética, Políticas e Procedimentos | E25: O Código de Ética e Conduta, ou documento equivalente, apresentado: expressa o compromisso da empresa com o cumprimento da legislação ambiental, com o seu papel diante dos efeitos das mudanças climáticas e com o desenvolvimento sustentável? | F25: seção e a página do Código de Ética e Conduta ou documento equivalente onde a empresa assume seu compromisso com a legislação ambiental, as mudanças climáticas e o desenvolvimento sustentável.; POL-01 — Código de Ética | G25: 0.1 | H25: AG-FCG-QPE-061 | I25: NORMATIVO | J25: Desenho | K25: VIGENTE | L25: 6.2.6 | M25: ISO-12 | N25: II
A26: QPE-062 | B26: 7.2.11 | C26: Pacto Brasil | D26: Código de Ética, Políticas e Procedimentos | E26: O Código de Ética e Conduta, ou documento equivalente, apresentado: menciona a possibilidade de aplicação de sanções para aqueles que cometerem violações éticas/legais, inclusive para os membros da alta direção da empresa? | F26: seção e a página do Código de Ética e Conduta ou documento equivalente que tratam das sanções aplicáveis a violações éticas ou legais, incluindo penalidades para membros da alta direção.; POL-01 — Código de Ética | G26: 0.2 | H26: AG-FCG-QPE-062 | I26: GOVERNANCA | J26: Desenho | K26: VIGENTE | L26: 6.2.8 | M26: ISO-12; ISO-24 | N26: II; XI
A27: QPE-066 | B27: 7.3 | C27: Pacto Brasil | D27: Código de Ética, Políticas e Procedimentos | E27: O Código de Ética e Conduta, ou documento equivalente, encontra-se disponível na página eletrônica da empresa? | F27: Informar tanto o link de acesso quanto o caminho da página inicial do site da empresa até o Código de Ética e Conduta ou documento equivalente.; POL-01 — Código de Ética | G27: 0.4 | H27: AG-FCG-QPE-066 | I27: NORMATIVO | J27: Publicação | K27: VIGENTE | L27: 6.3 | M27: ISO-12 | N27: II
A28: QPE-072 | B28: 8.4 | C28: Pacto Brasil | D28: Código de Ética, Políticas e Procedimentos | E28: A empresa solicita aos terceiros que declarem expressamente que estão cientes da existência e do conteúdo desse documento, e que se comprometem a observar os termos e condições nele previstos? Se sim, informar como e em que momento isso ocorre. | F28: Evidências como termos de ciência, contratos ou declarações assinadas por terceiros confirmando a ciência e o compromisso com o Código de Ética e Conduta ou documento equivalente, incluindo atualizações. Contratos firmados com terceiros/fornecedores que contenham cláusulas de ciência e concordância e de compromisso com o cumprimento do Código de Ética e Conduta aplicável a terceiros.; POL-01 — Código de Ética | POL-06 — Due Diligence de Terceiros | G28: 0.3 | H28: AG-FCG-QPE-072 | I28: RISCOS_TERCEIROS | J28: Execução | K28: PERIODO | L28: 18.3 | M28: ISO-35; ISO-36 | N28: III
A29: QPE-074 | B29: 9.1.2 | C29: Pacto Brasil | D29: Código de Ética, Políticas e Procedimentos | E29: A empresa possui políticas e procedimentos de integridade que: tratam do oferecimento de presentes, brindes e hospitalidades (refeições, entretenimento, viagem e hospedagem) a agentes públicos? | F29: Políticas, regras, orientações e/ou procedimentos (indicar a seção e a página) que: regulam o oferecimento de presentes, brindes e hospitalidades (como refeições, entretenimento, viagens e hospedagem) a agentes públicos;; POL-03 — Brindes, Presentes e Hospitalidade | POL-05 — Relacionamento com o Setor Público | G29: 0.3 | H29: AG-FCG-QPE-074 | I29: GOVERNANCA | J29: Desenho | K29: VIGENTE | L29: 7.1.2 | M29: ISO-31; ISO-37 | N29: II
A30: QPE-076 | B30: 9.1.4 | C30: Pacto Brasil | D30: Código de Ética, Políticas e Procedimentos | E30: A empresa possui políticas e procedimentos de integridade que: estabelecem orientações e controles sobre temas como realização de reuniões, encontros e outros tipos de interações entre administradores e empregados da empresa com agentes públicos? | F30: definem diretrizes e controles sobre reuniões, encontros e outras interações entre administradores ou empregados da empresa e agentes públicos;; POL-05 — Relacionamento com o Setor Público | G30: 0.2 | H30: AG-FCG-QPE-076 | I30: NORMATIVO | J30: Desenho | K30: VIGENTE | L30: 7.1.4 | M30: ISO-31; ISO-37 | N30: VIII | O30: Sim
A31: QPE-078 | B31: 9.1.6 | C31: Pacto Brasil | D31: Código de Ética, Políticas e Procedimentos | E31: A empresa possui políticas e procedimentos de integridade que: tratam da realização de doação e patrocínio, ou informam claramente que a empresa não realiza essas atividades? | F31: abordam a realização de doações e patrocínios ou que deixam claro que a empresa não realiza essas atividades;; POL-04 — Doações, Patrocínios e Contribuições | G31: 0.3 | H31: AG-FCG-QPE-078 | I31: GOVERNANCA | J31: Desenho | K31: VIGENTE | L31: 7.1.5 | M31: ISO-31; ISO-37 | N31: XIII
A32: QPE-083 | B32: 9.3 | C32: Pacto Brasil | D32: Código de Ética, Políticas e Procedimentos | E32: A empresa aplicou, no período avaliado, as políticas e procedimentos de integridade apresentados? | F32: Relatórios, atas de reuniões, e-mails, due diligence, medidas disciplinares aplicadas a empregados, contratos rescindidos e/ou multas aplicadas a terceiros, monitoramento dos canais de denúncias etc.; POL-06 — Due Diligence de Terceiros | POL-10 — Investigações e Medidas Disciplinares | G32: 3.4 | H32: AG-FCG-QPE-083 | I32: RISCOS_TERCEIROS | J32: Execução | K32: PERIODO | L32: 7.2 | M32: ISO-05; ISO-30; ISO-31 | N32: II
A33: QPE-093 | B33: 10.3.1 | C33: Pacto Brasil | D33: Código de Ética, Políticas e Procedimentos | E33: Em relação à gestão e à execução do contrato administrativo, a empresa, na condição de contratada, possui políticas e procedimentos que: estabelecem orientações sobre a conduta esperada (o que é permitido/proibido) para os seus empregados? | F33: Evidência que indique a seção e a página das políticas, regras, orientações ou procedimentos que: estabelecem diretrizes claras sobre a conduta esperada dos empregados, especificando ações permitidas e proibidas; | G33: 0.3 | H33: AG-FCG-QPE-093 | I33: GOVERNANCA | J33: Desenho | K33: VIGENTE | L33: 7.1.7 | M33: ISO-34 | N33: VIII | O33: Sim
A34: QPE-103 | B34: 11.1.4 | C34: Pacto Brasil | D34: Treinamento e Comunicação | E34: A empresa possui um planejamento para realização de treinamentos relacionados ao programa de integridade contendo: a definição dos públicos-alvo dos treinamentos? | F34: Documento formal em que conste o planejamento das atividades de treinamentos relacionadas à integridade para determinado período (anual, geralmente). O documento deve elencar: os públicos-alvo definidos para os treinamentos; | G34: 0.3 | H34: AG-FCG-QPE-103 | I34: TREINAMENTO | J34: Desenho | K34: VIGENTE | L34: 8.2 | M34: ISO-26 | N34: IV
A35: QPE-112 | B35: 11.3.6 | C35: Pacto Brasil | D35: Treinamento e Comunicação | E35: No período avaliado, a empresa realizou treinamentos: direcionados aos principais parceiros de negócio, de acordo com a avaliação de riscos, incluindo agentes intermediários, quando for o caso? | F35: Listas de presenças acompanhadas de materiais de estudo, links de acesso a treinamentos online ou registros de frequência e participação que demonstrem: o treinamento específico para parceiros de negócio (identificando- os claramente), alinhados à avaliação de riscos, incluindo agentes intermediários quando pertinente. | G35: 0.3 | H35: AG-FCG-QPE-112 | I35: TREINAMENTO | J35: Execução | K35: PERIODO | L35: 18.3 | M35: ISO-26; ISO-35 | N35: IV; III
A36: QPE-114 | B36: 11.4.2 | C36: Pacto Brasil | D36: Treinamento e Comunicação | E36: Os treinamentos realizados no período avaliado: atingiram, pelo menos, 70% de cada um dos públicos-alvo? Relatórios ou históricos dos treinamentos contendo dados estatísticos ou percentuais de participação, acompanhados de listas de presença para comprovação | F36: Relatórios ou históricos dos treinamentos contendo dados estatísticos ou percentuais de participação, acompanhados de listas de presença para comprovação. | G36: 0.6 | H36: AG-FCG-QPE-114 | I36: TREINAMENTO | J36: Execução | K36: PERIODO | L36: 8.3 | M36: ISO-26 | N36: IV
A37: QPE-122 | B37: 12.3.1 | C37: Pacto Brasil | D37: Treinamento e Comunicação | E37: As ações de comunicação realizadas pela empresa no período avaliado: buscaram promover a divulgação do Código de Ética e das principais políticas de integridade? | F37: Comunicações internas veiculando o conteúdo dos documentos relacionados ao programa de integridade, assegurando a identificação dos destinatários, tais como: e-mails, vídeos, cartazes, folders, links do site ou printscreen de página da intranet onde os documentos relacionados ao programa de integridade podem ser acessados, que: tenham como teor a divulgação do Código de Ética e principais políticas de integridade;; POL-01 — Código de Ética | G37: 0.3 | H37: AG-FCG-QPE-122 | I37: PUBLICACAO_COMUNICACAO | J37: Execução | K37: PERIODO | L37: 9.2.1 | M37: ISO-27; ISO-28 | N37: IV
A38: QPE-123 | B38: 12.3.2 | C38: Pacto Brasil | D38: Treinamento e Comunicação | E38: As ações de comunicação realizadas pela empresa no período avaliado: buscaram promover a divulgação dos canais de denúncias? | F38: Comunicações internas veiculando o conteúdo dos documentos relacionados ao programa de integridade, assegurando a identificação dos destinatários, tais como: e-mails, vídeos, cartazes, folders, links do site ou printscreen de página da intranet onde os documentos relacionados ao programa de integridade podem ser acessados, que: tenham como teor à divulgação dos canais de denúncia; | G38: 0.3 | H38: AG-FCG-QPE-123 | I38: PUBLICACAO_COMUNICACAO | J38: Execução | K38: PERIODO | L38: 9.2.1 | M38: ISO-27; ISO-28; ISO-39 | N38: IV
A39: QPE-124 | B39: 12.3.3 | C39: Pacto Brasil | D39: Treinamento e Comunicação | E39: As ações de comunicação realizadas pela empresa no período avaliado: buscaram promover o combate ao preconceito, à discriminação e ao assédio de qualquer natureza? | F39: Comunicações internas veiculando o conteúdo dos documentos relacionados ao programa de integridade, assegurando a identificação dos destinatários, tais como: e-mails, vídeos, cartazes, folders, links do site ou printscreen de página da intranet onde os documentos relacionados ao programa de integridade podem ser acessados, que: promovam o combate ao preconceito, à discriminação e ao assédio de qualquer natureza; | G39: 0.1 | H39: AG-FCG-QPE-124 | I39: PUBLICACAO_COMUNICACAO | J39: Execução | K39: PERIODO | L39: 9.2.2 | M39: ISO-28 | N39: IV
A40: QPE-125 | B40: 12.3.4 | C40: Pacto Brasil | D40: Treinamento e Comunicação | E40: As ações de comunicação realizadas pela empresa no período avaliado: buscaram divulgar práticas de sustentabilidade socioambiental da empresa e promover a conscientização ambiental para os públicos interno e externo? | F40: Comunicações internas veiculando o conteúdo dos documentos relacionados ao programa de integridade, assegurando a identificação dos destinatários, tais como: e-mails, vídeos, cartazes, folders, links do site ou printscreen de página da intranet onde os documentos relacionados ao programa de integridade podem ser acessados, que: promovam práticas de sustentabilidade socioambiental e conscientização ambiental, para os públicos interno e externo. | G40: 0.1 | H40: AG-FCG-QPE-125 | I40: PUBLICACAO_COMUNICACAO | J40: Execução | K40: PERIODO | L40: 9.2.3 | M40: ISO-28 | N40: IV
A41: QPE-132 | B41: 14.1 | C41: Pacto Brasil | D41: Controles Contábeis, Financeiros e Auditoria | E41: A empresa possui fluxos de trabalho para elaboração dos lançamentos financeiros? | F41: Fluxogramas, dashboards, printscreen de telas de sistemas, relatórios de auditorias e comunicações internas etc., que comprovem a existência de rotinas e atividades necessárias tanto para os registros feitos pela área financeira quanto para os registros feitos pela área contábil. Políticas, normas, procedimentos e medidas de controle interno contábil e financeiro adotadas pela empresa.; POL-08 — Registros Contábeis | G41: 0.3 | H41: AG-FCG-QPE-132 | I41: PUBLICACAO_COMUNICACAO | J41: Desenho | K41: VIGENTE | L41: 10.1 | M41: ISO-33 | N41: VI; VII
A42: QPE-133 | B42: 14.2 | C42: Pacto Brasil | D42: Controles Contábeis, Financeiros e Auditoria | E42: A empresa possui fluxos de trabalho para elaboração dos lançamentos contábeis? | F42: Fluxogramas, dashboards, printscreen de telas de sistemas, relatórios de auditorias e comunicações internas etc., que comprovem a existência de rotinas e atividades necessárias tanto para os registros feitos pela área financeira quanto para os registros feitos pela área contábil. Políticas, normas, procedimentos e medidas de controle interno contábil e financeiro adotadas pela empresa.; POL-08 — Registros Contábeis | G42: 0.3 | H42: AG-FCG-QPE-133 | I42: PUBLICACAO_COMUNICACAO | J42: Desenho | K42: VIGENTE | L42: 10.1 | M42: ISO-33 | N42: VI; VII
A43: QPE-134 | B43: 14.3 | C43: Pacto Brasil | D43: Controles Contábeis, Financeiros e Auditoria | E43: A empresa possui regras que estabelecem a segregação de funções e a definição de níveis de aprovação (alçadas) de receitas e despesas? | F43: Normas internas que estabeleçam separação de competências e a necessidade de aprovações/autorizações por diferentes níveis hierárquicos para realização de pagamentos e recebimentos, aprovação de relatórios e outras atividades. Prints de sistemas em que constem perfis segregados de acordo com as funções. | G43: 0.7 | H43: AG-FCG-QPE-134 | I43: GOVERNANCA | J43: Desenho | K43: VIGENTE | L43: 10.1 | M43: ISO-16; ISO-33 | N43: VI; VII
A44: QPE-135 | B44: 14.4 | C44: Pacto Brasil | D44: Controles Contábeis, Financeiros e Auditoria | E44: A empresa possui mecanismos para detectar receitas e despesas fora do padrão e/ou "red flags" durante a realização de lançamentos contábeis? | F44: Normas ou documentos formais que estabeleçam mecanismos e controles para registros contábeis que possam identificar, ainda durante o fechamento da contabilidade, “red flags” envolvendo transações suspeitas. Exemplos de “red flags” podem incluir: receitas e despesas com valores mais elevados que o habitual ou de natureza estranha ao objeto social da empresa, sem justificativa; operações sem documentação comprobatória ou envolvendo pessoas suspeitas; transferências sem identificação etc. Sistema de alerta precoce (“early warning”), para verificar se nas demonstrações financeiras existe a probabilidade de fraude. | G44: 0.7 | H44: AG-FCG-QPE-135 | I44: EXECUCAO_CONTROLE | J44: Desenho | K44: VIGENTE | L44: 10.2 | M44: ISO-33 | N44: VI; VII
A45: QPE-137 | B45: 15.1 | C45: Pacto Brasil | D45: Controles Contábeis, Financeiros e Auditoria | E45: A empresa possui uma área de auditoria interna formalmente instituída ou contrato vigente com auditoria interna terceirizada? | F45: Documento (regimento interno, estatuto social, organograma) formalmente aprovado que estabeleça a instituição de uma área de auditoria interna. Contratos vigentes com empresas terceirizadas de auditoria interna. | G45: 0.4 | H45: AG-FCG-QPE-137 | I45: NORMATIVO | J45: Desenho | K45: VIGENTE | L45: 10.3 | M45: ISO-46 | N45: VII
... A58: QPE-176 | B58: 19.2.7 | C58: Pacto Brasil | D58: Canal de Denúncia e Medidas Disciplinares | E58: Os canais de denúncias da empresa: permitem o acompanhamento da apuração da denúncia pelo denunciante? | F58: Prints de tela da intranet/internet, juntamente com o link de acesso ao canal de denúncias, contendo informação expressa: − acerca da possibilidade de utilizar o canal para a realização de denúncias relacionadas a atos de corrupção, fraude e outras irregularidades previstas na Lei n. 12.846/2013, bem como violações de direitos humanos e degradação ambiental decorrente das atividades da empresa; − acerca das garantias de proteção oferecidas aos denunciantes de boa-fé (não retaliação, sigilo do denunciante – excepcionalizando-se legislações estrangeiras que não admitem denúncias anônimas); − acerca da possibilidade de acompanhamento da apuração da denúncia pelo denunciante, inclusive com a disponibilização, no próprio canal, de campo específico para esse fim, tais como protocolo etc.; | G58: 0.4 | H58: AG-FCG-QPE-176 | I58: PUBLICACAO_COMUNICACAO | J58: Desenho | K58: VIGENTE | L58: 14.2.5 | M58: ISO-39 | N58: X
A59: QPE-178 | B59: 19.4 | C59: Pacto Brasil | D59: Canal de Denúncia e Medidas Disciplinares | E59: Os canais de denúncia são de fácil acesso para os diversos públicos? (questão direcionada ao avaliador) | F59: Informação não especificada na fonte; pendente de confirmação por pergunta. | G59: 0.3 | H59: AG-FCG-QPE-178 | I59: EXECUCAO_CONTROLE | J59: Avaliador | L59: 14.2.3 | M59: ISO-39 | N59: X
A60: QPE-179 | B60: 20.1.1 | C60: Pacto Brasil | D60: Canal de Denúncia e Medidas Disciplinares | E60: A empresa possui políticas e procedimentos que: estabelecem o fluxo de recebimento, tratamento e apuração das denúncias? | F60: Normativos que estabeleçam o fluxo de tratamento de denúncias, contendo os responsáveis por cada etapa e prazos de apuração, inclusive com garantias de acesso irrestrito a documentos, sistemas e pessoas; | G60: 0.4 | H60: AG-FCG-QPE-179 | I60: GOVERNANCA | J60: Desenho | K60: VIGENTE | L60: 15.1 | M60: ISO-40 | N60: X
A61: QPE-187 | B61: 20.5 | C61: Pacto Brasil | D61: Canal de Denúncia e Medidas Disciplinares | E61: A empresa realizou a apuração de denúncias relacionadas com atos de fraude e corrupção entre 2023 e 2025? | F61: Documentos reais de apuração de denúncias envolvendo os temas dos itens 20.5 a 20.7, recebidas e apuradas entre 2023 e 2025, com os seus respectivos desdobramentos. | G61: 1.2 | H61: AG-FCG-QPE-187 | I61: EXECUCAO_CONTROLE | J61: Execução | K61: JANELA:2023-01-01:2025-12-31 | L61: 15.2 | M61: ISO-40 | N61: X
A62: QPE-192 | B62: 21.1.3 | C62: Pacto Brasil | D62: Canal de Denúncia e Medidas Disciplinares | E62: A empresa possui políticas e procedimentos que: definem as medidas disciplinares aplicáveis? | F62: Política, norma ou procedimento que: − assegure a pronta interrupção de irregularidades; − vise garantir a aplicação de medidas cautelares de afastamento de membros da alta administração suspeitos de envolvimento em atos de corrupção ou fraude; − indique as medidas disciplinares aplicáveis; − correlacione infrações das normas da empresa às penalidades previstas; − indique os responsáveis pela aplicação das medidas disciplinares − oriente a decisão sobre quando e como deve ser feito o encaminhamento às autoridades competentes de denúncias de irregularidades envolvendo funcionários, dirigentes, intermediários, fornecedores e prestadores de serviço; − oriente sobre quando e como deve ser feito o encaminhamento às autoridades competentes para ações de acolhimento e proteção das vítimas, bem como para a persecução e responsabilização dos envolvidos, nos casos de denúncias procedentes relacionadas a violações de direitos humanos.; POL-06 — Due Diligence de Terceiros | POL-10 — Investigações e Medidas Disciplinares | G62: 0.2 | H62: AG-FCG-QPE-192 | I62: RISCOS_TERCEIROS | J62: Desenho | K62: VIGENTE | L62: 16.1 | M62: ISO-24; ISO-40 | N62: XI
A63: QPE-193 | B63: 21.1.4 | C63: Pacto Brasil | D63: Canal de Denúncia e Medidas Disciplinares | E63: A empresa possui políticas e procedimentos que: correlacionam as medidas disciplinares ao tipo de infração cometida? | F63: Política, norma ou procedimento que: − assegure a pronta interrupção de irregularidades; − vise garantir a aplicação de medidas cautelares de afastamento de membros da alta administração suspeitos de envolvimento em atos de corrupção ou fraude; − indique as medidas disciplinares aplicáveis; − correlacione infrações das normas da empresa às penalidades previstas; − indique os responsáveis pela aplicação das medidas disciplinares − oriente a decisão sobre quando e como deve ser feito o encaminhamento às autoridades competentes de denúncias de irregularidades envolvendo funcionários, dirigentes, intermediários, fornecedores e prestadores de serviço; − oriente sobre quando e como deve ser feito o encaminhamento às autoridades competentes para ações de acolhimento e proteção das vítimas, bem como para a persecução e responsabilização dos envolvidos, nos casos de denúncias procedentes relacionadas a violações de direitos humanos.; POL-06 — Due Diligence de Terceiros | POL-10 — Investigações e Medidas Disciplinares | G63: 0.3 | H63: AG-FCG-QPE-193 | I63: RISCOS_TERCEIROS | J63: Desenho | K63: VIGENTE | L63: 16.2 | M63: ISO-24; ISO-40 | N63: XI
A64: QPE-198 | B64: 22.1.1 | C64: Pacto Brasil | D64: Monitoramento do Programa | E64: A empresa possui políticas e procedimentos que estabelecem: os responsáveis por realizar o monitoramento do programa de integridade? | F64: Normas internas que definam os mecanismos e procedimentos de monitoramento do programa de integridade e seus responsáveis, que: − definam os responsáveis pelo monitoramento do programa de integridade; − definam a periodicidade de monitoramento do programa de integridade; − definam as instâncias para as quais os dados e informações de monitoramento são submetidos. | G64: 0.2 | H64: AG-FCG-QPE-198 | I64: NORMATIVO | J64: Desenho | K64: VIGENTE | L64: 17.2.2 | M64: ISO-41; ISO-49 | N64: XV
A65: QPE-199 | B65: 22.1.2 | C65: Pacto Brasil | D65: Monitoramento do Programa | E65: A empresa possui políticas e procedimentos que estabelecem: a periodicidade para realização do monitoramento? | F65: Normas internas que definam os mecanismos e procedimentos de monitoramento do programa de integridade e seus responsáveis, que: − definam os responsáveis pelo monitoramento do programa de integridade; − definam a periodicidade de monitoramento do programa de integridade; − definam as instâncias para as quais os dados e informações de monitoramento são submetidos. | G65: 0.3 | H65: AG-FCG-QPE-199 | I65: NORMATIVO | J65: Desenho | K65: VIGENTE | L65: 17.2.1 | M65: ISO-41 | N65: XV
A66: QPE-201 | B66: 22.2.1 | C66: Pacto Brasil | D66: Monitoramento do Programa | E66: *A empresa realiza um monitoramento contínuo do programa de integridade por meio de: utilização de indicadores e estabelecimento de metas de desempenho sobre o programa de integridade, visando avaliar sua efetividade e cumprimento? (*Medida mínima prevista no art. 14 do Regulamento, de caráter obrigatório) | F66: Documentos contendo os indicadores e metas para o programa de integridade, incluindo ações de responsabilidade socioambiental e de proteção dos direitos humanos; | G66: 0.5 | H66: AG-FCG-QPE-201 | I66: EXECUCAO_CONTROLE | J66: Execução | K66: PERIODO | L66: 17.1; 17.2.4 | M66: ISO-18; ISO-41; ISO-43 | N66: XV
A67: QPE-202 | B67: 22.2.2 | C67: Pacto Brasil | D67: Monitoramento do Programa | E67: *A empresa realiza um monitoramento contínuo do programa de integridade por meio de: utilização de indicadores e estabelecimento de metas de desempenho relacionados com a sustentabilidade ambiental e com a proteção dos direitos humanos? | F67: Documentos, relatórios, dashboards e apresentações contendo registros das metas e do desempenho alcançado em cada período de acordo com os indicadores do programa de integridade incluindo suas ações de responsabilidade socioambiental e de proteção dos direitos humanos. | G67: 0.2 | H67: AG-FCG-QPE-202 | I67: EXECUCAO_CONTROLE | J67: Execução | K67: PERIODO | L67: 17.2.4 | M67: ISO-18; ISO-41; ISO-43 | N67: XV
A68: QPE-203 | B68: 22.2.3 | C68: Pacto Brasil | D68: Monitoramento do Programa | E68: *A empresa realiza um monitoramento contínuo do programa de integridade por meio de: análise estatística de dados relativos às denúncias recebidas pelos canais de denúncias e ao seu tratamento? | F68: Documentos, dashboards etc. contendo análise estatística de dados relativos às denúncias recebidas, bem como as medidas adotadas para o seu tratamento. | G68: 0.5 | H68: AG-FCG-QPE-203 | I68: GOVERNANCA | J68: Execução | K68: PERIODO | L68: 14.3 | M68: ISO-41; ISO-42 | N68: XV
A69: QPE-204 | B69: 22.2.4 | C69: Pacto Brasil | D69: Monitoramento do Programa | E69: *A empresa realiza um monitoramento contínuo do programa de integridade por meio de: relatórios periódicos com dados e estatísticas sobre aplicação das principais políticas e procedimentos de integridade? Se sim, esclarecer os tipos de relatórios produzidos, o conteúdo neles abordado e os sistemas/softwares eventualmente utilizados. | F69: Relatórios ou outros instrumentos que demonstrem que o monitoramento é realizado regularmente; Relatórios com o histórico (semestral, anual) do monitoramento, mostrando seus resultados ao longo de tempo; Prints de telas com dashboards ou outros sistemas informacionais de monitoramento contendo registros históricos. Apresentações realizadas em comitês e em reuniões com a respectiva ata. | G69: 1.3 | H69: AG-FCG-QPE-204 | I69: GOVERNANCA | J69: Execução | K69: PERIODO | L69: 17.2.3 | M69: ISO-41; ISO-44; ISO-49 | N69: XV
A70: QPE-205 | B70: 22.2.5 | C70: Pacto Brasil | D70: Monitoramento do Programa | E70: *A empresa realiza um monitoramento contínuo do programa de integridade por meio de: registro histórico do desempenho alcançado em cada período em relação às metas estabelecidas com base nos indicadores do programa de integridade? | F70: Documentos, dashboards, apresentações etc. contendo o registro histórico do desempenho alcançado em cada período em relação às metas e indicadores do programa de integridade. | G70: 0.9 | H70: AG-FCG-QPE-205 | I70: EXECUCAO_CONTROLE | J70: Execução | K70: PERIODO | L70: 17.2.3 | M70: ISO-41; ISO-43; ISO-45 | N70: XV
A71: QPE-207 | B71: 23.1.1 | C71: Pacto Brasil | D71: Transparência e Responsabilidade Socioambiental | E71: A empresa disponibiliza em seu site institucional, em português, informações completas e atualizadas sobre: as principais atividades exercidas? | F71: Links do site e caminho de navegação, desde a página inicial, para se encontrar as informações solicitadas nos itens. Observações: − Sobre as principais atividades exercidas, apresentar informações sobre o(s) setor(res) de atuação, bem como os bens, produtos e serviços ofertados; − Sobre a identificação dos proprietários e principais acionistas, a informação constante do link deve ser a mais clara e completa possível; − Sobre a identificação da função dos dirigentes, incluindo membros do Conselho de Administração, o link pode trazer a descrição dos cargos e apontar seus ocupantes, ou apresentar um organograma da empresa em que seja possível identificar estas informações; − Sobre a demonstrações financeiras, apresentar o link direto e o caminho no site para acessar essas informações; − Sobre a participação em licitações públicas, o link deve trazer informações (ainda que as mesmas constem do Portal da Transparência) como: ente público licitante, objeto e resultado do certame, incluindo as informações sobre licitação não vencidas; − Sobre os contratos firmados com a Administração Pública, o link deve trazer as seguintes informações (ainda que as mesmas constem do Portal da Transparência): partes contratantes, objeto, valor do contrato, prazo, etapa atual. − Sobre incentivos ou benefícios fiscais, espera-se visualizar informações sobre a natureza do incentivo ou benefício, valores, órgão ou entidade pública concedente, instrumento legal de concessão acompanhado das razões para enquadramento da empresa como beneficiária, prazo de concessão etc.; − Sobre as doações e patrocínios, espera-se visualizar informações sobre as entidades ou projetos beneficiados, objeto da doação ou patrocínio, data de realização, forma de monitoramento das doações e patrocínios realizados; − Sobre os relatórios, eles devem conter informações sobre as ações relacionadas ao programa de integridade promovidas pela empresa no ano de referência, tais como: i) informações sobre a aprovação ou atualização das principais políticas de integridade; (ii) eventuais alterações na estrutura das áreas e comitês relacionados diretamente ao tema integridade; (iii) treinamentos realizados no período e o número de funcionários alcançados por esses treinamentos; (iv) estatísticas dos canais de denúncia e as principais ações de fomento à integridade realizadas internamente e junto aos parceiros de negócio. − Sobre os critérios de integridade, espera-se encontrar as seguintes informações: i) os critérios estabelecidos; ii) os membros da alta direção aos quais são aplicados; iii) como são aplicados e em que momento; iv) como o cumprimento desses critérios é supervisionado; v) indicação expressa sobre a possibilidade de realização de denúncias, caso algum colaborador ou terceiro tenha ciência de acontecimento contrário aos critérios estabelecidos na política. − Sobre a estrutura da equipe que compõe a instância interna responsável pelo programa de integridade, apresentar evidências como organograma de reporte, documento que formalize a linha de reporte, cargo, atribuições e responsabilidades dos seus integrantes etc.; POL-04 — Doações, Patrocínios e Contribuições | POL-06 — Due Diligence de Terceiros | G71: 0.4 | H71: AG-FCG-QPE-207 | I71: PUBLICACAO_COMUNICACAO | J71: Publicação | K71: VIGENTE | L71: 19.2.1
A72: QPE-208 | B72: 23.1.2 | C72: Pacto Brasil | D72: Transparência e Responsabilidade Socioambiental | E72: A empresa disponibiliza em seu site institucional, em português, informações completas e atualizadas sobre: a identificação de seus proprietários ou principais acionistas? | F72: Links do site e caminho de navegação, desde a página inicial, para se encontrar as informações solicitadas nos itens. Observações: − Sobre as principais atividades exercidas, apresentar informações sobre o(s) setor(res) de atuação, bem como os bens, produtos e serviços ofertados; − Sobre a identificação dos proprietários e principais acionistas, a informação constante do link deve ser a mais clara e completa possível; − Sobre a identificação da função dos dirigentes, incluindo membros do Conselho de Administração, o link pode trazer a descrição dos cargos e apontar seus ocupantes, ou apresentar um organograma da empresa em que seja possível identificar estas informações; − Sobre a demonstrações financeiras, apresentar o link direto e o caminho no site para acessar essas informações; − Sobre a participação em licitações públicas, o link deve trazer informações (ainda que as mesmas constem do Portal da Transparência) como: ente público licitante, objeto e resultado do certame, incluindo as informações sobre licitação não vencidas; − Sobre os contratos firmados com a Administração Pública, o link deve trazer as seguintes informações (ainda que as mesmas constem do Portal da Transparência): partes contratantes, objeto, valor do contrato, prazo, etapa atual. − Sobre incentivos ou benefícios fiscais, espera-se visualizar informações sobre a natureza do incentivo ou benefício, valores, órgão ou entidade pública concedente, instrumento legal de concessão acompanhado das razões para enquadramento da empresa como beneficiária, prazo de concessão etc.; − Sobre as doações e patrocínios, espera-se visualizar informações sobre as entidades ou projetos beneficiados, objeto da doação ou patrocínio, data de realização, forma de monitoramento das doações e patrocínios realizados; − Sobre os relatórios, eles devem conter informações sobre as ações relacionadas ao programa de integridade promovidas pela empresa no ano de referência, tais como: i) informações sobre a aprovação ou atualização das principais políticas de integridade; (ii) eventuais alterações na estrutura das áreas e comitês relacionados diretamente ao tema integridade; (iii) treinamentos realizados no período e o número de funcionários alcançados por esses treinamentos; (iv) estatísticas dos canais de denúncia e as principais ações de fomento à integridade realizadas internamente e junto aos parceiros de negócio. − Sobre os critérios de integridade, espera-se encontrar as seguintes informações: i) os critérios estabelecidos; ii) os membros da alta direção aos quais são aplicados; iii) como são aplicados e em que momento; iv) como o cumprimento desses critérios é supervisionado; v) indicação expressa sobre a possibilidade de realização de denúncias, caso algum colaborador ou terceiro tenha ciência de acontecimento contrário aos critérios estabelecidos na política. − Sobre a estrutura da equipe que compõe a instância interna responsável pelo programa de integridade, apresentar evidências como organograma de reporte, documento que formalize a linha de reporte, cargo, atribuições e responsabilidades dos seus integrantes etc.; POL-04 — Doações, Patrocínios e Contribuições | POL-06 — Due Diligence de Terceiros | G72: 0.5 | H72: AG-FCG-QPE-208 | I72: PUBLICACAO_COMUNICACAO | J72: Publicação | K72: VIGENTE | L72: 19.2.2
A73: QPE-209 | B73: 23.1.3 | C73: Pacto Brasil | D73: Transparência e Responsabilidade Socioambiental | E73: A empresa disponibiliza em seu site institucional, em português, informações completas e atualizadas sobre: a identificação e função de seus executivos e dirigentes? | F73: Links do site e caminho de navegação, desde a página inicial, para se encontrar as informações solicitadas nos itens. Observações: − Sobre as principais atividades exercidas, apresentar informações sobre o(s) setor(res) de atuação, bem como os bens, produtos e serviços ofertados; − Sobre a identificação dos proprietários e principais acionistas, a informação constante do link deve ser a mais clara e completa possível; − Sobre a identificação da função dos dirigentes, incluindo membros do Conselho de Administração, o link pode trazer a descrição dos cargos e apontar seus ocupantes, ou apresentar um organograma da empresa em que seja possível identificar estas informações; − Sobre a demonstrações financeiras, apresentar o link direto e o caminho no site para acessar essas informações; − Sobre a participação em licitações públicas, o link deve trazer informações (ainda que as mesmas constem do Portal da Transparência) como: ente público licitante, objeto e resultado do certame, incluindo as informações sobre licitação não vencidas; − Sobre os contratos firmados com a Administração Pública, o link deve trazer as seguintes informações (ainda que as mesmas constem do Portal da Transparência): partes contratantes, objeto, valor do contrato, prazo, etapa atual. − Sobre incentivos ou benefícios fiscais, espera-se visualizar informações sobre a natureza do incentivo ou benefício, valores, órgão ou entidade pública concedente, instrumento legal de concessão acompanhado das razões para enquadramento da empresa como beneficiária, prazo de concessão etc.; − Sobre as doações e patrocínios, espera-se visualizar informações sobre as entidades ou projetos beneficiados, objeto da doação ou patrocínio, data de realização, forma de monitoramento das doações e patrocínios realizados; − Sobre os relatórios, eles devem conter informações sobre as ações relacionadas ao programa de integridade promovidas pela empresa no ano de referência, tais como: i) informações sobre a aprovação ou atualização das principais políticas de integridade; (ii) eventuais alterações na estrutura das áreas e comitês relacionados diretamente ao tema integridade; (iii) treinamentos realizados no período e o número de funcionários alcançados por esses treinamentos; (iv) estatísticas dos canais de denúncia e as principais ações de fomento à integridade realizadas internamente e junto aos parceiros de negócio. − Sobre os critérios de integridade, espera-se encontrar as seguintes informações: i) os critérios estabelecidos; ii) os membros da alta direção aos quais são aplicados; iii) como são aplicados e em que momento; iv) como o cumprimento desses critérios é supervisionado; v) indicação expressa sobre a possibilidade de realização de denúncias, caso algum colaborador ou terceiro tenha ciência de acontecimento contrário aos critérios estabelecidos na política. − Sobre a estrutura da equipe que compõe a instância interna responsável pelo programa de integridade, apresentar evidências como organograma de reporte, documento que formalize a linha de reporte, cargo, atribuições e responsabilidades dos seus integrantes etc.; POL-04 — Doações, Patrocínios e Contribuições | POL-06 — Due Diligence de Terceiros | G73: 0.6 | H73: AG-FCG-QPE-209 | I73: PUBLICACAO_COMUNICACAO | J73: Publicação | K73: VIGENTE | L73: 19.2.2
A74: QPE-211 | B74: 23.1.5 | C74: Pacto Brasil | D74: Transparência e Responsabilidade Socioambiental | E74: A empresa disponibiliza em seu site institucional, em português, informações completas e atualizadas sobre: as participações em licitações públicas? | F74: Links do site e caminho de navegação, desde a página inicial, para se encontrar as informações solicitadas nos itens. Observações: − Sobre as principais atividades exercidas, apresentar informações sobre o(s) setor(res) de atuação, bem como os bens, produtos e serviços ofertados; − Sobre a identificação dos proprietários e principais acionistas, a informação constante do link deve ser a mais clara e completa possível; − Sobre a identificação da função dos dirigentes, incluindo membros do Conselho de Administração, o link pode trazer a descrição dos cargos e apontar seus ocupantes, ou apresentar um organograma da empresa em que seja possível identificar estas informações; − Sobre a demonstrações financeiras, apresentar o link direto e o caminho no site para acessar essas informações; − Sobre a participação em licitações públicas, o link deve trazer informações (ainda que as mesmas constem do Portal da Transparência) como: ente público licitante, objeto e resultado do certame, incluindo as informações sobre licitação não vencidas; − Sobre os contratos firmados com a Administração Pública, o link deve trazer as seguintes informações (ainda que as mesmas constem do Portal da Transparência): partes contratantes, objeto, valor do contrato, prazo, etapa atual. − Sobre incentivos ou benefícios fiscais, espera-se visualizar informações sobre a natureza do incentivo ou benefício, valores, órgão ou entidade pública concedente, instrumento legal de concessão acompanhado das razões para enquadramento da empresa como beneficiária, prazo de concessão etc.; − Sobre as doações e patrocínios, espera-se visualizar informações sobre as entidades ou projetos beneficiados, objeto da doação ou patrocínio, data de realização, forma de monitoramento das doações e patrocínios realizados; − Sobre os relatórios, eles devem conter informações sobre as ações relacionadas ao programa de integridade promovidas pela empresa no ano de referência, tais como: i) informações sobre a aprovação ou atualização das principais políticas de integridade; (ii) eventuais alterações na estrutura das áreas e comitês relacionados diretamente ao tema integridade; (iii) treinamentos realizados no período e o número de funcionários alcançados por esses treinamentos; (iv) estatísticas dos canais de denúncia e as principais ações de fomento à integridade realizadas internamente e junto aos parceiros de negócio. − Sobre os critérios de integridade, espera-se encontrar as seguintes informações: i) os critérios estabelecidos; ii) os membros da alta direção aos quais são aplicados; iii) como são aplicados e em que momento; iv) como o cumprimento desses critérios é supervisionado; v) indicação expressa sobre a possibilidade de realização de denúncias, caso algum colaborador ou terceiro tenha ciência de acontecimento contrário aos critérios estabelecidos na política. − Sobre a estrutura da equipe que compõe a instância interna responsável pelo programa de integridade, apresentar evidências como organograma de reporte, documento que formalize a linha de reporte, cargo, atribuições e responsabilidades dos seus integrantes etc.; POL-04 — Doações, Patrocínios e Contribuições | POL-06 — Due Diligence de Terceiros | G74: 0.6 | H74: AG-FCG-QPE-211 | I74: PUBLICACAO_COMUNICACAO | J74: Publicação | K74: VIGENTE | L74: 19.2.3
A75: QPE-212 | B75: 23.1.6 | C75: Pacto Brasil | D75: Transparência e Responsabilidade Socioambiental | E75: A empresa disponibiliza em seu site institucional, em português, informações completas e atualizadas sobre: os contratos firmados com a Administração Pública? | F75: Links do site e caminho de navegação, desde a página inicial, para se encontrar as informações solicitadas nos itens. Observações: − Sobre as principais atividades exercidas, apresentar informações sobre o(s) setor(res) de atuação, bem como os bens, produtos e serviços ofertados; − Sobre a identificação dos proprietários e principais acionistas, a informação constante do link deve ser a mais clara e completa possível; − Sobre a identificação da função dos dirigentes, incluindo membros do Conselho de Administração, o link pode trazer a descrição dos cargos e apontar seus ocupantes, ou apresentar um organograma da empresa em que seja possível identificar estas informações; − Sobre a demonstrações financeiras, apresentar o link direto e o caminho no site para acessar essas informações; − Sobre a participação em licitações públicas, o link deve trazer informações (ainda que as mesmas constem do Portal da Transparência) como: ente público licitante, objeto e resultado do certame, incluindo as informações sobre licitação não vencidas; − Sobre os contratos firmados com a Administração Pública, o link deve trazer as seguintes informações (ainda que as mesmas constem do Portal da Transparência): partes contratantes, objeto, valor do contrato, prazo, etapa atual. − Sobre incentivos ou benefícios fiscais, espera-se visualizar informações sobre a natureza do incentivo ou benefício, valores, órgão ou entidade pública concedente, instrumento legal de concessão acompanhado das razões para enquadramento da empresa como beneficiária, prazo de concessão etc.; − Sobre as doações e patrocínios, espera-se visualizar informações sobre as entidades ou projetos beneficiados, objeto da doação ou patrocínio, data de realização, forma de monitoramento das doações e patrocínios realizados; − Sobre os relatórios, eles devem conter informações sobre as ações relacionadas ao programa de integridade promovidas pela empresa no ano de referência, tais como: i) informações sobre a aprovação ou atualização das principais políticas de integridade; (ii) eventuais alterações na estrutura das áreas e comitês relacionados diretamente ao tema integridade; (iii) treinamentos realizados no período e o número de funcionários alcançados por esses treinamentos; (iv) estatísticas dos canais de denúncia e as principais ações de fomento à integridade realizadas internamente e junto aos parceiros de negócio. − Sobre os critérios de integridade, espera-se encontrar as seguintes informações: i) os critérios estabelecidos; ii) os membros da alta direção aos quais são aplicados; iii) como são aplicados e em que momento; iv) como o cumprimento desses critérios é supervisionado; v) indicação expressa sobre a possibilidade de realização de denúncias, caso algum colaborador ou terceiro tenha ciência de acontecimento contrário aos critérios estabelecidos na política. − Sobre a estrutura da equipe que compõe a instância interna responsável pelo programa de integridade, apresentar evidências como organograma de reporte, documento que formalize a linha de reporte, cargo, atribuições e responsabilidades dos seus integrantes etc.; POL-04 — Doações, Patrocínios e Contribuições | POL-06 — Due Diligence de Terceiros | G75: 0.6 | H75: AG-FCG-QPE-212 | I75: PUBLICACAO_COMUNICACAO | J75: Publicação | K75: VIGENTE | L75: 19.2.4
A76: QPE-214 | B76: 23.1.8 | C76: Pacto Brasil | D76: Transparência e Responsabilidade Socioambiental | E76: A empresa disponibiliza em seu site institucional, em português, informações completas e atualizadas sobre: os patrocínios e doações realizados ou informa explicitamente que não realiza tais ações? | F76: Links do site e caminho de navegação, desde a página inicial, para se encontrar as informações solicitadas nos itens. Observações: − Sobre as principais atividades exercidas, apresentar informações sobre o(s) setor(res) de atuação, bem como os bens, produtos e serviços ofertados; − Sobre a identificação dos proprietários e principais acionistas, a informação constante do link deve ser a mais clara e completa possível; − Sobre a identificação da função dos dirigentes, incluindo membros do Conselho de Administração, o link pode trazer a descrição dos cargos e apontar seus ocupantes, ou apresentar um organograma da empresa em que seja possível identificar estas informações; − Sobre a demonstrações financeiras, apresentar o link direto e o caminho no site para acessar essas informações; − Sobre a participação em licitações públicas, o link deve trazer informações (ainda que as mesmas constem do Portal da Transparência) como: ente público licitante, objeto e resultado do certame, incluindo as informações sobre licitação não vencidas; − Sobre os contratos firmados com a Administração Pública, o link deve trazer as seguintes informações (ainda que as mesmas constem do Portal da Transparência): partes contratantes, objeto, valor do contrato, prazo, etapa atual. − Sobre incentivos ou benefícios fiscais, espera-se visualizar informações sobre a natureza do incentivo ou benefício, valores, órgão ou entidade pública concedente, instrumento legal de concessão acompanhado das razões para enquadramento da empresa como beneficiária, prazo de concessão etc.; − Sobre as doações e patrocínios, espera-se visualizar informações sobre as entidades ou projetos beneficiados, objeto da doação ou patrocínio, data de realização, forma de monitoramento das doações e patrocínios realizados; − Sobre os relatórios, eles devem conter informações sobre as ações relacionadas ao programa de integridade promovidas pela empresa no ano de referência, tais como: i) informações sobre a aprovação ou atualização das principais políticas de integridade; (ii) eventuais alterações na estrutura das áreas e comitês relacionados diretamente ao tema integridade; (iii) treinamentos realizados no período e o número de funcionários alcançados por esses treinamentos; (iv) estatísticas dos canais de denúncia e as principais ações de fomento à integridade realizadas internamente e junto aos parceiros de negócio. − Sobre os critérios de integridade, espera-se encontrar as seguintes informações: i) os critérios estabelecidos; ii) os membros da alta direção aos quais são aplicados; iii) como são aplicados e em que momento; iv) como o cumprimento desses critérios é supervisionado; v) indicação expressa sobre a possibilidade de realização de denúncias, caso algum colaborador ou terceiro tenha ciência de acontecimento contrário aos critérios estabelecidos na política. − Sobre a estrutura da equipe que compõe a instância interna responsável pelo programa de integridade, apresentar evidências como organograma de reporte, documento que formalize a linha de reporte, cargo, atribuições e responsabilidades dos seus integrantes etc.; POL-04 — Doações, Patrocínios e Contribuições | POL-06 — Due Diligence de Terceiros | G76: 0.2 | H76: AG-FCG-QPE-214 | I76: PUBLICACAO_COMUNICACAO | J76: Publicação | K76: VIGENTE | L76: 19.2.5; 19.2.6 | M76: ISO-37 | N76: XIII
A77: QPE-215 | B77: 23.1.9 | C77: Pacto Brasil | D77: Transparência e Responsabilidade Socioambiental | E77: A empresa disponibiliza em seu site institucional, em português, informações completas e atualizadas sobre: o relatório periódico com informações relativas ao programa de integridade (relatório de sustentabilidade / relatório de integridade/ relato integrado/relatório anual)? | F77: Links do site e caminho de navegação, desde a página inicial, para se encontrar as informações solicitadas nos itens. Observações: − Sobre as principais atividades exercidas, apresentar informações sobre o(s) setor(res) de atuação, bem como os bens, produtos e serviços ofertados; − Sobre a identificação dos proprietários e principais acionistas, a informação constante do link deve ser a mais clara e completa possível; − Sobre a identificação da função dos dirigentes, incluindo membros do Conselho de Administração, o link pode trazer a descrição dos cargos e apontar seus ocupantes, ou apresentar um organograma da empresa em que seja possível identificar estas informações; − Sobre a demonstrações financeiras, apresentar o link direto e o caminho no site para acessar essas informações; − Sobre a participação em licitações públicas, o link deve trazer informações (ainda que as mesmas constem do Portal da Transparência) como: ente público licitante, objeto e resultado do certame, incluindo as informações sobre licitação não vencidas; − Sobre os contratos firmados com a Administração Pública, o link deve trazer as seguintes informações (ainda que as mesmas constem do Portal da Transparência): partes contratantes, objeto, valor do contrato, prazo, etapa atual. − Sobre incentivos ou benefícios fiscais, espera-se visualizar informações sobre a natureza do incentivo ou benefício, valores, órgão ou entidade pública concedente, instrumento legal de concessão acompanhado das razões para enquadramento da empresa como beneficiária, prazo de concessão etc.; − Sobre as doações e patrocínios, espera-se visualizar informações sobre as entidades ou projetos beneficiados, objeto da doação ou patrocínio, data de realização, forma de monitoramento das doações e patrocínios realizados; − Sobre os relatórios, eles devem conter informações sobre as ações relacionadas ao programa de integridade promovidas pela empresa no ano de referência, tais como: i) informações sobre a aprovação ou atualização das principais políticas de integridade; (ii) eventuais alterações na estrutura das áreas e comitês relacionados diretamente ao tema integridade; (iii) treinamentos realizados no período e o número de funcionários alcançados por esses treinamentos; (iv) estatísticas dos canais de denúncia e as principais ações de fomento à integridade realizadas internamente e junto aos parceiros de negócio. − Sobre os critérios de integridade, espera-se encontrar as seguintes informações: i) os critérios estabelecidos; ii) os membros da alta direção aos quais são aplicados; iii) como são aplicados e em que momento; iv) como o cumprimento desses critérios é supervisionado; v) indicação expressa sobre a possibilidade de realização de denúncias, caso algum colaborador ou terceiro tenha ciência de acontecimento contrário aos critérios estabelecidos na política. − Sobre a estrutura da equipe que compõe a instância interna responsável pelo programa de integridade, apresentar evidências como organograma de reporte, documento que formalize a linha de reporte, cargo, atribuições e responsabilidades dos seus integrantes etc.; POL-04 — Doações, Patrocínios e Contribuições | POL-06 — Due Diligence de Terceiros | G77: 0.2 | H77: AG-FCG-QPE-215 | I77: PUBLICACAO_COMUNICACAO | J77: Publicação | K77: VIGENTE | L77: 19.2.8
A78: QPE-216 | B78: 23.1.10 | C78: Pacto Brasil | D78: Transparência e Responsabilidade Socioambiental | E78: A empresa disponibiliza em seu site institucional, em português, informações completas e atualizadas sobre: os critérios de integridade incluídos na política de remuneração variável para os membros da alta direção? | F78: Links do site e caminho de navegação, desde a página inicial, para se encontrar as informações solicitadas nos itens. Observações: − Sobre as principais atividades exercidas, apresentar informações sobre o(s) setor(res) de atuação, bem como os bens, produtos e serviços ofertados; − Sobre a identificação dos proprietários e principais acionistas, a informação constante do link deve ser a mais clara e completa possível; − Sobre a identificação da função dos dirigentes, incluindo membros do Conselho de Administração, o link pode trazer a descrição dos cargos e apontar seus ocupantes, ou apresentar um organograma da empresa em que seja possível identificar estas informações; − Sobre a demonstrações financeiras, apresentar o link direto e o caminho no site para acessar essas informações; − Sobre a participação em licitações públicas, o link deve trazer informações (ainda que as mesmas constem do Portal da Transparência) como: ente público licitante, objeto e resultado do certame, incluindo as informações sobre licitação não vencidas; − Sobre os contratos firmados com a Administração Pública, o link deve trazer as seguintes informações (ainda que as mesmas constem do Portal da Transparência): partes contratantes, objeto, valor do contrato, prazo, etapa atual. − Sobre incentivos ou benefícios fiscais, espera-se visualizar informações sobre a natureza do incentivo ou benefício, valores, órgão ou entidade pública concedente, instrumento legal de concessão acompanhado das razões para enquadramento da empresa como beneficiária, prazo de concessão etc.; − Sobre as doações e patrocínios, espera-se visualizar informações sobre as entidades ou projetos beneficiados, objeto da doação ou patrocínio, data de realização, forma de monitoramento das doações e patrocínios realizados; − Sobre os relatórios, eles devem conter informações sobre as ações relacionadas ao programa de integridade promovidas pela empresa no ano de referência, tais como: i) informações sobre a aprovação ou atualização das principais políticas de integridade; (ii) eventuais alterações na estrutura das áreas e comitês relacionados diretamente ao tema integridade; (iii) treinamentos realizados no período e o número de funcionários alcançados por esses treinamentos; (iv) estatísticas dos canais de denúncia e as principais ações de fomento à integridade realizadas internamente e junto aos parceiros de negócio. − Sobre os critérios de integridade, espera-se encontrar as seguintes informações: i) os critérios estabelecidos; ii) os membros da alta direção aos quais são aplicados; iii) como são aplicados e em que momento; iv) como o cumprimento desses critérios é supervisionado; v) indicação expressa sobre a possibilidade de realização de denúncias, caso algum colaborador ou terceiro tenha ciência de acontecimento contrário aos critérios estabelecidos na política. − Sobre a estrutura da equipe que compõe a instância interna responsável pelo programa de integridade, apresentar evidências como organograma de reporte, documento que formalize a linha de reporte, cargo, atribuições e responsabilidades dos seus integrantes etc.; POL-04 — Doações, Patrocínios e Contribuições | POL-06 — Due Diligence de Terceiros | G78: 0.1 | H78: AG-FCG-QPE-216 | I78: PUBLICACAO_COMUNICACAO | J78: Publicação | K78: VIGENTE | L78: 19.2.7
A79: QPE-222 | B79: 24.4 | C79: Pacto Brasil | D79: Transparência e Responsabilidade Socioambiental | E79: A empresa participa de iniciativas coletivas ou divulga ao público externo ações que promovam a proteção dos direitos humanos? | F79: Divulgações voltadas ao público externo, promovendo a proteção dos direitos humanos. Isso inclui artigos em jornais, entrevistas, comunicados, e-mails, mensagens no site da empresa e em mídias sociais. Link da internet e/ou documento de adesão à ação coletiva assinado pela instituição promotora e pela empresa, em que conste a associação da empresa com ações coletivas voltadas à proteção dos direitos humanos. | G79: 0.1 | H79: AG-FCG-QPE-222 | I79: PUBLICACAO_COMUNICACAO | J79: Execução | K79: PERIODO | L79: 18.2
A80: QPE-223 | B80: 24.5 | C80: Pacto Brasil | D80: Transparência e Responsabilidade Socioambiental | E80: A empresa participa de iniciativas coletivas ou divulga ao público externo ações que promovam o desenvolvimento sustentável, a preservação do meio ambiente e a mitigação ou adaptação às mudanças climáticas? | F80: Divulgações voltadas ao público externo, promovendo a proteção ao meio ambiente, ações de desenvolvimento sustentável e o combate às mudanças climáticas. Isso inclui artigos em jornais, entrevistas, comunicados, e-mails, mensagens no site da empresa e em mídias sociais. Link da internet e/ou documento de adesão à ação coletiva assinado pela instituição promotora e pela empresa, em que conste a associação da empresa com ações coletivas voltadas à proteção ao meio ambiente, a ações de desenvolvimento sustentável e de combate às mudanças climáticas. | G80: 0.1 | H80: AG-FCG-QPE-223 | I80: PUBLICACAO_COMUNICACAO | J80: Execução | K80: PERIODO | L80: 19.2.8
E82: Total de perguntas / pontos | F82: =COUNTA(A5:A80) -> 76 | G82: =SUM(G5:G80) -> 35.5

Sheet III_PROETICA_137
A1: Etapa III · Complemento do Pró-Ética — 137 perguntas novas
A2: Fonte: portal (DB.Q trilha Pró-Ética).
A4: ID | B4: Nº formulário | C4: Trilha | D4: Área | E4: Pergunta | F4: Evidência sugerida | G4: Peso (pts) | H4: Agente | I4: Tipo de verificação | J4: Natureza | K4: Janela | L4: Itens do Pacto | M4: Itens ISO | N4: Incisos art. 57 | O4: Licitações? | P4: Medida essencial (ITP)
A5: QPE-003 | B5: 1.3 | C5: Pró-Ética | D5: Comprometimento da Alta Direção | E5: Os critérios de integridade aplicados no processo de seleção de membros da alta direção são divulgados para o público interno da empresa? Se sim, informar como é feita essa divulgação. | F5: Comunicados e publicações internas informando os critérios de integridade aplicados, tais como e-mails, vídeos, reuniões e eventos, divulgações no site/intranet ou por meios físicos etc. | G5: 0.1 | H5: AG-FCG-QPE-003 | I5: PUBLICACAO_COMUNICACAO | J5: Desenho | K5: VIGENTE | N5: I
A6: QPE-007 | B6: 2.3 | C6: Pró-Ética | D6: Comprometimento da Alta Direção | E6: A avaliação dos relatórios periódicos pela alta direção considera tanto aspectos quantitativos quanto qualitativos de aplicação do programa de integridade? | F6: Documentos que indiquem a forma como a alta direção avalia os relatórios periódicos do programa de integridade, tais como: − atas de reuniões entre membros da alta direção e responsáveis pelas atividades do programa de integridade, documentos, relatórios e recomendações, com análises quantitativas (dados numéricos) e qualitativas (relatórios críticos, escalas explicativas ou palavras descritivas). | G6: 0.5 | H6: AG-FCG-QPE-007 | I6: GOVERNANCA | J6: Execução | K6: PERIODO | M6: ISO-08; ISO-44; ISO-47 | N6: I
A7: QPE-008 | B7: 2.4 | C7: Pró-Ética | D7: Comprometimento da Alta Direção | E7: A empresa possui em sua estrutura organizacional órgão(s) colegiado(s) para tratar de temas de ética e integridade que contam com a participação de membros da alta direção, como comitês e conselhos de ética? | F7: Documentos que demonstrem a existência de órgão colegiado responsável por tratar de temas relacionados ao programa de integridade, como estatutos, regimentos, políticas internas, atas, e que indiquem a participação ativa dos membros da alta direção nesse colegiado. | G7: 0.5 | H7: AG-FCG-QPE-008 | I7: GOVERNANCA | J7: Desenho | K7: VIGENTE | M7: ISO-08 | N7: I
A8: QPE-009 | B8: 2.4.1 | C8: Pró-Ética | D8: Comprometimento da Alta Direção | E8: Os membros da alta direção que integram esse(s) órgão(s) são qualificados para tratar do tema integridade ou receberam capacitação específica em compliance para participar do colegiado? | F8: Documentos que comprovem a qualificação ou realização de treinamentos relevantes para que os membros da alta direção possam exercer de forma adequada suas atribuições no colegiado que trata de temas de ética e integridade (currículo, listas de presença acompanhadas dos materiais de apoio dos treinamentos, fotos, vídeos, certificados). | G8: 0.7 | H8: AG-FCG-QPE-009 | I8: TREINAMENTO | J8: Desenho | K8: VIGENTE | M8: ISO-21 | N8: I
A9: QPE-010 | B9: 2.4.2 | C9: Pró-Ética | D9: Comprometimento da Alta Direção | E9: Os membros da alta direção que integram esse(s) órgão(s) receberam capacitação específica em temas relacionados com o combate ao preconceito, à discriminação e ao assédio de qualquer natureza para participar do colegiado? | F9: Documentos que evidenciam a qualificação ou treinamentos realizados pela alta direção para atuar adequadamente em temas relacionados com o combate ao preconceito, à discriminação e ao assédio de qualquer natureza, incluindo currículo, listas de presença, materiais de apoio dos treinamentos, fotos, vídeos e certificados. | G9: 0.1 | H9: AG-FCG-QPE-010 | I9: TREINAMENTO | J9: Execução | K9: PERIODO | M9: ISO-21 | N9: I
A10: QPE-011 | B10: 2.4.3 | C10: Pró-Ética | D10: Comprometimento da Alta Direção | E10: A forma como ocorre a participação dos membros da alta direção nesse(s) órgão(s) está formalizada em regimento próprio ou documento equivalente? Se sim, detalhar sua composição, suas atribuições e a periodicidade de reuniões. | F10: Documentos que demonstrem como ocorre a participação da alta direção no órgão colegiado (competências, atribuições, composição, quórum para decisão, periodicidade de reuniões) responsável por tratar de temas relacionados ao programa de integridade, como estatutos, regimentos, políticas internas, atas. | G10: 0.3 | H10: AG-FCG-QPE-011 | I10: GOVERNANCA | J10: Desenho | K10: VIGENTE | M10: ISO-08 | N10: I
A11: QPE-012 | B11: 2.4.4 | C11: Pró-Ética | D11: Comprometimento da Alta Direção | E11: Foram apresentados documentos que comprovem a realização de mais de 2 (duas) reuniões desse(s) órgão(s) no período avaliado? | F11: Atas, comunicações internas ou outros documentos que comprovem a realização de reuniões do colegiado para tratar de temas de ética e integridade e que contem com a participação de membros da alta direção. | G11: 1 | H11: AG-FCG-QPE-012 | I11: PUBLICACAO_COMUNICACAO | J11: Execução | K11: PERIODO | M11: ISO-08; ISO-48 | N11: I
A12: QPE-015 | B12: 3.2.1 | C12: Pró-Ética | D12: Comprometimento da Alta Direção | E12: As manifestações de apoio ao programa de integridade: são feitas por diferentes membros da alta direção da empresa avaliada, incluindo integrantes do Conselho de Administração, quando for o caso? | F12: Manifestações de apoio ao programa de integridade emitidas por diferentes membros da alta direção para demonstrar seu comprometimento. | G12: 0.7 | H12: AG-FCG-QPE-015 | I12: GOVERNANCA | J12: Execução | K12: PERIODO | M12: ISO-09 | N12: I
A13: QPE-016 | B13: 3.2.2 | C13: Pró-Ética | D13: Comprometimento da Alta Direção | E13: As manifestações de apoio ao programa de integridade: São feitas por membros da média gerência da empresa avaliada? | F13: Manifestações de apoio ao programa de integridade realizada por gerentes, supervisores, coordenadores, chefes de setor, diretores adjuntos e outros líderes da média gerência, reforçando o compromisso da empresa com a ética e a transparência em todos os níveis da empresa. | G13: 0.4 | H13: AG-FCG-QPE-016 | I13: EXECUCAO_CONTROLE | J13: Execução | K13: PERIODO | M13: ISO-09 | N13: I
A14: QPE-017 | B14: 3.2.3 | C14: Pró-Ética | D14: Comprometimento da Alta Direção | E14: As manifestações de apoio ao programa de integridade: são realizadas de forma periódica com comprovação de, ao menos, 4 (quatro) manifestações no período avaliado? | F14: ao menos, 4 (quatro) manifestações no período avaliado?, Evidências de pelo menos 4 (quatro) manifestações públicas no período avaliado. | G14: 0.8 | H14: AG-FCG-QPE-017 | I14: EXECUCAO_CONTROLE | J14: Execução | K14: PERIODO | M14: ISO-09 | N14: I
A15: QPE-018 | B15: 3.2.4 | C15: Pró-Ética | D15: Comprometimento da Alta Direção | E15: As manifestações de apoio ao programa de integridade: são divulgadas por diferentes meios para alcançar o público interno da empresa em toda sua diversidade? | F15: Correlação entre os diversos públicos de empregados da empresa com os meios de divulgação das manifestações ao programa de integridade, tais como e-mails, cartazes, comunicados, mídia social, intranet etc. | G15: 0.7 | H15: AG-FCG-QPE-018 | I15: PUBLICACAO_COMUNICACAO | J15: Execução | K15: PERIODO | M15: ISO-09 | N15: I
A16: QPE-021 | B16: 3.2.7 | C16: Pró-Ética | D16: Comprometimento da Alta Direção | E16: As manifestações de apoio ao programa de integridade: alcançam o público externo da empresa, o que inclui a sua participação em ações coletivas relacionadas ao tema integridade e prevenção da corrupção? | F16: Material relacionado a manifestações públicas da alta direção ao público externo, promovendo o comportamento ético e demonstrando o compromisso da empresa com a prevenção e o combate à corrupção, como artigos, entrevistas, publicações online, postagens institucionais, além de links ou documentos que comprovem a adesão da empresa a iniciativas coletivas de integridade. | G16: 0.7 | H16: AG-FCG-QPE-021 | I16: PUBLICACAO_COMUNICACAO | J16: Execução | K16: PERIODO | M16: ISO-09 | N16: I
A17: QPE-022 | B17: 3.3 | C17: Pró-Ética | D17: Comprometimento da Alta Direção | E17: A empresa elabora orçamento que contemple recursos destinados às atividades da área responsável pelo programa de integridade, aprovado pela alta direção, antes de cada exercício? | F17: aprovado pela alta direção, antes de cada exercício?, Documentos que comprovem a elaboração de orçamento para as atividades da área de integridade, como atas de reuniões, aprovações formais, estudos ou notas técnicas. | G17: 0.8 | H17: AG-FCG-QPE-022 | I17: GOVERNANCA | J17: Execução | K17: PERIODO | M17: ISO-09; ISO-20 | N17: I
... A22: QPE-029 | B22: 4.2.5 | C22: Pró-Ética | D22: Instância Responsável pelo Programa | E22: A instância interna responsável pelo programa de integridade: possui estrutura independente, não estando subordinada a outro departamento da empresa – jurídico, auditoria, RH etc.? | F22: Documento como política ou procedimento que formalize tal estrutura, organograma da empresa que demonstre a posição hierárquica e as linhas de reporte da área de integridade. | G22: 1.4 | H22: AG-FCG-QPE-029 | I22: NORMATIVO | J22: Desenho | K22: VIGENTE | M22: ISO-11; ISO-14 | N22: IX
A23: QPE-030 | B23: 4.2.6 | C23: Pró-Ética | D23: Instância Responsável pelo Programa | E23: A instância interna responsável pelo programa de integridade: conta com quantitativo de funcionários proporcional às atribuições conferidas à área, incluindo representantes nas diferentes localidades em que a empresa atua (quando for o caso)? (questão direcionada ao avaliador) | F23: Informação não especificada na fonte; pendente de confirmação por pergunta. | G23: 1.5 | H23: AG-FCG-QPE-030 | I23: EXECUCAO_CONTROLE | J23: Avaliador | M23: ISO-14; ISO-20 | N23: IX
A24: QPE-031 | B24: 4.2.7 | C24: Pró-Ética | D24: Instância Responsável pelo Programa | E24: A instância interna responsável pelo programa de integridade: faz uso de inteligência artificial (IA) na execução de suas atividades? Se sim, descrever a ferramenta e como ela é aplicada. (questão sem pontuação) | F24: Documentos que comprovem a utilização de inteligência artificial no planejamento ou na execução das atividades relacionadas ao programa de integridade, detalhando a ferramenta empregada, sua aplicação específica e como ela contribui para a gestão e eficiência do programa. | G24: 0 | H24: AG-FCG-QPE-031 | I24: EXECUCAO_CONTROLE | J24: Desenho | K24: VIGENTE | M24: ISO-20 | N24: IX
A25: QPE-032 | B25: 4.2.8 | C25: Pró-Ética | D25: Instância Responsável pelo Programa | E25: A instância interna responsável pelo programa de integridade: recebeu, no período avaliado, capacitação específica em temas relacionados com o combate ao preconceito, à discriminação e ao assédio de qualquer natureza? | F25: Documentos que comprovem a qualificação ou realização de treinamentos relevantes sobre os temas descritos para os membros e colaboradores da instância interna responsável pelo programa de integridade, como: currículo, listas de presença acompanhadas do material didático utilizado, fotos, vídeos, certificados e outros comprovantes. | G25: 0.1 | H25: AG-FCG-QPE-032 | I25: TREINAMENTO | J25: Execução | K25: PERIODO | M25: ISO-14; ISO-21 | N25: IX
A26: QPE-033 | B26: 5.1 | C26: Pró-Ética | D26: Instância Responsável pelo Programa | E26: O responsável pela instância interna possui como prerrogativa a possibilidade de se reportar diretamente ao nível hierárquico mais elevado da empresa – no Brasil e no exterior, quando for o caso? | F26: Documento formal (ex.: estatuto, regimento interno e política de integridade) especificando as garantias aplicadas à área responsável pelo programa de integridade, incluindo a confirmação de que a área reporta diretamente ao mais alto nível hierárquico da empresa no Brasil ou exterior, conforme o caso. | G26: 1 | H26: AG-FCG-QPE-033 | I26: NORMATIVO | J26: Desenho | K26: VIGENTE | M26: ISO-11; ISO-14 | N26: IX
A27: QPE-034 | B27: 5.1.1 | C27: Pró-Ética | D27: Instância Responsável pelo Programa | E27: Essa prerrogativa é de fato exercida, tendo o representante da instância interna responsável pelo programa se reunido com o nível hierárquico mais elevado da empresa pelo menos 4 (quatro) vezes no período avaliado? | F27: Documentos que comprovem o reporte direto, tais como atas de reuniões, entre a instância de integridade e a alta direção da empresa, compreendendo ainda a apresentação de relatórios, estudos, e proposições submetidas à apreciação/conhecimento da alta direção. | G27: 1.5 | H27: AG-FCG-QPE-034 | I27: GOVERNANCA | J27: Execução | K27: PERIODO | M27: ISO-11; ISO-14; ISO-44; ISO-49 | N27: IX
A28: QPE-035 | B28: 5.2 | C28: Pró-Ética | D28: Instância Responsável pelo Programa | E28: O responsável pela instância interna possui garantias expressas que possibilitam o exercício das suas atribuições com independência e autoridade? | F28: Documento formal (ex.: estatuto, regimento interno, política de integridade, job description) especificando as garantias aplicadas à área responsável pelo programa de integridade, tais como: validade e execução de suas decisões; independência na investigação e apuração das acusações e casos de violações éticas/legais; permissão de acesso a documentos e pessoas de diferentes departamentos da empresa; proteção contra punições arbitrárias; mandato; remuneração compatível com cargos de igual posição hierárquica etc.; POL-10 — Investigações e Medidas Disciplinares | G28: 1.8 | H28: AG-FCG-QPE-035 | I28: NORMATIVO | J28: Desenho | K28: VIGENTE | M28: ISO-11; ISO-14 | N28: IX
A29: QPE-036 | B29: 5.3 | C29: Pró-Ética | D29: Instância Responsável pelo Programa | E29: O responsável pela instância interna atua diretamente ou como instância supervisora na investigação e apuração de situações que configurem violações éticas ou legais? | F29: Documento formal (ex.: estatuto, regimento interno, política de integridade, job description) que indique, no fluxo de tratamento de investigações e apurações de violações éticas e legais, que a instância de integridade atua diretamente ou supervisiona-o.; POL-10 — Investigações e Medidas Disciplinares | G29: 1 | H29: AG-FCG-QPE-036 | I29: GOVERNANCA | J29: Execução | K29: PERIODO | M29: ISO-40 | N29: IX
A30: QPE-039 | B30: 6.1.2 | C30: Pró-Ética | D30: Gestão de Riscos para a Integridade | E30: A política ou planejamento que trata da gestão de riscos determina a área ou pessoa responsável pela gestão de riscos? | F30: determinação da área ou pessoa responsável pela gestão de riscos;; Documento normativo do tema explicitamente citado na pergunta; não atribuir automaticamente uma das 11 políticas essenciais. | G30: 0.6 | H30: AG-FCG-QPE-039 | I30: RISCOS_TERCEIROS | J30: Desenho | K30: VIGENTE | M30: ISO-07; ISO-13 | N30: V
A31: QPE-040 | B31: 6.1.3 | C31: Pró-Ética | D31: Gestão de Riscos para a Integridade | E31: A política ou planejamento que trata da gestão de riscos contém evidências de sua aprovação pela alta direção? | F31: evidências de sua aprovação pela alta direção, como atas de normas, atas de reunião ou planejamento da empresa que incluem e detalham revisões e aprovação, por parte da alta direção, na gestão dos riscos em virtude de novos riscos identificados, ou de alteração na análise de impacto e probabilidade.; Documento normativo do tema explicitamente citado na pergunta; não atribuir automaticamente uma das 11 políticas essenciais. | G31: 1.2 | H31: AG-FCG-QPE-040 | I31: RISCOS_TERCEIROS | J31: Desenho | K31: VIGENTE | M31: ISO-07 | N31: V
A32: QPE-045 | B32: 6.3.4 | C32: Pró-Ética | D32: Gestão de Riscos para a Integridade | E32: A análise de riscos para a integridade realizada contempla: As medidas de contingência para o caso de concretização dos riscos? | F32: Política ou planejamento da empresa, aprovado(s) pela alta direção, que trate da gestão de riscos e que defina a metodologia de análise de riscos, contendo: o plano de contingência para o caso de concretização dos riscos.; | G32: 0.5 | H32: AG-FCG-QPE-045 | I32: RISCOS_TERCEIROS | J32: Execução | K32: PERIODO | M32: ISO-07; ISO-17 | N32: V
A33: QPE-046 | B33: 6.3.5 | C33: Pró-Ética | D33: Gestão de Riscos para a Integridade | E33: A análise de riscos para a integridade realizada contempla: os riscos para a integridade relacionados às atividades de suas controladas/subsidiárias, se for o caso? | F33: Política ou planejamento da empresa, aprovado(s) pela alta direção, que trate da gestão de riscos e que defina a metodologia de análise de riscos, contendo: a identificação dos riscos de integridade associados às atividades das controladas ou subsidiárias, relacionadas à corrupção e fraude; | G33: 1 | H33: AG-FCG-QPE-046 | I33: RISCOS_TERCEIROS | J33: Execução | K33: PERIODO | M33: ISO-07; ISO-35 | N33: V
A34: QPE-047 | B34: 6.3.6 | C34: Pró-Ética | D34: Gestão de Riscos para a Integridade | E34: A análise de riscos para a integridade realizada contempla: A aprovação pela alta direção da empresa? | F34: Política ou planejamento da empresa, aprovado(s) pela alta direção, que trate da gestão de riscos e que defina a metodologia de análise de riscos, contendo: Documentos como atas de reunião e relatórios formalmente homologados, que indicam a aprovação pela alta direção da empresa; | G34: 1 | H34: AG-FCG-QPE-047 | I34: RISCOS_TERCEIROS | J34: Execução | K34: PERIODO | M34: ISO-07 | N34: V
A35: QPE-048 | B35: 6.3.7 | C35: Pró-Ética | D35: Gestão de Riscos para a Integridade | E35: A análise de riscos para a integridade realizada contempla: A participação da área responsável pelo programa de integridade na análise do risco priorizado. | F35: Política ou planejamento da empresa, aprovado(s) pela alta direção, que trate da gestão de riscos e que defina a metodologia de análise de riscos, contendo: Documentos como atas de reunião e relatório que indicam a participação da área responsável pelo programa de integridade análise do risco priorizado; apetite ao risco; estratégia utilizada para cada | G35: 0.6 | H35: AG-FCG-QPE-048 | I35: RISCOS_TERCEIROS | J35: Execução | K35: PERIODO | M35: ISO-07 | N35: V
A36: QPE-049 | B36: 6.4 | C36: Pró-Ética | D36: Gestão de Riscos para a Integridade | E36: No período avaliado, a empresa identificou e tratou riscos relacionados à violação dos direitos humanos? | F36: Exemplos de processos reais como matriz de risco, relatórios, plano de gestão, que identificou e tratou os riscos à violação dos direitos humanos; | G36: 0.1 | H36: AG-FCG-QPE-049 | I36: RISCOS_TERCEIROS | J36: Execução | K36: PERIODO
A37: QPE-054 | B37: 7.2.3 | C37: Pró-Ética | D37: Código de Ética, Políticas e Procedimentos | E37: O Código de Ética e Conduta, ou documento equivalente, apresentado: está alinhado às especificidades da empresa, como áreas de atuação e grau de interação com a Administração Pública? (questão direcionada ao avaliador) | F37: POL-01 — Código de Ética | G37: 0.4 | H37: AG-FCG-QPE-054 | I37: NORMATIVO | J37: Avaliador | N37: II
A38: QPE-057 | B38: 7.2.6 | C38: Pró-Ética | D38: Código de Ética, Políticas e Procedimentos | E38: O Código de Ética e Conduta, ou documento equivalente, apresentado: indica expressamente os responsáveis por dirimir dúvidas sobre sua aplicação? | F38: Indicar a seção e a página do Código de Ética e Conduta ou documento equivalente onde conste expressamente os responsáveis por dirimir dúvidas sobre sua aplicação.; POL-01 — Código de Ética | G38: 0.1 | H38: AG-FCG-QPE-057 | I38: NORMATIVO | J38: Desenho | K38: VIGENTE | N38: II
A39: QPE-058 | B39: 7.2.7 | C39: Pró-Ética | D39: Código de Ética, Políticas e Procedimentos | E39: O Código de Ética e Conduta, ou documento equivalente, apresentado: indica expressamente a existência e a forma de acesso dos canais para realização de denúncias de violações éticas/legais? | F39: Indicar a seção e a página do Código de Ética e Conduta ou documento equivalente onde são informados os canais de denúncia para violações éticas ou legais e como acessá-los.; POL-01 — Código de Ética | G39: 0.3 | H39: AG-FCG-QPE-058 | I39: NORMATIVO | J39: Desenho | K39: VIGENTE | M39: ISO-39 | N39: II; X
A40: QPE-059 | B40: 7.2.8 | C40: Pró-Ética | D40: Código de Ética, Políticas e Procedimentos | E40: O Código de Ética e Conduta, ou documento equivalente, apresentado: prevê expressamente as garantias para proteção do denunciante de boa-fé? | F40: Indicar a seção e a página do Código de Ética e Conduta ou documento equivalente onde se prevê expressamente as garantias para proteção do denunciante de boa-fé.; POL-01 — Código de Ética | G40: 0.3 | H40: AG-FCG-QPE-059 | I40: NORMATIVO | J40: Desenho | K40: VIGENTE | M40: ISO-12; ISO-24; ISO-39 | N40: II; X
A41: QPE-060 | B41: 7.2.9 | C41: Pró-Ética | D41: Código de Ética, Políticas e Procedimentos | E41: O Código de Ética e Conduta, ou documento equivalente, apresentado: expressa o compromisso da empresa em combater o preconceito, a discriminação e o assédio de qualquer natureza em suas relações internas e externas? | F41: Indicar a seção e a página do Código de Ética e Conduta ou documento equivalente onde a empresa reafirma seu compromisso contra o preconceito, a discriminação e o assédio em todas as suas relações.; POL-01 — Código de Ética | G41: 0.1 | H41: AG-FCG-QPE-060 | I41: NORMATIVO | J41: Desenho | K41: VIGENTE | N41: II
A42: QPE-063 | B42: 7.2.12 | C42: Pró-Ética | D42: Código de Ética, Políticas e Procedimentos | E42: O Código de Ética e Conduta, ou documento equivalente, apresentado: possui uma linguagem clara e de fácil compreensão? (questão direcionada ao avaliador) | F42: POL-01 — Código de Ética | G42: 0.1 | H42: AG-FCG-QPE-063 | I42: NORMATIVO | J42: Avaliador | N42: II
A43: QPE-064 | B43: 7.2.13 | C43: Pró-Ética | D43: Código de Ética, Políticas e Procedimentos | E43: O Código de Ética e Conduta, ou documento equivalente, apresentado: possui versão nos principais idiomas dos demais países em que a empresa atua? | F43: Evidência que informa tanto o link de acesso quanto o caminho da página inicial do site da empresa até o Código de Ética e Conduta ou documento equivalente nos principais idiomas dos demais países que a empresa atua.; POL-01 — Código de Ética | G43: 0.1 | H43: AG-FCG-QPE-064 | I43: NORMATIVO | J43: Desenho | K43: VIGENTE | N43: II
A44: QPE-065 | B44: 7.2.14 | C44: Pró-Ética | D44: Código de Ética, Políticas e Procedimentos | E44: O Código de Ética e Conduta, ou documento equivalente, apresentado: pode ser facilmente acessado pelos empregados da empresa, incluindo aqueles que não possuem acesso a computadores, se for o caso? | F44: Evidência que forneça o link e o caminho detalhado para acesso ao Código de Ética e Conduta ou equivalente no site da empresa. Caso alguns colaboradores não tenham internet no trabalho, enviar comprovação visual (fotos, vídeos) que demonstre a presença do Código impresso nos espaços físicos da organização.; POL-01 — Código de Ética | G44: 0.4 | H44: AG-FCG-QPE-065 | I44: NORMATIVO | J44: Desenho | K44: VIGENTE | M44: ISO-27 | N44: II
A45: QPE-224 | B45: 7.4 | C45: Pró-Ética | D45: Código de Ética, Políticas e Procedimentos | E45: A empresa exige que seus empregados declarem expressamente ciência do Código de Ética e compromisso de observá-lo? | F45: Atestes ou declarações de ciência, assinados pelos empregados; especificar como e quando são obtidos.; POL-01 — Código de Ética | G45: 0.4 | H45: AG-FCG-QPE-224 | I45: NORMATIVO | J45: Execução | K45: PERIODO | M45: ISO-15; ISO-22; ISO-27 | N45: II
A46: QPE-067 | B46: 8.1 | C46: Pró-Ética | D46: Código de Ética, Políticas e Procedimentos | E46: Código de Ética e Conduta aplicável a terceiros: A empresa possui Código de Ética e Conduta, ou documento equivalente, aplicável a terceiros e disponível em português? | F46: Código de Ética e Conduta da empresa ou documento equivalente aplicável a terceiros, em português. Caso seja parte do Código de Ética geral da empresa, devem ser apresentadas seções específicas para terceiros. Referências genéricas no Código de Conduta geral não serão aceitas.; POL-01 — Código de Ética | POL-06 — Due Diligence de Terceiros | G46: 0.1 | H46: AG-FCG-QPE-067 | I46: RISCOS_TERCEIROS | J46: Desenho | K46: VIGENTE | M46: ISO-35 | N46: III
A47: QPE-068 | B47: 8.2.1 | C47: Pró-Ética | D47: Código de Ética, Políticas e Procedimentos | E47: O Código de Ética e Conduta da empresa ou documento equivalente aplicável a terceiros: proíbe expressamente a prática de corrupção e outros atos lesivos à Administração Pública por parte dos terceiros? | F47: Seção e a página do Código de Ética e Conduta aplicável a terceiros ou documento equivalente onde se proíbe expressamente a prática de corrupção e outros atos lesivos à Administração Pública.; POL-01 — Código de Ética | POL-06 — Due Diligence de Terceiros | G47: 0.2 | H47: AG-FCG-QPE-068 | I47: RISCOS_TERCEIROS | J47: Desenho | K47: VIGENTE | M47: ISO-35 | N47: III
A48: QPE-069 | B48: 8.2.2 | C48: Pró-Ética | D48: Código de Ética, Políticas e Procedimentos | E48: O Código de Ética e Conduta da empresa ou documento equivalenteaplicável a terceiros: indica expressamente a existência e a forma de acesso dos canais para realização de denúncias de violações éticas/legais para os terceiros? | F48: Seção e a página do Código de Ética e Conduta para terceiros ou documento equivalente onde são mencionados os canais disponíveis para denúncias de violações éticas/legais.; POL-01 — Código de Ética | POL-06 — Due Diligence de Terceiros | G48: 0.3 | H48: AG-FCG-QPE-069 | I48: RISCOS_TERCEIROS | J48: Desenho | K48: VIGENTE | M48: ISO-35 | N48: III
A49: QPE-070 | B49: 8.2.3 | C49: Pró-Ética | D49: Código de Ética, Políticas e Procedimentos | E49: O Código de Ética e Conduta da empresa ou documento equivalente aplicável a terceiros: menciona a possibilidade de aplicação de sanções para os terceiros que cometerem violações éticas/legais? | F49: Seção e a página do Código de Ética e Conduta para terceiros ou documento equivalente que trata das sanções previstas a terceiros em caso de violações éticas ou legais.; POL-01 — Código de Ética | POL-06 — Due Diligence de Terceiros | G49: 0.3 | H49: AG-FCG-QPE-070 | I49: RISCOS_TERCEIROS | J49: Desenho | K49: VIGENTE | M49: ISO-35 | N49: III
A50: QPE-071 | B50: 8.3 | C50: Pró-Ética | D50: Código de Ética, Políticas e Procedimentos | E50: A empresa disponibiliza esse documento em sua página eletrônica ou informa como ele pode ser acessado por esses terceiros? | F50: Informar tanto o link de acesso quanto o caminho da página inicial do site da empresa até o Código de Ética e Conduta para terceiros ou documento equivalente.; POL-01 — Código de Ética | POL-06 — Due Diligence de Terceiros | G50: 0.2 | H50: AG-FCG-QPE-071 | I50: RISCOS_TERCEIROS | J50: Publicação | K50: VIGENTE | M50: ISO-28 | N50: III
A51: QPE-077 | B51: 9.1.5 | C51: Pró-Ética | D51: Código de Ética, Políticas e Procedimentos | E51: A empresa possui políticas e procedimentos de integridade que: estabelecem orientações para que seus administradores, empregados ou terceiros, agindo em nome da empresa, cooperem com eventuais investigações e fiscalizações realizadas por órgãos, entidades ou agentes públicos? | F51: estabelecem diretrizes para que administradores, empregados ou terceiros, em nome da empresa, colaborem com investigações e fiscalizações conduzidas por órgãos, entidades ou agentes públicos; 9.1.6 abordam a realização de doações e patrocínios ou que deixam claro que a empresa não realiza essas atividades;; POL-04 — Doações, Patrocínios e Contribuições | POL-05 — Relacionamento com o Setor Público | POL-06 — Due Diligence de Terceiros | POL-10 — Investigações e Medidas Disciplinares | G51: 0.4 | H51: AG-FCG-QPE-077 | I51: RISCOS_TERCEIROS | J51: Desenho | K51: VIGENTE | M51: ISO-31 | N51: VIII | O51: Sim
A52: QPE-079 | B52: 9.2.1 | C52: Pró-Ética | D52: Código de Ética, Políticas e Procedimentos | E52: As políticas e procedimentos de integridade apresentados: são proporcionais ao perfil da empresa e aos riscos a que está submetida? (questão direcionada ao avaliador) | F52: Informação não especificada na fonte; pendente de confirmação por pergunta. | G52: 0.4 | H52: AG-FCG-QPE-079 | I52: RISCOS_TERCEIROS | J52: Avaliador | M52: ISO-05; ISO-31 | N52: II
A53: QPE-080 | B53: 9.2.2 | C53: Pró-Ética | D53: Código de Ética, Políticas e Procedimentos | E53: As políticas e procedimentos de integridade apresentados: são operacionais e contam com mecanismos que visem sua aplicação, isto é, não são apenas documentos principiológicos? (questão direcionada ao avaliador) | F53: Informação não especificada na fonte; pendente de confirmação por pergunta. | G53: 0.6 | H53: AG-FCG-QPE-080 | I53: NORMATIVO | J53: Avaliador | M53: ISO-05; ISO-30; ISO-31 | N53: II
A54: QPE-081 | B54: 9.2.3 | C54: Pró-Ética | D54: Código de Ética, Políticas e Procedimentos | E54: As políticas e procedimentos de integridade apresentados: indicam os responsáveis por sua aplicação e monitoramento? Se sim, esclarecer se é utilizado algum sistema/software na aplicação e controle dessas políticas e procedimentos. | F54: Evidência que indique a seção e a página das políticas, regras, orientações ou procedimentos que apontam os responsáveis pela aplicação e monitoramento. Caso exista, apresentar evidências de sistemas ou softwares utilizados para a gestão e controle dessas políticas e procedimentos. | G54: 0.4 | H54: AG-FCG-QPE-081 | I54: NORMATIVO | J54: Desenho | K54: VIGENTE | M54: ISO-13; ISO-15; ISO-31 | N54: II
A55: QPE-082 | B55: 9.2.4 | C55: Pró-Ética | D55: Código de Ética, Políticas e Procedimentos | E55: estão disponíveis em português e podem ser facilmente acessados pelos empregados da empresa? | F55: Informar tanto o link de acesso quanto o caminho da página inicial do site/intranet da empresa até o documento. No caso de colaboradores sem acesso à internet no local de trabalho, enviar vídeos, imagens etc. que comprovem a disponibilização do Código impresso nos ambientes físicos em que estes colaboradores atuam. | G55: 0.6 | H55: AG-FCG-QPE-082 | I55: PUBLICACAO_COMUNICACAO | J55: Desenho | K55: VIGENTE | M55: ISO-12 | N55: II
A56: QPE-085 | B56: 10.1.1 | C56: Pró-Ética | D56: Código de Ética, Políticas e Procedimentos | E56: A empresa possui políticas e procedimentos relacionados à sua participação em licitações e à celebração de contratos administrativos que: determinam o mapeamento prévio dos riscos para integridade existentes na sua participação em licitação e na celebração de contrato administrativo? | F56: Evidência que indique a seção e a página das políticas, regras, orientações ou procedimentos que: estabeleçam o mapeamento prévio dos riscos de integridade associados à participação em licitações e à formalização de contratos administrativo; | G56: 0.1 | H56: AG-FCG-QPE-085 | I56: RISCOS_TERCEIROS | J56: Desenho | K56: VIGENTE | M56: ISO-34 | N56: VIII | O56: Sim
A57: QPE-086 | B57: 10.1.2 | C57: Pró-Ética | D57: Código de Ética, Políticas e Procedimentos | E57: A empresa possui políticas e procedimentos relacionados à sua participação em licitações e à celebração de contratos administrativos que: determinam a verificação prévia da capacidade da empresa de atender plenamente as condições exigidas para a licitação e para execução do contrato? | F57: Evidência que indique a seção e a página das políticas, regras, orientações ou procedimentos que: estabeleçam a verificação prévia da capacidade da empresa de atender às condições exigidas para a licitação e a execução do contrato administrativo; | G57: 0.1 | H57: AG-FCG-QPE-086 | I57: NORMATIVO | J57: Desenho | K57: VIGENTE | M57: ISO-34 | N57: VIII | O57: Sim
A58: QPE-087 | B58: 10.1.3 | C58: Pró-Ética | D58: Código de Ética, Políticas e Procedimentos | E58: A empresa possui políticas e procedimentos relacionados à sua participação em licitações e à celebração de contratos administrativos que: determinam a transparência e disponibilização, em sua página eletrônica, de informações sobre sua participação em licitações e celebração de contratos administrativos? | F58: Evidência que indique a seção e a página das políticas, regras, orientações ou procedimentos que: tratam da transparência e da disponibilização de informações sobre participação em licitações e contratos administrativos no site da empresa; | G58: 0.5 | H58: AG-FCG-QPE-087 | I58: PUBLICACAO_COMUNICACAO | J58: Publicação | K58: VIGENTE | M58: ISO-34 | N58: VIII | O58: Sim
A59: QPE-088 | B59: 10.2.1 | C59: Pró-Ética | D59: Código de Ética, Políticas e Procedimentos | E59: Em relação ao processo licitatório, a empresa, na condição de participante de licitações, possui políticas e procedimentos que: estabelecem orientações sobre a conduta esperada (o que é permitido/proibido) para os seus empregados? | F59: estabelecem diretrizes claras sobre a conduta esperada dos empregados, especificando ações permitidas e proibidas; | G59: 0.2 | H59: AG-FCG-QPE-088 | I59: NORMATIVO | J59: Desenho | K59: VIGENTE | M59: ISO-34 | N59: VIII | O59: Sim
A60: QPE-089 | B60: 10.2.2 | C60: Pró-Ética | D60: Código de Ética, Políticas e Procedimentos | E60: Em relação ao processo licitatório, a empresa, na condição de participante de licitações, possui políticas e procedimentos que: estabelecem orientações sobre a conduta esperada (o que é permitido/proibido) para os terceiros que atuam em seu nome? | F60: estabelecem diretrizes claras sobre a conduta esperada dos terceiros que atuam em seu nome, especificando ações permitidas e proibidas;; POL-06 — Due Diligence de Terceiros | G60: 0.3 | H60: AG-FCG-QPE-089 | I60: RISCOS_TERCEIROS | J60: Desenho | K60: VIGENTE | M60: ISO-34 | N60: VIII | O60: Sim
A61: QPE-090 | B61: 10.2.3 | C61: Pró-Ética | D61: Código de Ética, Políticas e Procedimentos | E61: Em relação ao processo licitatório, a empresa, na condição de participante de licitações, possui políticas e procedimentos que: indicam expressamente os responsáveis por autorizar a adoção de medidas relacionadas à participação em licitações? | F61: indicam expressamente os responsáveis pela autorização de medidas vinculadas à participação da empresa em licitações; | G61: 0.5 | H61: AG-FCG-QPE-090 | I61: NORMATIVO | J61: Desenho | K61: VIGENTE | M61: ISO-34 | N61: VIII | O61: Sim
A62: QPE-091 | B62: 10.2.4 | C62: Pró-Ética | D62: Código de Ética, Políticas e Procedimentos | E62: Em relação ao processo licitatório, a empresa, na condição de participante de licitações, possui políticas e procedimentos que: proíbem expressamente a combinação de preços ou condições de proposta de licitação com concorrentes? | F62: proíbem expressamente a combinação de preços ou condições de proposta de licitação com concorrentes; | G62: 0.1 | H62: AG-FCG-QPE-091 | I62: NORMATIVO | J62: Desenho | K62: VIGENTE | M62: ISO-34 | N62: VIII | O62: Sim
A63: QPE-092 | B63: 10.2.5 | C63: Pró-Ética | D63: Código de Ética, Políticas e Procedimentos | E63: orientam a relação da empresa com seus concorrentes, a fim de evitar práticas anticoncorrenciais que possibilitem fraude em processos licitatórios? | F63: estabelecem diretrizes para a relação da empresa com concorrentes, prevenindo práticas anticoncorrenciais e coibindo fraudes em processos licitatórios; | G63: 0.5 | H63: AG-FCG-QPE-092 | I63: EXECUCAO_CONTROLE | J63: Desenho | K63: VIGENTE | M63: ISO-34 | N63: VIII | O63: Sim
A64: QPE-094 | B64: 10.3.2 | C64: Pró-Ética | D64: Código de Ética, Políticas e Procedimentos | E64: Em relação à gestão e à execução do contrato administrativo, a empresa, na condição de contratada, possui políticas e procedimentos que: estabelecem orientações sobre a conduta esperada (o que é permitido/proibido) para os terceiros que atuam em seu nome? | F64: Evidência que indique a seção e a página das políticas, regras, orientações ou procedimentos que: estabelecem diretrizes claras sobre a conduta esperada dos terceiros que atuam em seu nome, especificando ações permitidas e proibidas;; POL-06 — Due Diligence de Terceiros | G64: 0.3 | H64: AG-FCG-QPE-094 | I64: RISCOS_TERCEIROS | J64: Desenho | K64: VIGENTE | M64: ISO-34 | N64: VIII | O64: Sim
A65: QPE-095 | B65: 10.3.3 | C65: Pró-Ética | D65: Código de Ética, Políticas e Procedimentos | E65: Em relação à gestão e à execução do contrato administrativo, a empresa, na condição de contratada, possui políticas e procedimentos que: definem os responsáveis pela interação com os agentes públicos para tratar de questões relacionadas à gestão do contrato, como pagamento, alterações contratuais, aditivos e prorrogações? | F65: Evidência que indique a seção e a página das políticas, regras, orientações ou procedimentos que: estabelecem diretrizes que designam os responsáveis pela comunicação com agentes públicos sobre gestão contratual, incluindo pagamentos, ajustes, aditivos e prorrogações;; POL-05 — Relacionamento com o Setor Público | POL-07 — Compras e Pagamentos | G65: 0.5 | H65: AG-FCG-QPE-095 | I65: PUBLICACAO_COMUNICACAO | J65: Desenho | K65: VIGENTE | M65: ISO-34 | N65: VIII | O65: Sim
A66: QPE-096 | B66: 10.3.4 | C66: Pró-Ética | D66: Código de Ética, Políticas e Procedimentos | E66: Em relação à gestão e à execução do contrato administrativo, a empresa, na condição de contratada, possui políticas e procedimentos que: preveem a rotatividade dos responsáveis por interagir com os agentes públicos durante a execução de contrato, a depender do prazo de vigência da contratação? | F66: Evidência que indique a seção e a página das políticas, regras, orientações ou procedimentos que: estabelecem a alternância dos responsáveis pela comunicação com agentes públicos ao longo da execução do contrato, considerando seu prazo de vigência;; POL-05 — Relacionamento com o Setor Público | G66: 0.1 | H66: AG-FCG-QPE-096 | I66: PUBLICACAO_COMUNICACAO | J66: Desenho | K66: VIGENTE | M66: ISO-34 | N66: VIII | O66: Sim
A67: QPE-097 | B67: 10.3.5 | C67: Pró-Ética | D67: Código de Ética, Políticas e Procedimentos | E67: Em relação à gestão e à execução do contrato administrativo, a empresa, na condição de contratada, possui políticas e procedimentos que: estabelecem as alçadas internas relacionadas à gestão do contrato a depender da complexidade ou do risco da questão a ser tratada? | F67: Evidência que indique a seção e a página das políticas, regras, orientações ou procedimentos que: determinam as alçadas internas na gestão contratual, ajustando níveis de decisão conforme a complexidade ou o risco envolvido; | G67: 0.1 | H67: AG-FCG-QPE-097 | I67: RISCOS_TERCEIROS | J67: Desenho | K67: VIGENTE | M67: ISO-34 | N67: VIII | O67: Sim
... A69: QPE-099 | B69: 10.4 | C69: Pró-Ética | D69: Código de Ética, Políticas e Procedimentos | E69: A empresa aplicou, no período avaliado, as políticas e procedimentos adotados para prevenção de ilícitos em licitações e contratos administrativos, na condição de participante de licitações e de contratada? | F69: Exemplos de processos reais contendo: matriz de riscos, atas de reuniões, aprovações, e-mails e documentos da alta direção que comprovem a aplicação das políticas de prevenção a ilícitos em licitações e contratos administrativos, incluindo ações implementadas e resultados para empregados e terceiros.; POL-06 — Due Diligence de Terceiros | G69: 3 | H69: AG-FCG-QPE-099 | I69: RISCOS_TERCEIROS | J69: Execução | K69: PERIODO | M69: ISO-30; ISO-34 | N69: VIII | O69: Sim
A70: QPE-100 | B70: 11.1.1 | C70: Pró-Ética | D70: Treinamento e Comunicação | E70: A empresa possui um planejamento para realização de treinamentos relacionados ao programa de integridade contendo: cronograma de realização dos treinamentos? | F70: Documento formal em que conste o planejamento das atividades de treinamentos relacionadas à integridade para determinado período (anual, geralmente). O documento deve elencar: o cronograma previsto para a realização dos treinamentos | G70: 0.2 | H70: AG-FCG-QPE-100 | I70: TREINAMENTO | J70: Desenho | K70: VIGENTE | M70: ISO-26 | N70: IV
A71: QPE-101 | B71: 11.1.2 | C71: Pró-Ética | D71: Treinamento e Comunicação | E71: A empresa possui um planejamento para realização de treinamentos relacionados ao programa de integridade contendo: a identificação da área ou pessoa responsável pela execução e supervisão dos treinamentos? | F71: Documento formal em que conste o planejamento das atividades de treinamentos relacionadas à integridade para determinado período (anual, geralmente). O documento deve elencar: a área ou responsável designado para a execução e supervisão dos treinamentos; | G71: 0.2 | H71: AG-FCG-QPE-101 | I71: TREINAMENTO | J71: Desenho | K71: VIGENTE | M71: ISO-26 | N71: IV
A72: QPE-102 | B72: 11.1.3 | C72: Pró-Ética | D72: Treinamento e Comunicação | E72: A empresa possui um planejamento para realização de treinamentos relacionados ao programa de integridade contendo: os temas e as modalidades de realização dos treinamentos? | F72: Documento formal em que conste o planejamento das atividades de treinamentos relacionadas à integridade para determinado período (anual, geralmente). O documento deve elencar: os temas (assuntos abordados) e a modalidade (presencial, on- line, híbrido) de realização dos treinamentos; | G72: 0.2 | H72: AG-FCG-QPE-102 | I72: TREINAMENTO | J72: Desenho | K72: VIGENTE | M72: ISO-26 | N72: IV
A73: QPE-104 | B73: 11.1.5 | C73: Pró-Ética | D73: Treinamento e Comunicação | E73: A empresa possui um planejamento para realização de treinamentos relacionados ao programa de integridade contendo: os controles que serão utilizados para verificar a participação dos públicos-alvo? | F73: Documento formal em que conste o planejamento das atividades de treinamentos relacionadas à integridade para determinado período (anual, geralmente). O documento deve elencar: os mecanismos de controle utilizados para registar e verificar a participação dos públicos-alvo; | G73: 0.1 | H73: AG-FCG-QPE-104 | I73: TREINAMENTO | J73: Desenho | K73: VIGENTE | M73: ISO-26 | N73: IV
A74: QPE-105 | B74: 11.1.6 | C74: Pró-Ética | D74: Treinamento e Comunicação | E74: A empresa possui um planejamento para realização de treinamentos relacionados ao programa de integridade contendo: os objetivos e metas relativos à realização dos treinamentos? | F74: Documento formal em que conste o planejamento das atividades de treinamentos relacionadas à integridade para determinado período (anual, geralmente). O documento deve elencar: Os objetivos e metas relativos à realização dos treinamentos. | G74: 0.5 | H74: AG-FCG-QPE-105 | I74: TREINAMENTO | J74: Desenho | K74: VIGENTE | M74: ISO-26 | N74: IV
A75: QPE-106 | B75: 11.2 | C75: Pró-Ética | D75: Treinamento e Comunicação | E75: A instância interna responsável pelo programa de integridade participa do planejamento, da elaboração, da aplicação ou da contratação dos treinamentos sobre temas de integridade? | F75: Documentos, atas de reuniões, estudos, relatórios, ou planos assinados, que demonstrem que a instância interna responsável pelo programa de integridade participa do planejamento, elaboração, aplicação e/ou contratação dos treinamentos sobre temas de integridade. | G75: 0.3 | H75: AG-FCG-QPE-106 | I75: TREINAMENTO | J75: Execução | K75: PERIODO | M75: ISO-26 | N75: IV
A76: QPE-108 | B76: 11.3.2 | C76: Pró-Ética | D76: Treinamento e Comunicação | E76: No período avaliado, a empresa realizou treinamentos: direcionados a todos os empregados, abordando temas relacionados com o combate ao preconceito, à discriminação e ao assédio de qualquer natureza? | F76: Listas de presenças acompanhadas de materiais de estudo, links de acesso a treinamentos online ou registros de frequência e participação que demonstrem: o treinamento geral dos colaboradores abordando temas relacionados com o combate ao preconceito, à discriminação e ao assédio de qualquer natureza; | G76: 0.1 | H76: AG-FCG-QPE-108 | I76: TREINAMENTO | J76: Execução | K76: PERIODO | M76: ISO-26 | N76: IV
A77: QPE-109 | B77: 11.3.3 | C77: Pró-Ética | D77: Treinamento e Comunicação | E77: No período avaliado, a empresa realizou treinamentos: direcionados a todos os empregados, abordando temas relacionados ao meio ambiente e mudanças climáticas? | F77: Listas de presenças acompanhadas de materiais de estudo, links de acesso a treinamentos online ou registros de frequência e participação que demonstrem: o treinamento geral dos colaboradores, ao meio ambiente e mudanças climáticas; | G77: 0.1 | H77: AG-FCG-QPE-109 | I77: TREINAMENTO | J77: Execução | K77: PERIODO | M77: ISO-26 | N77: IV
A78: QPE-110 | B78: 11.3.4 | C78: Pró-Ética | D78: Treinamento e Comunicação | E78: No período avaliado, a empresa realizou treinamentos: direcionados a públicos específicos, abordando conteúdo alinhado aos principais riscos daqueles públicos, como políticas de doação e patrocínio, política de licitação e contratos administrativos, controles contábeis e financeiros, realização de diligências para contratação e supervisão de terceiros? | F78: Listas de presenças acompanhadas de materiais de estudo, links de acesso a treinamentos online ou registros de frequência e participação que demonstrem: o treinamento de públicos expostos a riscos específicos, que demonstrem treinamento direcionado a públicos expostos a riscos específicos, com temas relevantes para cada área, como licitações, controles financeiros e diligências em contratações;; POL-04 — Doações, Patrocínios e Contribuições | POL-06 — Due Diligence de Terceiros | POL-08 — Registros Contábeis | G78: 0.6 | H78: AG-FCG-QPE-110 | I78: TREINAMENTO | J78: Execução | K78: PERIODO | M78: ISO-26 | N78: IV
A79: QPE-111 | B79: 11.3.5 | C79: Pró-Ética | D79: Treinamento e Comunicação | E79: No período avaliado, a empresa realizou treinamentos: direcionados aos membros da alta direção, abordando conteúdo compatível com os papéis das lideranças em relação ao programa de integridade? | F79: Listas de presenças acompanhadas de materiais de estudo, links de acesso a treinamentos online ou registros de frequência e participação que demonstrem: o treinamento a membros da alta direção com listas de presença (identificando claramente o nome e o cargo), materiais de estudo ou registros de frequência, que abordando suas responsabilidades e o papel estratégico no programa de integridade. | G79: 0.6 | H79: AG-FCG-QPE-111 | I79: TREINAMENTO | J79: Execução | K79: PERIODO | M79: ISO-26 | N79: IV
A80: QPE-113 | B80: 11.4.1 | C80: Pró-Ética | D80: Treinamento e Comunicação | E80: Os treinamentos realizados no período avaliado: contaram com a utilização de controles para verificar a participação dos públicos-alvo? | F80: Relatórios, listas de presença, registros em sistemas etc. que permitam controlar a participação dos públicos-alvo dos treinamentos. | G80: 0.1 | H80: AG-FCG-QPE-113 | I80: TREINAMENTO | J80: Execução | K80: PERIODO | M80: ISO-26; ISO-45 | N80: IV
A81: QPE-115 | B81: 11.4.3 | C81: Pró-Ética | D81: Treinamento e Comunicação | E81: Os treinamentos realizados no período avaliado: foram realizados de forma periódica? Relatórios ou outros registros históricos que demonstrem a frequência dos treinamentos realizados. | F81: Relatórios ou outros registros históricos que demonstrem a frequência dos treinamentos realizados. | G81: 0.6 | H81: AG-FCG-QPE-115 | I81: TREINAMENTO | J81: Execução | K81: PERIODO | M81: ISO-26; ISO-45 | N81: IV
... A87: QPE-121 | B87: 12.2 | C87: Pró-Ética | D87: Treinamento e Comunicação | E87: A instância interna responsável pelo programa de integridade participa do planejamento, elaboração, aplicação e/ou contratação das ações de comunicação sobre temas de integridade? | F87: Documentos como atas de reuniões, regimentos, políticas ou planos aprovados, que demonstrem o envolvimento da instância interna responsável pelo programa de integridade no planejamento, desenvolvimento e implementação das ações de comunicação sobre integridade, para o período avaliado. | G87: 0.3 | H87: AG-FCG-QPE-121 | I87: PUBLICACAO_COMUNICACAO | J87: Execução | K87: PERIODO | M87: ISO-28 | N87: IV
